Workbook

Sheet Dashboard
A1: ZATCA VAT Inspection Pack – Dashboard
A2: ="Company: "&Setup!B4&" | VAT No: "&Setup!B5&" | Period: "&TEXT(Setup!C19,"dd-mmm-yyyy")&" to "&TEXT(MAX(Setup!D19:D30),"dd-mmm-yyyy")&" | Filing: "&Setup!B8
A3: Indicator | B3: Value (SAR) | C3: Status | D3: What it means
A4: 1. Sales & Revenue
A5: Total sales per VAT returns (Box 6) | B5: =Recon_Sales!E88
A6: Revenue subject to VAT per Trial Balance | B6: =Recon_Sales!E87
A7: Unexplained revenue difference | B7: =Recon_Sales!E96 | C7: =IF(ABS(B7)<=Setup!$B$10,"✓ Reconciled","✗ Explain") | D7: ZATCA treats unexplained excess revenue as undeclared taxable sales
A8: Sales periods/boxes not matched | B8: =COUNTIF(Recon_Sales!H6:H17,"✗*")+COUNTIF(Recon_Sales!H22:H33,"✗*")+COUNTIF(Recon_Sales!H38:H49,"✗*")+COUNTIF(Recon_Sales!H54:H65,"✗*")+COUNTIF(Recon_Sales!H70:H81,"✗*") | C8: =IF(B8=0,"✓ None","✗ Review Recon_Sales")
A9: 2. Output VAT
A10: Output VAT per returns | B10: =Recon_OutputVAT!C17
A11: Output VAT per GL | B11: =Recon_OutputVAT!H17
A12: Potential under-declared output VAT | B12: =Recon_OutputVAT!M17 | C12: =IF(B12<=Setup!$B$10,"✓ None","✗ Exposure") | D12: Higher of register or GL above the return, per period
A13: 3. Input VAT
A14: Input VAT claimed per returns | B14: =Recon_InputVAT!C17
A15: Defensible input VAT per register | B15: =Recon_InputVAT!E17
A16: Potential over-claimed input VAT | B16: =Recon_InputVAT!K17 | C16: =IF(B16<=Setup!$B$10,"✓ None","✗ Exposure") | D16: Claimed in return but not supported by a valid, non-blocked invoice
A17: 4. VAT Account, Filing & Payment
A18: Returns filed late | B18: =COUNTIF(VAT_Returns!AT6:AT17,"✗*") | C18: =IF(B18=0,"✓ None","✗ Late")
A19: Return arithmetic errors | B19: =COUNTIF(VAT_Returns!AS6:AS17,"✗*") | C19: =IF(B19=0,"✓ None","✗ Check")
A20: VAT unpaid (outstanding) | B20: =Recon_VAT_Account!G18 | C20: =IF(B20<=Setup!$B$10,"✓ Settled","✗ Unpaid")
A21: GL VAT account periods not agreeing | B21: =COUNTIF(Recon_VAT_Account!O6:O17,"✗*") | C21: =IF(B21=0,"✓ None","✗ Investigate")
A22: Est. late payment penalties | B22: =Recon_VAT_Account!I18+Recon_VAT_Account!J18 | D22: 5% per month or part on late / unpaid tax
A23: 5. Data Quality
A24: Sales rows with exceptions | B24: =Sales_Register!B3 | C24: =IF(B24=0,"✓ Clean","✗ Review flags")
A25: Purchase rows with exceptions | B25: =Purchase_Register!B3 | C25: =IF(B25=0,"✓ Clean","✗ Review flags")
A26: TB months out of balance | B26: =COUNTIF(TB_Monthly!E3:S3,"<>0") | C26: =IF(B26=0,"✓ Balanced","✗ Fix TB")
A27: TB accounts without VAT mapping | B27: =SUMPRODUCT((TB_Monthly!A6:A505<>"")*(TB_Monthly!D6:D505="")) | C27: =IF(B27=0,"✓ All mapped","✗ Map accounts")
A28: Document checklist readiness | B28: =Checklist!F3 | C28: =IF(B28>=1,"✓ Ready","✗ Incomplete")
A29: 6. Indicative Exposure (before objection / penalty relief)
A30: Tax exposure (under-declared + over-claimed + unexplained revenue × rate) | B30: =B12+B16+MAX(0,B7)*Setup!$B$9 | D30: Unexplained revenue (TB > returns) × 15%. Indicative only
A31: Incorrect-return penalty on tax exposure | B31: =B30*Setup!$B$13 | D31: Art. 42 – 50% of the difference (indicative)
A32: Late payment penalties (est.) | B32: =B22
A33: TOTAL INDICATIVE EXPOSURE | B33: =B30+B31+B22 | C33: =IF(B33<=Setup!$B$10,"✓ Low risk","✗ Prepare defence / consider voluntary disclosure")
A35: Legend: yellow cells with blue text = inputs · grey = formulas · green text = links to other sheets · ✓ = OK · ✗ = needs action. All amounts in SAR. Example rows (Jan 2025) are included to show the format – overwrite them with your data.

Sheet Setup
A1: Setup – Company & Audit Period
A2: Yellow cells with blue text are inputs. Everything else in the workbook is driven by these settings.
A3: Setting | B3: Value | C3: Check / Note
A4: Company Name (اسم المنشأة) | B4: Example Trading Company | C4: Your legal name as on the VAT certificate
A5: VAT Registration No (الرقم الضريبي) | B5: 300000000000003 | C5: =IF(AND(LEN(B5)=15,LEFT(B5,1)="3",RIGHT(B5,1)="3",ISNUMBER(--B5)),"✓ Valid format","✗ Invalid VAT number format")
A6: Commercial Registration No | B6: 1010000000
A7: Fiscal Year Start (audit year) | B7: 45658 | C7: First day of the year under inspection
A8: Filing Frequency | B8: Monthly | C8: Monthly if taxable supplies > SAR 40M/yr, otherwise Quarterly
A9: Standard VAT Rate | B9: 0.15 | C9: 15% since 1 July 2020
A10: Variance Tolerance (SAR) | B10: 10 | C10: Differences within this amount are treated as rounding
A11: As-of Date (for penalty estimates) | B11: 46299 | C11: Usually today's date or the inspection date
A12: Late Payment Penalty (per month or part) | B12: 0.05 | C12: VAT Law Art. 43 – verify current rule
A13: Incorrect Return Penalty (% of difference) | B13: 0.5 | C13: VAT Law Art. 42 – indicative, verify current rule
A14: Periods in Year (calc) | B14: =IF(B8="Monthly",12,4)
A15: Months per Period (calc) | B15: =12/B14
A17: Tax Periods (auto-generated from the settings above)
A18: Period # | B18: Period Label | C18: Start Date | D18: End Date | E18: Return & Payment Due Date
A19: 1 | B19: =IF(C19="","",IF($B$8="Monthly",TEXT(C19,"mmm yyyy"),"Q"&A19&" "&TEXT(C19,"yyyy"))) | C19: =IF(A19>$B$14,"",EDATE($B$7,(A19-1)*$B$15)) | D19: =IF(C19="","",EDATE(C19,$B$15)-1) | E19: =IF(D19="","",EOMONTH(D19,1))
A20: 2 | B20: =IF(C20="","",IF($B$8="Monthly",TEXT(C20,"mmm yyyy"),"Q"&A20&" "&TEXT(C20,"yyyy"))) | C20: =IF(A20>$B$14,"",EDATE($B$7,(A20-1)*$B$15)) | D20: =IF(C20="","",EDATE(C20,$B$15)-1) | E20: =IF(D20="","",EOMONTH(D20,1))
A21: 3 | B21: =IF(C21="","",IF($B$8="Monthly",TEXT(C21,"mmm yyyy"),"Q"&A21&" "&TEXT(C21,"yyyy"))) | C21: =IF(A21>$B$14,"",EDATE($B$7,(A21-1)*$B$15)) | D21: =IF(C21="","",EDATE(C21,$B$15)-1) | E21: =IF(D21="","",EOMONTH(D21,1))
A22: 4 | B22: =IF(C22="","",IF($B$8="Monthly",TEXT(C22,"mmm yyyy"),"Q"&A22&" "&TEXT(C22,"yyyy"))) | C22: =IF(A22>$B$14,"",EDATE($B$7,(A22-1)*$B$15)) | D22: =IF(C22="","",EDATE(C22,$B$15)-1) | E22: =IF(D22="","",EOMONTH(D22,1))
A23: 5 | B23: =IF(C23="","",IF($B$8="Monthly",TEXT(C23,"mmm yyyy"),"Q"&A23&" "&TEXT(C23,"yyyy"))) | C23: =IF(A23>$B$14,"",EDATE($B$7,(A23-1)*$B$15)) | D23: =IF(C23="","",EDATE(C23,$B$15)-1) | E23: =IF(D23="","",EOMONTH(D23,1))
A24: 6 | B24: =IF(C24="","",IF($B$8="Monthly",TEXT(C24,"mmm yyyy"),"Q"&A24&" "&TEXT(C24,"yyyy"))) | C24: =IF(A24>$B$14,"",EDATE($B$7,(A24-1)*$B$15)) | D24: =IF(C24="","",EDATE(C24,$B$15)-1) | E24: =IF(D24="","",EOMONTH(D24,1))
A25: 7 | B25: =IF(C25="","",IF($B$8="Monthly",TEXT(C25,"mmm yyyy"),"Q"&A25&" "&TEXT(C25,"yyyy"))) | C25: =IF(A25>$B$14,"",EDATE($B$7,(A25-1)*$B$15)) | D25: =IF(C25="","",EDATE(C25,$B$15)-1) | E25: =IF(D25="","",EOMONTH(D25,1))
A26: 8 | B26: =IF(C26="","",IF($B$8="Monthly",TEXT(C26,"mmm yyyy"),"Q"&A26&" "&TEXT(C26,"yyyy"))) | C26: =IF(A26>$B$14,"",EDATE($B$7,(A26-1)*$B$15)) | D26: =IF(C26="","",EDATE(C26,$B$15)-1) | E26: =IF(D26="","",EOMONTH(D26,1))
A27: 9 | B27: =IF(C27="","",IF($B$8="Monthly",TEXT(C27,"mmm yyyy"),"Q"&A27&" "&TEXT(C27,"yyyy"))) | C27: =IF(A27>$B$14,"",EDATE($B$7,(A27-1)*$B$15)) | D27: =IF(C27="","",EDATE(C27,$B$15)-1) | E27: =IF(D27="","",EOMONTH(D27,1))
A28: 10 | B28: =IF(C28="","",IF($B$8="Monthly",TEXT(C28,"mmm yyyy"),"Q"&A28&" "&TEXT(C28,"yyyy"))) | C28: =IF(A28>$B$14,"",EDATE($B$7,(A28-1)*$B$15)) | D28: =IF(C28="","",EDATE(C28,$B$15)-1) | E28: =IF(D28="","",EOMONTH(D28,1))
A29: 11 | B29: =IF(C29="","",IF($B$8="Monthly",TEXT(C29,"mmm yyyy"),"Q"&A29&" "&TEXT(C29,"yyyy"))) | C29: =IF(A29>$B$14,"",EDATE($B$7,(A29-1)*$B$15)) | D29: =IF(C29="","",EDATE(C29,$B$15)-1) | E29: =IF(D29="","",EOMONTH(D29,1))
A30: 12 | B30: =IF(C30="","",IF($B$8="Monthly",TEXT(C30,"mmm yyyy"),"Q"&A30&" "&TEXT(C30,"yyyy"))) | C30: =IF(A30>$B$14,"",EDATE($B$7,(A30-1)*$B$15)) | D30: =IF(C30="","",EDATE(C30,$B$15)-1) | E30: =IF(D30="","",EOMONTH(D30,1))

Sheet Checklist
A1: Document Request Checklist (قائمة المستندات المطلوبة)
A2: Typical documents ZATCA requests in a VAT inspection. Track status, owner and file reference for each.
E3: Readiness: | F3: =(COUNTIF(G5:G42,"Ready")+COUNTIF(G5:G42,"Submitted")+COUNTIF(G5:G42,"N/A"))/COUNTA(G5:G42)
A4: # | B4: Area | C4: Document / Analysis Requested | D4: Prepared in this workbook? | E4: Owner | F4: Due Date | G4: Status | H4: File Ref / Location | I4: Notes
A5: 1 | B5: General | C5: VAT registration certificate, Commercial Registration, Articles of Association | G5: Not started
A6: 2 | B6: General | C6: Description of business activities and revenue streams + VAT treatment memo for each | G6: Not started
A7: 3 | B7: General | C7: List of branches, related parties and VAT group members (if any) | G7: Not started
A8: 4 | B8: General | C8: Chart of accounts with VAT mapping | D8: TB_Monthly col D | G8: Not started
A9: 5 | B9: General | C9: ERP / accounting system description and e-invoicing (FATOORA) solution details, onboarding & CSID | G9: Not started
A10: 6 | B10: General | C10: Authorisation letter for the representative dealing with ZATCA | G10: Not started
A11: 7 | B11: Financial | C11: Audited financial statements for each year under review | G11: Not started
A12: 8 | B12: Financial | C12: Monthly trial balances (opening, movements, closing) | D12: TB_Monthly | G12: Not started
A13: 9 | B13: Financial | C13: General ledger detail: revenue, VAT, and major expense accounts | G13: Not started
A14: 10 | B14: Financial | C14: Bank statements (ZATCA compares receipts with declared sales) | G14: Not started
A15: 11 | B15: VAT Returns | C15: Copies of all filed VAT returns and SADAD payment receipts | D15: VAT_Returns, ZATCA_Payments | G15: Not started
A16: 12 | B16: VAT Returns | C16: Voluntary disclosures / corrections filed (Box 14 usage) | D16: VAT_Returns col AJ | G16: Not started
A17: 13 | B17: Reconciliation | C17: Revenue per financial statements vs total sales per VAT returns | D17: Recon_Sales (bottom) | G17: Not started
A18: 14 | B18: Reconciliation | C18: Sales per VAT box vs sales listing vs GL – by period | D18: Recon_Sales | G18: Not started
A19: 15 | B19: Reconciliation | C19: Output VAT per GL vs returns | D19: Recon_OutputVAT | G19: Not started
A20: 16 | B20: Reconciliation | C20: Input VAT per GL vs returns | D20: Recon_InputVAT | G20: Not started
A21: 17 | B21: Reconciliation | C21: VAT control (payable) account roll-forward | D21: Recon_VAT_Account | G21: Not started
A22: 18 | B22: Reconciliation | C22: Customs imports (Bayan data) vs Box 8 | D22: Recon_InputVAT cols L–N | G22: Not started
A23: 19 | B23: Sales | C23: Sales listing (invoice level) with customer VAT numbers | D23: Sales_Register | G23: Not started
A24: 20 | B24: Sales | C24: Sample tax invoices, simplified invoices, credit/debit notes (XML / QR code) | G24: Not started
A25: 21 | B25: Sales | C25: Export evidence: customs exit declarations, bills of lading, contracts, proof of payment | D25: Sales_Register col N | G25: Not started
A26: 22 | B26: Sales | C26: Zero-rated domestic supply evidence (e.g. qualifying medicines, intl. transport) | D26: Sales_Register col N | G26: Not started
A27: 23 | B27: Sales | C27: Exempt supplies support (financial services margin, residential leases) | G27: Not started
A28: 24 | B28: Sales | C28: Major customer contracts incl. government contracts and VAT clauses | G28: Not started
A29: 25 | B29: Sales | C29: Deemed supplies: free samples, gifts, own use, staff benefits, write-offs | G29: Not started
A30: 26 | B30: Sales | C30: Related-party / intercompany charges and their VAT treatment | G30: Not started
A31: 27 | B31: Sales | C31: Fixed asset & real estate disposals (VAT / RETT treatment) | G31: Not started
A32: 28 | B32: Purchases | C32: Purchase listing (invoice level) with supplier VAT numbers | D32: Purchase_Register | G32: Not started
A33: 29 | B33: Purchases | C33: Sample supplier tax invoices supporting input VAT claimed | D33: Purchase_Register col K | G33: Not started
A34: 30 | B34: Purchases | C34: Import customs declarations (Bayan) and customs VAT payment proof | D34: Purchase_Register col M | G34: Not started
A35: 31 | B35: Purchases | C35: Reverse charge: foreign supplier invoices, contracts, RCM calculation | D35: Purchase_Register (Box 9) | G35: Not started
A36: 32 | B36: Purchases | C36: Blocked input VAT analysis (entertainment, vehicles, staff benefits) | D36: Purchase_Register col G | G36: Not started
A37: 33 | B37: Purchases | C37: Fixed asset register and capital assets adjustment | G37: Not started
A38: 34 | B38: Purchases | C38: Input VAT apportionment calculation (if exempt supplies exist) | G38: Not started
A39: 35 | B39: Cross-tax | C39: Withholding tax returns (foreign payments should match RCM in Box 9) | G39: Not started
A40: 36 | B40: Cross-tax | C40: Zakat / income tax return revenue vs VAT revenue | G40: Not started
A41: 37 | B41: E-invoicing | C41: E-invoicing compliance: Phase 2 integration wave, cleared/reported invoices report | D41: Sales_Register col L | G41: Not started
A42: 38 | B42: Response | C42: Written explanations / memos for every difference found | D42: Recon sheets | G42: Not started

Sheet TB_Monthly
A1: Monthly Trial Balance (ميزان المراجعة الشهري)
A2: Paste your TB: opening balance + monthly NET movements. Debit = positive, Credit = negative. Map every account in column D.
D3: Balance check (must = 0) → | E3: =ROUND(SUM(E6:E505),2) | F3: =ROUND(SUM(F6:F505),2) | G3: =ROUND(SUM(G6:G505),2) | H3: =ROUND(SUM(H6:H505),2) | I3: =ROUND(SUM(I6:I505),2) | J3: =ROUND(SUM(J6:J505),2) | K3: =ROUND(SUM(K6:K505),2) | L3: =ROUND(SUM(L6:L505),2) | ... S3: =ROUND(SUM(S6:S505),2)
E4: Month-end → | F4: =EOMONTH(Setup!$B$7,0) | G4: =EOMONTH(F4,1) | H4: =EOMONTH(G4,1) | I4: =EOMONTH(H4,1) | J4: =EOMONTH(I4,1) | K4: =EOMONTH(J4,1) | L4: =EOMONTH(K4,1) | M4: =EOMONTH(L4,1) | N4: =EOMONTH(M4,1) | ... Q4: =EOMONTH(P4,1)
A5: Account Code | B5: Account Name | C5: FS Class | D5: VAT Mapping | E5: Opening Balance | F5: Movement M1 | G5: Movement M2 | H5: Movement M3 | I5: Movement M4 | J5: Movement M5 | K5: Movement M6 | L5: Movement M7 | M5: Movement M8 | N5: Movement M9 | O5: Movement M10 | P5: Movement M11 | Q5: Movement M12 | R5: Total Movements | S5: Closing Balance
A6: 1100 | B6: Cash at Bank | C6: Asset | D6: Not VAT relevant | E6: 500000 | F6: 81000 | G6: -9000 | R6: =IF(A6="","",SUM(F6:Q6)) | S6: =IF(A6="","",E6+R6)
A7: 2210 | B7: Output VAT | C7: Liability | D7: Output VAT | E7: 0 | F7: -16500 | R7: =IF(A7="","",SUM(F7:Q7)) | S7: =IF(A7="","",E7+R7)
A8: 2220 | B8: Input VAT | C8: Asset | D8: Input VAT | E8: 0 | F8: 7500 | R8: =IF(A8="","",SUM(F8:Q8)) | S8: =IF(A8="","",E8+R8)
A9: 2230 | B9: VAT Payable - Settlement with ZATCA | C9: Liability | D9: VAT Payable / Settlement | E9: 0 | G9: 9000 | R9: =IF(A9="","",SUM(F9:Q9)) | S9: =IF(A9="","",E9+R9)
A10: 3100 | B10: Share Capital / Retained Earnings | C10: Equity | D10: Not VAT relevant | E10: -500000 | R10: =IF(A10="","",SUM(F10:Q10)) | S10: =IF(A10="","",E10+R10)
A11: 4100 | B11: Sales - Local | C11: Revenue | D11: Standard 15% (Box 1) | E11: 0 | F11: -100000 | R11: =IF(A11="","",SUM(F11:Q11)) | S11: =IF(A11="","",E11+R11)
A12: 4200 | B12: Sales - Export | C12: Revenue | D12: Export (Box 4) | E12: 0 | F12: -20000 | R12: =IF(A12="","",SUM(F12:Q12)) | S12: =IF(A12="","",E12+R12)
A13: 4900 | B13: Other Income - Dividends | C13: Revenue | D13: Revenue - Out of scope / Other income | E13: 0 | F13: -2000 | R13: =IF(A13="","",SUM(F13:Q13)) | S13: =IF(A13="","",E13+R13)
A14: 5100 | B14: Cost of Goods Purchased | C14: Expense | D14: Not VAT relevant | E14: 0 | F14: 40000 | R14: =IF(A14="","",SUM(F14:Q14)) | S14: =IF(A14="","",E14+R14)
A15: 6100 | B15: Consulting Fees - Foreign | C15: Expense | D15: Not VAT relevant | E15: 0 | F15: 10000 | R15: =IF(A15="","",SUM(F15:Q15)) | S15: =IF(A15="","",E15+R15)
R16: =IF(A16="","",SUM(F16:Q16)) | S16: =IF(A16="","",E16+R16)
R17: =IF(A17="","",SUM(F17:Q17)) | S17: =IF(A17="","",E17+R17)
R18: =IF(A18="","",SUM(F18:Q18)) | S18: =IF(A18="","",E18+R18)
R19: =IF(A19="","",SUM(F19:Q19)) | S19: =IF(A19="","",E19+R19)
R20: =IF(A20="","",SUM(F20:Q20)) | S20: =IF(A20="","",E20+R20)
R21: =IF(A21="","",SUM(F21:Q21)) | S21: =IF(A21="","",E21+R21)
R22: =IF(A22="","",SUM(F22:Q22)) | S22: =IF(A22="","",E22+R22)
R23: =IF(A23="","",SUM(F23:Q23)) | S23: =IF(A23="","",E23+R23)
R24: =IF(A24="","",SUM(F24:Q24)) | S24: =IF(A24="","",E24+R24)
R25: =IF(A25="","",SUM(F25:Q25)) | S25: =IF(A25="","",E25+R25)
R26: =IF(A26="","",SUM(F26:Q26)) | S26: =IF(A26="","",E26+R26)
R27: =IF(A27="","",SUM(F27:Q27)) | S27: =IF(A27="","",E27+R27)
... R505: =IF(A505="","",SUM(F505:Q505)) | S505: =IF(A505="","",E505+R505)

Sheet VAT_Returns
A1: VAT Returns as Filed (إقرارات ضريبة القيمة المضافة)
A2: Copy each return EXACTLY as filed on the ZATCA portal. Adjustments (credit notes) as negative. Grey columns recalculate the return and check it.
F4: Box 1 – Standard rated sales 15% المبيعات الخاضعة للنسبة الأساسية | I4: Box 2 – Sales to citizens (private health / education) المبيعات للمواطنين | L4: Box 3 – Zero-rated domestic sales المبيعات المحلية بنسبة صفر | O4: Box 4 – Exports الصادرات | R4: Box 5 – Exempt sales المبيعات المعفاة | U4: Box 7 – Standard rated domestic purchases 15% المشتريات المحلية الخاضعة للنسبة الأساسية | X4: Box 8 – Imports – VAT paid at customs الاستيرادات – ضريبة مدفوعة في الجمارك | AA4: Box 9 – Imports – reverse charge (RCM) الاستيرادات – الاحتساب العكسي | AD4: Box 10 – Zero-rated purchases المشتريات بنسبة صفر | AG4: Box 11 – Exempt purchases المشتريات المعفاة | AJ4: Box 14 – Corrections from previous periods (±5,000) | AK4: Box 15 – VAT credit carried forward | AL4: Box 16 – Net VAT due AS FILED | AM4: Box 6 – Total sales (net, recalc) | AN4: Box 6 – Output VAT incl. RCM (recalc) | AO4: Box 12 – Total purchases (net, recalc) | AP4: Box 12 – Input VAT (recalc) | AQ4: Box 13 – Net VAT for period (recalc) | AR4: Box 16 – Net VAT due (recalc) | AS4: Arithmetic check (filed vs recalc) | AT4: Filed on time? | AU4: Box 14 within ±5,000?
F5: Amount | G5: Adjustment | H5: VAT | I5: Amount | J5: Adjustment | K5: VAT | L5: Amount | M5: Adjustment | N5: VAT | O5: Amount | P5: Adjustment | Q5: VAT | R5: Amount | S5: Adjustment | T5: VAT | U5: Amount | V5: Adjustment | W5: VAT | X5: Amount | Y5: Adjustment | Z5: VAT | AA5: Amount | AB5: Adjustment | AC5: VAT | AD5: Amount | AE5: Adjustment | AF5: VAT | AG5: Amount | AH5: Adjustment | AI5: VAT
A6: =IF(Setup!C19="","",Setup!A19) | B6: =Setup!B19 | C6: =Setup!E19 | D6: 45713 | E6: VAT-2025-01 | F6: 100000 | H6: 15000 | O6: 20000 | U6: 40000 | W6: 6000 | AA6: 10000 | AC6: 1500 | AJ6: 0 | AK6: 0 | AL6: 9000 | AM6: =IF($A6="","",(F6+G6)+(I6+J6)+(L6+M6)+(O6+P6)+(R6+S6)) | AN6: =IF($A6="","",H6+K6+N6+Q6+T6+AC6) | AO6: =IF($A6="","",(U6+V6)+(X6+Y6)+(AA6+AB6)+(AD6+AE6)+(AG6+AH6)) | AP6: =IF($A6="","",W6+Z6+AC6+AF6+AI6) | AQ6: =IF($A6="","",AN6-AP6) | AR6: =IF($A6="","",AQ6+AJ6-AK6) | AS6: =IF($A6="","",IF(AND(D6="",AL6=""),"– Not entered",IF(ABS(AL6-AR6)<=Setup!$B$10,"✓ Agrees","✗ Filed ≠ recalc"))) | AT6: =IF($A6="","",IF(D6="","– No filing date",IF(D6<=C6,"✓ On time","✗ Late "&(D6-C6)&" days"))) | AU6: =IF($A6="","",IF(ABS(AJ6)<=5000,"✓ OK","✗ >5,000 – needs voluntary disclosure"))
A7: =IF(Setup!C20="","",Setup!A20) | B7: =Setup!B20 | C7: =Setup!E20 | AM7: =IF($A7="","",(F7+G7)+(I7+J7)+(L7+M7)+(O7+P7)+(R7+S7)) | AN7: =IF($A7="","",H7+K7+N7+Q7+T7+AC7) | AO7: =IF($A7="","",(U7+V7)+(X7+Y7)+(AA7+AB7)+(AD7+AE7)+(AG7+AH7)) | AP7: =IF($A7="","",W7+Z7+AC7+AF7+AI7) | AQ7: =IF($A7="","",AN7-AP7) | AR7: =IF($A7="","",AQ7+AJ7-AK7) | AS7: =IF($A7="","",IF(AND(D7="",AL7=""),"– Not entered",IF(ABS(AL7-AR7)<=Setup!$B$10,"✓ Agrees","✗ Filed ≠ recalc"))) | AT7: =IF($A7="","",IF(D7="","– No filing date",IF(D7<=C7,"✓ On time","✗ Late "&(D7-C7)&" days"))) | AU7: =IF($A7="","",IF(ABS(AJ7)<=5000,"✓ OK","✗ >5,000 – needs voluntary disclosure"))
A8: =IF(Setup!C21="","",Setup!A21) | B8: =Setup!B21 | C8: =Setup!E21 | AM8: =IF($A8="","",(F8+G8)+(I8+J8)+(L8+M8)+(O8+P8)+(R8+S8)) | AN8: =IF($A8="","",H8+K8+N8+Q8+T8+AC8) | AO8: =IF($A8="","",(U8+V8)+(X8+Y8)+(AA8+AB8)+(AD8+AE8)+(AG8+AH8)) | AP8: =IF($A8="","",W8+Z8+AC8+AF8+AI8) | AQ8: =IF($A8="","",AN8-AP8) | AR8: =IF($A8="","",AQ8+AJ8-AK8) | AS8: =IF($A8="","",IF(AND(D8="",AL8=""),"– Not entered",IF(ABS(AL8-AR8)<=Setup!$B$10,"✓ Agrees","✗ Filed ≠ recalc"))) | AT8: =IF($A8="","",IF(D8="","– No filing date",IF(D8<=C8,"✓ On time","✗ Late "&(D8-C8)&" days"))) | AU8: =IF($A8="","",IF(ABS(AJ8)<=5000,"✓ OK","✗ >5,000 – needs voluntary disclosure"))
A9: =IF(Setup!C22="","",Setup!A22) | B9: =Setup!B22 | C9: =Setup!E22 | AM9: =IF($A9="","",(F9+G9)+(I9+J9)+(L9+M9)+(O9+P9)+(R9+S9)) | AN9: =IF($A9="","",H9+K9+N9+Q9+T9+AC9) | AO9: =IF($A9="","",(U9+V9)+(X9+Y9)+(AA9+AB9)+(AD9+AE9)+(AG9+AH9)) | AP9: =IF($A9="","",W9+Z9+AC9+AF9+AI9) | AQ9: =IF($A9="","",AN9-AP9) | AR9: =IF($A9="","",AQ9+AJ9-AK9) | AS9: =IF($A9="","",IF(AND(D9="",AL9=""),"– Not entered",IF(ABS(AL9-AR9)<=Setup!$B$10,"✓ Agrees","✗ Filed ≠ recalc"))) | AT9: =IF($A9="","",IF(D9="","– No filing date",IF(D9<=C9,"✓ On time","✗ Late "&(D9-C9)&" days"))) | AU9: =IF($A9="","",IF(ABS(AJ9)<=5000,"✓ OK","✗ >5,000 – needs voluntary disclosure"))
A10: =IF(Setup!C23="","",Setup!A23) | B10: =Setup!B23 | C10: =Setup!E23 | AM10: =IF($A10="","",(F10+G10)+(I10+J10)+(L10+M10)+(O10+P10)+(R10+S10)) | AN10: =IF($A10="","",H10+K10+N10+Q10+T10+AC10) | AO10: =IF($A10="","",(U10+V10)+(X10+Y10)+(AA10+AB10)+(AD10+AE10)+(AG10+AH10)) | AP10: =IF($A10="","",W10+Z10+AC10+AF10+AI10) | AQ10: =IF($A10="","",AN10-AP10) | AR10: =IF($A10="","",AQ10+AJ10-AK10) | AS10: =IF($A10="","",IF(AND(D10="",AL10=""),"– Not entered",IF(ABS(AL10-AR10)<=Setup!$B$10,"✓ Agrees","✗ Filed ≠ recalc"))) | AT10: =IF($A10="","",IF(D10="","– No filing date",IF(D10<=C10,"✓ On time","✗ Late "&(D10-C10)&" days"))) | AU10: =IF($A10="","",IF(ABS(AJ10)<=5000,"✓ OK","✗ >5,000 – needs voluntary disclosure"))
A11: =IF(Setup!C24="","",Setup!A24) | B11: =Setup!B24 | C11: =Setup!E24 | AM11: =IF($A11="","",(F11+G11)+(I11+J11)+(L11+M11)+(O11+P11)+(R11+S11)) | AN11: =IF($A11="","",H11+K11+N11+Q11+T11+AC11) | AO11: =IF($A11="","",(U11+V11)+(X11+Y11)+(AA11+AB11)+(AD11+AE11)+(AG11+AH11)) | AP11: =IF($A11="","",W11+Z11+AC11+AF11+AI11) | AQ11: =IF($A11="","",AN11-AP11) | AR11: =IF($A11="","",AQ11+AJ11-AK11) | AS11: =IF($A11="","",IF(AND(D11="",AL11=""),"– Not entered",IF(ABS(AL11-AR11)<=Setup!$B$10,"✓ Agrees","✗ Filed ≠ recalc"))) | AT11: =IF($A11="","",IF(D11="","– No filing date",IF(D11<=C11,"✓ On time","✗ Late "&(D11-C11)&" days"))) | AU11: =IF($A11="","",IF(ABS(AJ11)<=5000,"✓ OK","✗ >5,000 – needs voluntary disclosure"))
A12: =IF(Setup!C25="","",Setup!A25) | B12: =Setup!B25 | C12: =Setup!E25 | AM12: =IF($A12="","",(F12+G12)+(I12+J12)+(L12+M12)+(O12+P12)+(R12+S12)) | AN12: =IF($A12="","",H12+K12+N12+Q12+T12+AC12) | AO12: =IF($A12="","",(U12+V12)+(X12+Y12)+(AA12+AB12)+(AD12+AE12)+(AG12+AH12)) | AP12: =IF($A12="","",W12+Z12+AC12+AF12+AI12) | AQ12: =IF($A12="","",AN12-AP12) | AR12: =IF($A12="","",AQ12+AJ12-AK12) | AS12: =IF($A12="","",IF(AND(D12="",AL12=""),"– Not entered",IF(ABS(AL12-AR12)<=Setup!$B$10,"✓ Agrees","✗ Filed ≠ recalc"))) | AT12: =IF($A12="","",IF(D12="","– No filing date",IF(D12<=C12,"✓ On time","✗ Late "&(D12-C12)&" days"))) | AU12: =IF($A12="","",IF(ABS(AJ12)<=5000,"✓ OK","✗ >5,000 – needs voluntary disclosure"))
A13: =IF(Setup!C26="","",Setup!A26) | B13: =Setup!B26 | C13: =Setup!E26 | AM13: =IF($A13="","",(F13+G13)+(I13+J13)+(L13+M13)+(O13+P13)+(R13+S13)) | AN13: =IF($A13="","",H13+K13+N13+Q13+T13+AC13) | AO13: =IF($A13="","",(U13+V13)+(X13+Y13)+(AA13+AB13)+(AD13+AE13)+(AG13+AH13)) | AP13: =IF($A13="","",W13+Z13+AC13+AF13+AI13) | AQ13: =IF($A13="","",AN13-AP13) | AR13: =IF($A13="","",AQ13+AJ13-AK13) | AS13: =IF($A13="","",IF(AND(D13="",AL13=""),"– Not entered",IF(ABS(AL13-AR13)<=Setup!$B$10,"✓ Agrees","✗ Filed ≠ recalc"))) | AT13: =IF($A13="","",IF(D13="","– No filing date",IF(D13<=C13,"✓ On time","✗ Late "&(D13-C13)&" days"))) | AU13: =IF($A13="","",IF(ABS(AJ13)<=5000,"✓ OK","✗ >5,000 – needs voluntary disclosure"))
A14: =IF(Setup!C27="","",Setup!A27) | B14: =Setup!B27 | C14: =Setup!E27 | AM14: =IF($A14="","",(F14+G14)+(I14+J14)+(L14+M14)+(O14+P14)+(R14+S14)) | AN14: =IF($A14="","",H14+K14+N14+Q14+T14+AC14) | AO14: =IF($A14="","",(U14+V14)+(X14+Y14)+(AA14+AB14)+(AD14+AE14)+(AG14+AH14)) | AP14: =IF($A14="","",W14+Z14+AC14+AF14+AI14) | AQ14: =IF($A14="","",AN14-AP14) | AR14: =IF($A14="","",AQ14+AJ14-AK14) | AS14: =IF($A14="","",IF(AND(D14="",AL14=""),"– Not entered",IF(ABS(AL14-AR14)<=Setup!$B$10,"✓ Agrees","✗ Filed ≠ recalc"))) | AT14: =IF($A14="","",IF(D14="","– No filing date",IF(D14<=C14,"✓ On time","✗ Late "&(D14-C14)&" days"))) | AU14: =IF($A14="","",IF(ABS(AJ14)<=5000,"✓ OK","✗ >5,000 – needs voluntary disclosure"))
A15: =IF(Setup!C28="","",Setup!A28) | B15: =Setup!B28 | C15: =Setup!E28 | AM15: =IF($A15="","",(F15+G15)+(I15+J15)+(L15+M15)+(O15+P15)+(R15+S15)) | AN15: =IF($A15="","",H15+K15+N15+Q15+T15+AC15) | AO15: =IF($A15="","",(U15+V15)+(X15+Y15)+(AA15+AB15)+(AD15+AE15)+(AG15+AH15)) | AP15: =IF($A15="","",W15+Z15+AC15+AF15+AI15) | AQ15: =IF($A15="","",AN15-AP15) | AR15: =IF($A15="","",AQ15+AJ15-AK15) | AS15: =IF($A15="","",IF(AND(D15="",AL15=""),"– Not entered",IF(ABS(AL15-AR15)<=Setup!$B$10,"✓ Agrees","✗ Filed ≠ recalc"))) | AT15: =IF($A15="","",IF(D15="","– No filing date",IF(D15<=C15,"✓ On time","✗ Late "&(D15-C15)&" days"))) | AU15: =IF($A15="","",IF(ABS(AJ15)<=5000,"✓ OK","✗ >5,000 – needs voluntary disclosure"))
A16: =IF(Setup!C29="","",Setup!A29) | B16: =Setup!B29 | C16: =Setup!E29 | AM16: =IF($A16="","",(F16+G16)+(I16+J16)+(L16+M16)+(O16+P16)+(R16+S16)) | AN16: =IF($A16="","",H16+K16+N16+Q16+T16+AC16) | AO16: =IF($A16="","",(U16+V16)+(X16+Y16)+(AA16+AB16)+(AD16+AE16)+(AG16+AH16)) | AP16: =IF($A16="","",W16+Z16+AC16+AF16+AI16) | AQ16: =IF($A16="","",AN16-AP16) | AR16: =IF($A16="","",AQ16+AJ16-AK16) | AS16: =IF($A16="","",IF(AND(D16="",AL16=""),"– Not entered",IF(ABS(AL16-AR16)<=Setup!$B$10,"✓ Agrees","✗ Filed ≠ recalc"))) | AT16: =IF($A16="","",IF(D16="","– No filing date",IF(D16<=C16,"✓ On time","✗ Late "&(D16-C16)&" days"))) | AU16: =IF($A16="","",IF(ABS(AJ16)<=5000,"✓ OK","✗ >5,000 – needs voluntary disclosure"))
A17: =IF(Setup!C30="","",Setup!A30) | B17: =Setup!B30 | C17: =Setup!E30 | AM17: =IF($A17="","",(F17+G17)+(I17+J17)+(L17+M17)+(O17+P17)+(R17+S17)) | AN17: =IF($A17="","",H17+K17+N17+Q17+T17+AC17) | AO17: =IF($A17="","",(U17+V17)+(X17+Y17)+(AA17+AB17)+(AD17+AE17)+(AG17+AH17)) | AP17: =IF($A17="","",W17+Z17+AC17+AF17+AI17) | AQ17: =IF($A17="","",AN17-AP17) | AR17: =IF($A17="","",AQ17+AJ17-AK17) | AS17: =IF($A17="","",IF(AND(D17="",AL17=""),"– Not entered",IF(ABS(AL17-AR17)<=Setup!$B$10,"✓ Agrees","✗ Filed ≠ recalc"))) | AT17: =IF($A17="","",IF(D17="","– No filing date",IF(D17<=C17,"✓ On time","✗ Late "&(D17-C17)&" days"))) | AU17: =IF($A17="","",IF(ABS(AJ17)<=5000,"✓ OK","✗ >5,000 – needs voluntary disclosure"))
B18: TOTAL YEAR | F18: =SUM(F6:F17) | G18: =SUM(G6:G17) | H18: =SUM(H6:H17) | I18: =SUM(I6:I17) | J18: =SUM(J6:J17) | K18: =SUM(K6:K17) | L18: =SUM(L6:L17) | M18: =SUM(M6:M17) | ... AR18: =SUM(AR6:AR17)
A20: Example: January 2025 is filled in to show the format – overwrite with your real filed figures.

Sheet Sales_Register
A1: Sales Register – invoice level (سجل المبيعات)
A2: Export from ERP / FATOORA. Credit notes as NEGATIVE amounts. Grey columns calculate expected VAT and flag issues ZATCA will look for.
A3: Rows flagged: | B3: =SUMPRODUCT((A6:A5005<>"")*(LEN(R6:R5005)>0)) | C3: Rows with data: | D3: =COUNT(A6:A5005)
A5: Invoice Date | B5: Invoice No | C5: Document Type | D5: Customer Name | E5: Customer VAT No | F5: Customer Type | G5: VAT Category | H5: Net Amount (SAR) | I5: VAT Amount (SAR) | J5: Total (SAR) | K5: E-Invoice UUID / Ref | L5: Reported/Cleared on FATOORA? | M5: GL Revenue Account | N5: Evidence Ref (export / zero-rate) | O5: Period # | P5: Expected VAT | Q5: VAT Difference | R5: Exceptions / Flags
A6: 45672 | B6: INV-0001 | C6: Tax Invoice | D6: ABC Trading Co | E6: 310123456700003 | F6: B2B - VAT registered | G6: Standard 15% (Box 1) | H6: 100000 | I6: 15000 | J6: =IF(A6="","",H6+I6) | K6: e3b0c442-98fc-1c14 | L6: Yes | M6: 4100 | O6: =IF(A6="","",SUMPRODUCT((A6>=Setup!$C$19:$C$30)*(A6<=Setup!$D$19:$D$30)*Setup!$A$19:$A$30)) | P6: =IF(A6="","",IF(G6="Standard 15% (Box 1)",ROUND(H6*Setup!$B$9,2),0)) | Q6: =IF(A6="","",I6-P6) | R6: =IF(A6="","",IF(O6=0,"Outside audit periods; ","")&IF(G6="","No VAT category; ","")&IF(ABS(Q6)>Setup!$B$10,"VAT ≠ 15% × net; ","")&IF(AND(F6="B2B - VAT registered",NOT(AND(LEN(E6)=15,LEFT(E6,1)="3",RIGHT(E6,1)="3",ISNUMBER(--E6)))),"Invalid/missing customer VAT no; ","")&IF(L6<>"Yes","Not reported/cleared on FATOORA; ","")&IF(AND(OR(G6="Zero-rated domestic (Box 3)",G6="Export (Box 4)"),N6=""),"Zero-rate/export evidence missing; ","")&IF(AND(C6="Credit Note",H6>0),"Credit note should be negative; ","")&IF(AND(C6="Simplified Tax Invoice",F6="B2B - VAT registered"),"Simplified invoice issued to VAT-registered B2B; ",""))
A7: 45677 | B7: INV-0002 | C7: Tax Invoice | D7: Gulf Imports LLC (UAE) | F7: B2B - Not registered | G7: Export (Box 4) | H7: 20000 | I7: 0 | J7: =IF(A7="","",H7+I7) | K7: a1f2c3d4-55aa-77bb | L7: Yes | M7: 4200 | N7: Customs exit decl. 123456 + B/L GLF-889 | O7: =IF(A7="","",SUMPRODUCT((A7>=Setup!$C$19:$C$30)*(A7<=Setup!$D$19:$D$30)*Setup!$A$19:$A$30)) | P7: =IF(A7="","",IF(G7="Standard 15% (Box 1)",ROUND(H7*Setup!$B$9,2),0)) | Q7: =IF(A7="","",I7-P7) | R7: =IF(A7="","",IF(O7=0,"Outside audit periods; ","")&IF(G7="","No VAT category; ","")&IF(ABS(Q7)>Setup!$B$10,"VAT ≠ 15% × net; ","")&IF(AND(F7="B2B - VAT registered",NOT(AND(LEN(E7)=15,LEFT(E7,1)="3",RIGHT(E7,1)="3",ISNUMBER(--E7)))),"Invalid/missing customer VAT no; ","")&IF(L7<>"Yes","Not reported/cleared on FATOORA; ","")&IF(AND(OR(G7="Zero-rated domestic (Box 3)",G7="Export (Box 4)"),N7=""),"Zero-rate/export evidence missing; ","")&IF(AND(C7="Credit Note",H7>0),"Credit note should be negative; ","")&IF(AND(C7="Simplified Tax Invoice",F7="B2B - VAT registered"),"Simplified invoice issued to VAT-registered B2B; ",""))
J8: =IF(A8="","",H8+I8) | O8: =IF(A8="","",SUMPRODUCT((A8>=Setup!$C$19:$C$30)*(A8<=Setup!$D$19:$D$30)*Setup!$A$19:$A$30)) | P8: =IF(A8="","",IF(G8="Standard 15% (Box 1)",ROUND(H8*Setup!$B$9,2),0)) | Q8: =IF(A8="","",I8-P8) | R8: =IF(A8="","",IF(O8=0,"Outside audit periods; ","")&IF(G8="","No VAT category; ","")&IF(ABS(Q8)>Setup!$B$10,"VAT ≠ 15% × net; ","")&IF(AND(F8="B2B - VAT registered",NOT(AND(LEN(E8)=15,LEFT(E8,1)="3",RIGHT(E8,1)="3",ISNUMBER(--E8)))),"Invalid/missing customer VAT no; ","")&IF(L8<>"Yes","Not reported/cleared on FATOORA; ","")&IF(AND(OR(G8="Zero-rated domestic (Box 3)",G8="Export (Box 4)"),N8=""),"Zero-rate/export evidence missing; ","")&IF(AND(C8="Credit Note",H8>0),"Credit note should be negative; ","")&IF(AND(C8="Simplified Tax Invoice",F8="B2B - VAT registered"),"Simplified invoice issued to VAT-registered B2B; ",""))
J9: =IF(A9="","",H9+I9) | O9: =IF(A9="","",SUMPRODUCT((A9>=Setup!$C$19:$C$30)*(A9<=Setup!$D$19:$D$30)*Setup!$A$19:$A$30)) | P9: =IF(A9="","",IF(G9="Standard 15% (Box 1)",ROUND(H9*Setup!$B$9,2),0)) | Q9: =IF(A9="","",I9-P9) | R9: =IF(A9="","",IF(O9=0,"Outside audit periods; ","")&IF(G9="","No VAT category; ","")&IF(ABS(Q9)>Setup!$B$10,"VAT ≠ 15% × net; ","")&IF(AND(F9="B2B - VAT registered",NOT(AND(LEN(E9)=15,LEFT(E9,1)="3",RIGHT(E9,1)="3",ISNUMBER(--E9)))),"Invalid/missing customer VAT no; ","")&IF(L9<>"Yes","Not reported/cleared on FATOORA; ","")&IF(AND(OR(G9="Zero-rated domestic (Box 3)",G9="Export (Box 4)"),N9=""),"Zero-rate/export evidence missing; ","")&IF(AND(C9="Credit Note",H9>0),"Credit note should be negative; ","")&IF(AND(C9="Simplified Tax Invoice",F9="B2B - VAT registered"),"Simplified invoice issued to VAT-registered B2B; ",""))
J10: =IF(A10="","",H10+I10) | O10: =IF(A10="","",SUMPRODUCT((A10>=Setup!$C$19:$C$30)*(A10<=Setup!$D$19:$D$30)*Setup!$A$19:$A$30)) | P10: =IF(A10="","",IF(G10="Standard 15% (Box 1)",ROUND(H10*Setup!$B$9,2),0)) | Q10: =IF(A10="","",I10-P10) | R10: =IF(A10="","",IF(O10=0,"Outside audit periods; ","")&IF(G10="","No VAT category; ","")&IF(ABS(Q10)>Setup!$B$10,"VAT ≠ 15% × net; ","")&IF(AND(F10="B2B - VAT registered",NOT(AND(LEN(E10)=15,LEFT(E10,1)="3",RIGHT(E10,1)="3",ISNUMBER(--E10)))),"Invalid/missing customer VAT no; ","")&IF(L10<>"Yes","Not reported/cleared on FATOORA; ","")&IF(AND(OR(G10="Zero-rated domestic (Box 3)",G10="Export (Box 4)"),N10=""),"Zero-rate/export evidence missing; ","")&IF(AND(C10="Credit Note",H10>0),"Credit note should be negative; ","")&IF(AND(C10="Simplified Tax Invoice",F10="B2B - VAT registered"),"Simplified invoice issued to VAT-registered B2B; ",""))
J11: =IF(A11="","",H11+I11) | O11: =IF(A11="","",SUMPRODUCT((A11>=Setup!$C$19:$C$30)*(A11<=Setup!$D$19:$D$30)*Setup!$A$19:$A$30)) | P11: =IF(A11="","",IF(G11="Standard 15% (Box 1)",ROUND(H11*Setup!$B$9,2),0)) | Q11: =IF(A11="","",I11-P11) | R11: =IF(A11="","",IF(O11=0,"Outside audit periods; ","")&IF(G11="","No VAT category; ","")&IF(ABS(Q11)>Setup!$B$10,"VAT ≠ 15% × net; ","")&IF(AND(F11="B2B - VAT registered",NOT(AND(LEN(E11)=15,LEFT(E11,1)="3",RIGHT(E11,1)="3",ISNUMBER(--E11)))),"Invalid/missing customer VAT no; ","")&IF(L11<>"Yes","Not reported/cleared on FATOORA; ","")&IF(AND(OR(G11="Zero-rated domestic (Box 3)",G11="Export (Box 4)"),N11=""),"Zero-rate/export evidence missing; ","")&IF(AND(C11="Credit Note",H11>0),"Credit note should be negative; ","")&IF(AND(C11="Simplified Tax Invoice",F11="B2B - VAT registered"),"Simplified invoice issued to VAT-registered B2B; ",""))
J12: =IF(A12="","",H12+I12) | O12: =IF(A12="","",SUMPRODUCT((A12>=Setup!$C$19:$C$30)*(A12<=Setup!$D$19:$D$30)*Setup!$A$19:$A$30)) | P12: =IF(A12="","",IF(G12="Standard 15% (Box 1)",ROUND(H12*Setup!$B$9,2),0)) | Q12: =IF(A12="","",I12-P12) | R12: =IF(A12="","",IF(O12=0,"Outside audit periods; ","")&IF(G12="","No VAT category; ","")&IF(ABS(Q12)>Setup!$B$10,"VAT ≠ 15% × net; ","")&IF(AND(F12="B2B - VAT registered",NOT(AND(LEN(E12)=15,LEFT(E12,1)="3",RIGHT(E12,1)="3",ISNUMBER(--E12)))),"Invalid/missing customer VAT no; ","")&IF(L12<>"Yes","Not reported/cleared on FATOORA; ","")&IF(AND(OR(G12="Zero-rated domestic (Box 3)",G12="Export (Box 4)"),N12=""),"Zero-rate/export evidence missing; ","")&IF(AND(C12="Credit Note",H12>0),"Credit note should be negative; ","")&IF(AND(C12="Simplified Tax Invoice",F12="B2B - VAT registered"),"Simplified invoice issued to VAT-registered B2B; ",""))
J13: =IF(A13="","",H13+I13) | O13: =IF(A13="","",SUMPRODUCT((A13>=Setup!$C$19:$C$30)*(A13<=Setup!$D$19:$D$30)*Setup!$A$19:$A$30)) | P13: =IF(A13="","",IF(G13="Standard 15% (Box 1)",ROUND(H13*Setup!$B$9,2),0)) | Q13: =IF(A13="","",I13-P13) | R13: =IF(A13="","",IF(O13=0,"Outside audit periods; ","")&IF(G13="","No VAT category; ","")&IF(ABS(Q13)>Setup!$B$10,"VAT ≠ 15% × net; ","")&IF(AND(F13="B2B - VAT registered",NOT(AND(LEN(E13)=15,LEFT(E13,1)="3",RIGHT(E13,1)="3",ISNUMBER(--E13)))),"Invalid/missing customer VAT no; ","")&IF(L13<>"Yes","Not reported/cleared on FATOORA; ","")&IF(AND(OR(G13="Zero-rated domestic (Box 3)",G13="Export (Box 4)"),N13=""),"Zero-rate/export evidence missing; ","")&IF(AND(C13="Credit Note",H13>0),"Credit note should be negative; ","")&IF(AND(C13="Simplified Tax Invoice",F13="B2B - VAT registered"),"Simplified invoice issued to VAT-registered B2B; ",""))
J14: =IF(A14="","",H14+I14) | O14: =IF(A14="","",SUMPRODUCT((A14>=Setup!$C$19:$C$30)*(A14<=Setup!$D$19:$D$30)*Setup!$A$19:$A$30)) | P14: =IF(A14="","",IF(G14="Standard 15% (Box 1)",ROUND(H14*Setup!$B$9,2),0)) | Q14: =IF(A14="","",I14-P14) | R14: =IF(A14="","",IF(O14=0,"Outside audit periods; ","")&IF(G14="","No VAT category; ","")&IF(ABS(Q14)>Setup!$B$10,"VAT ≠ 15% × net; ","")&IF(AND(F14="B2B - VAT registered",NOT(AND(LEN(E14)=15,LEFT(E14,1)="3",RIGHT(E14,1)="3",ISNUMBER(--E14)))),"Invalid/missing customer VAT no; ","")&IF(L14<>"Yes","Not reported/cleared on FATOORA; ","")&IF(AND(OR(G14="Zero-rated domestic (Box 3)",G14="Export (Box 4)"),N14=""),"Zero-rate/export evidence missing; ","")&IF(AND(C14="Credit Note",H14>0),"Credit note should be negative; ","")&IF(AND(C14="Simplified Tax Invoice",F14="B2B - VAT registered"),"Simplified invoice issued to VAT-registered B2B; ",""))
J15: =IF(A15="","",H15+I15) | O15: =IF(A15="","",SUMPRODUCT((A15>=Setup!$C$19:$C$30)*(A15<=Setup!$D$19:$D$30)*Setup!$A$19:$A$30)) | P15: =IF(A15="","",IF(G15="Standard 15% (Box 1)",ROUND(H15*Setup!$B$9,2),0)) | Q15: =IF(A15="","",I15-P15) | R15: =IF(A15="","",IF(O15=0,"Outside audit periods; ","")&IF(G15="","No VAT category; ","")&IF(ABS(Q15)>Setup!$B$10,"VAT ≠ 15% × net; ","")&IF(AND(F15="B2B - VAT registered",NOT(AND(LEN(E15)=15,LEFT(E15,1)="3",RIGHT(E15,1)="3",ISNUMBER(--E15)))),"Invalid/missing customer VAT no; ","")&IF(L15<>"Yes","Not reported/cleared on FATOORA; ","")&IF(AND(OR(G15="Zero-rated domestic (Box 3)",G15="Export (Box 4)"),N15=""),"Zero-rate/export evidence missing; ","")&IF(AND(C15="Credit Note",H15>0),"Credit note should be negative; ","")&IF(AND(C15="Simplified Tax Invoice",F15="B2B - VAT registered"),"Simplified invoice issued to VAT-registered B2B; ",""))
J16: =IF(A16="","",H16+I16) | O16: =IF(A16="","",SUMPRODUCT((A16>=Setup!$C$19:$C$30)*(A16<=Setup!$D$19:$D$30)*Setup!$A$19:$A$30)) | P16: =IF(A16="","",IF(G16="Standard 15% (Box 1)",ROUND(H16*Setup!$B$9,2),0)) | Q16: =IF(A16="","",I16-P16) | R16: =IF(A16="","",IF(O16=0,"Outside audit periods; ","")&IF(G16="","No VAT category; ","")&IF(ABS(Q16)>Setup!$B$10,"VAT ≠ 15% × net; ","")&IF(AND(F16="B2B - VAT registered",NOT(AND(LEN(E16)=15,LEFT(E16,1)="3",RIGHT(E16,1)="3",ISNUMBER(--E16)))),"Invalid/missing customer VAT no; ","")&IF(L16<>"Yes","Not reported/cleared on FATOORA; ","")&IF(AND(OR(G16="Zero-rated domestic (Box 3)",G16="Export (Box 4)"),N16=""),"Zero-rate/export evidence missing; ","")&IF(AND(C16="Credit Note",H16>0),"Credit note should be negative; ","")&IF(AND(C16="Simplified Tax Invoice",F16="B2B - VAT registered"),"Simplified invoice issued to VAT-registered B2B; ",""))
J17: =IF(A17="","",H17+I17) | O17: =IF(A17="","",SUMPRODUCT((A17>=Setup!$C$19:$C$30)*(A17<=Setup!$D$19:$D$30)*Setup!$A$19:$A$30)) | P17: =IF(A17="","",IF(G17="Standard 15% (Box 1)",ROUND(H17*Setup!$B$9,2),0)) | Q17: =IF(A17="","",I17-P17) | R17: =IF(A17="","",IF(O17=0,"Outside audit periods; ","")&IF(G17="","No VAT category; ","")&IF(ABS(Q17)>Setup!$B$10,"VAT ≠ 15% × net; ","")&IF(AND(F17="B2B - VAT registered",NOT(AND(LEN(E17)=15,LEFT(E17,1)="3",RIGHT(E17,1)="3",ISNUMBER(--E17)))),"Invalid/missing customer VAT no; ","")&IF(L17<>"Yes","Not reported/cleared on FATOORA; ","")&IF(AND(OR(G17="Zero-rated domestic (Box 3)",G17="Export (Box 4)"),N17=""),"Zero-rate/export evidence missing; ","")&IF(AND(C17="Credit Note",H17>0),"Credit note should be negative; ","")&IF(AND(C17="Simplified Tax Invoice",F17="B2B - VAT registered"),"Simplified invoice issued to VAT-registered B2B; ",""))
J18: =IF(A18="","",H18+I18) | O18: =IF(A18="","",SUMPRODUCT((A18>=Setup!$C$19:$C$30)*(A18<=Setup!$D$19:$D$30)*Setup!$A$19:$A$30)) | P18: =IF(A18="","",IF(G18="Standard 15% (Box 1)",ROUND(H18*Setup!$B$9,2),0)) | Q18: =IF(A18="","",I18-P18) | R18: =IF(A18="","",IF(O18=0,"Outside audit periods; ","")&IF(G18="","No VAT category; ","")&IF(ABS(Q18)>Setup!$B$10,"VAT ≠ 15% × net; ","")&IF(AND(F18="B2B - VAT registered",NOT(AND(LEN(E18)=15,LEFT(E18,1)="3",RIGHT(E18,1)="3",ISNUMBER(--E18)))),"Invalid/missing customer VAT no; ","")&IF(L18<>"Yes","Not reported/cleared on FATOORA; ","")&IF(AND(OR(G18="Zero-rated domestic (Box 3)",G18="Export (Box 4)"),N18=""),"Zero-rate/export evidence missing; ","")&IF(AND(C18="Credit Note",H18>0),"Credit note should be negative; ","")&IF(AND(C18="Simplified Tax Invoice",F18="B2B - VAT registered"),"Simplified invoice issued to VAT-registered B2B; ",""))
J19: =IF(A19="","",H19+I19) | O19: =IF(A19="","",SUMPRODUCT((A19>=Setup!$C$19:$C$30)*(A19<=Setup!$D$19:$D$30)*Setup!$A$19:$A$30)) | P19: =IF(A19="","",IF(G19="Standard 15% (Box 1)",ROUND(H19*Setup!$B$9,2),0)) | Q19: =IF(A19="","",I19-P19) | R19: =IF(A19="","",IF(O19=0,"Outside audit periods; ","")&IF(G19="","No VAT category; ","")&IF(ABS(Q19)>Setup!$B$10,"VAT ≠ 15% × net; ","")&IF(AND(F19="B2B - VAT registered",NOT(AND(LEN(E19)=15,LEFT(E19,1)="3",RIGHT(E19,1)="3",ISNUMBER(--E19)))),"Invalid/missing customer VAT no; ","")&IF(L19<>"Yes","Not reported/cleared on FATOORA; ","")&IF(AND(OR(G19="Zero-rated domestic (Box 3)",G19="Export (Box 4)"),N19=""),"Zero-rate/export evidence missing; ","")&IF(AND(C19="Credit Note",H19>0),"Credit note should be negative; ","")&IF(AND(C19="Simplified Tax Invoice",F19="B2B - VAT registered"),"Simplified invoice issued to VAT-registered B2B; ",""))
... J5005: =IF(A5005="","",H5005+I5005) | O5005: =IF(A5005="","",SUMPRODUCT((A5005>=Setup!$C$19:$C$30)*(A5005<=Setup!$D$19:$D$30)*Setup!$A$19:$A$30)) | P5005: =IF(A5005="","",IF(G5005="Standard 15% (Box 1)",ROUND(H5005*Setup!$B$9,2),0)) | Q5005: =IF(A5005="","",I5005-P5005) | R5005: =IF(A5005="","",IF(O5005=0,"Outside audit periods; ","")&IF(G5005="","No VAT category; ","")&IF(ABS(Q5005)>Setup!$B$10,"VAT ≠ 15% × net; ","")&IF(AND(F5005="B2B - VAT registered",NOT(AND(LEN(E5005)=15,LEFT(E5005,1)="3",RIGHT(E5005,1)="3",ISNUMBER(--E5005)))),"Invalid/missing customer VAT no; ","")&IF(L5005<>"Yes","Not reported/cleared on FATOORA; ","")&IF(AND(OR(G5005="Zero-rated domestic (Box 3)",G5005="Export (Box 4)"),N5005=""),"Zero-rate/export evidence missing; ","")&IF(AND(C5005="Credit Note",H5005>0),"Credit note should be negative; ","")&IF(AND(C5005="Simplified Tax Invoice",F5005="B2B - VAT registered"),"Simplified invoice issued to VAT-registered B2B; ",""))

Sheet Purchase_Register
A1: Purchase Register – invoice level (سجل المشتريات)
A2: Every invoice / customs declaration on which input VAT exists. Grey columns test whether the input VAT is defensible in an inspection.
A3: Rows flagged: | B3: =SUMPRODUCT((A6:A5005<>"")*(LEN(U6:U5005)>0)) | C3: VAT at risk (SAR): | D3: =SUM(T6:T5005)
A5: Invoice Date | B5: Supplier Invoice No | C5: Supplier Name | D5: Supplier VAT No | E5: Supplier Country | F5: VAT Category | G5: Expense Nature | H5: Net Amount (SAR) | I5: VAT Amount (SAR) | J5: Total (SAR) | K5: Valid Tax Invoice / Customs Decl. Held? | L5: Input VAT Claimed in Return? | M5: Customs Declaration No (Bayan) | N5: GL Account | O5: Period # | P5: Expected VAT | Q5: VAT Difference | R5: VAT Claimed | S5: Defensible VAT | T5: VAT at Risk | U5: Exceptions / Flags
A6: 45667 | B6: SUP-778 | C6: Al Noor Supplies | D6: 310123456700003 | E6: Saudi Arabia | F6: Standard domestic 15% (Box 7) | G6: General business expense | H6: 40000 | I6: 6000 | J6: =IF(A6="","",H6+I6) | K6: Yes | L6: Yes | N6: 5100 | O6: =IF(A6="","",SUMPRODUCT((A6>=Setup!$C$19:$C$30)*(A6<=Setup!$D$19:$D$30)*Setup!$A$19:$A$30)) | P6: =IF(A6="","",IF(OR(F6="Standard domestic 15% (Box 7)",F6="Import - VAT paid at customs (Box 8)",F6="Import - Reverse charge (Box 9)"),ROUND(H6*Setup!$B$9,2),0)) | Q6: =IF(A6="","",I6-P6) | R6: =IF(A6="","",IF(L6="Yes",I6,0)) | S6: =IF(A6="","",IF(AND(L6="Yes",K6="Yes",NOT(ISNUMBER(SEARCH("blocked",G6))),OR(F6="Standard domestic 15% (Box 7)",F6="Import - VAT paid at customs (Box 8)",F6="Import - Reverse charge (Box 9)"),OR(F6<>"Standard domestic 15% (Box 7)",AND(LEN(D6)=15,LEFT(D6,1)="3",RIGHT(D6,1)="3",ISNUMBER(--D6)))),I6,0)) | T6: =IF(A6="","",R6-S6) | U6: =IF(A6="","",IF(O6=0,"Outside audit periods; ","")&IF(F6="","No VAT category; ","")&IF(ABS(Q6)>Setup!$B$10,"VAT ≠ 15% × net; ","")&IF(AND(F6="Standard domestic 15% (Box 7)",NOT(AND(LEN(D6)=15,LEFT(D6,1)="3",RIGHT(D6,1)="3",ISNUMBER(--D6)))),"Invalid/missing supplier VAT no; ","")&IF(AND(L6="Yes",K6<>"Yes"),"VAT claimed without valid tax invoice; ","")&IF(AND(L6="Yes",ISNUMBER(SEARCH("blocked",G6))),"Blocked input VAT claimed; ","")&IF(AND(F6="Import - VAT paid at customs (Box 8)",M6=""),"Customs declaration no missing; ","")&IF(AND(F6="Import - Reverse charge (Box 9)",E6="Saudi Arabia"),"RCM used for a local supplier; ","")&IF(AND(L6="Yes",NOT(OR(F6="Standard domestic 15% (Box 7)",F6="Import - VAT paid at customs (Box 8)",F6="Import - Reverse charge (Box 9)"))),"VAT claimed on non-taxable category; ",""))
A7: 45682 | B7: FX-2025-01 | C7: Global Consulting Ltd | E7: United Kingdom | F7: Import - Reverse charge (Box 9) | G7: General business expense | H7: 10000 | I7: 1500 | J7: =IF(A7="","",H7+I7) | K7: Yes | L7: Yes | N7: 6100 | O7: =IF(A7="","",SUMPRODUCT((A7>=Setup!$C$19:$C$30)*(A7<=Setup!$D$19:$D$30)*Setup!$A$19:$A$30)) | P7: =IF(A7="","",IF(OR(F7="Standard domestic 15% (Box 7)",F7="Import - VAT paid at customs (Box 8)",F7="Import - Reverse charge (Box 9)"),ROUND(H7*Setup!$B$9,2),0)) | Q7: =IF(A7="","",I7-P7) | R7: =IF(A7="","",IF(L7="Yes",I7,0)) | S7: =IF(A7="","",IF(AND(L7="Yes",K7="Yes",NOT(ISNUMBER(SEARCH("blocked",G7))),OR(F7="Standard domestic 15% (Box 7)",F7="Import - VAT paid at customs (Box 8)",F7="Import - Reverse charge (Box 9)"),OR(F7<>"Standard domestic 15% (Box 7)",AND(LEN(D7)=15,LEFT(D7,1)="3",RIGHT(D7,1)="3",ISNUMBER(--D7)))),I7,0)) | T7: =IF(A7="","",R7-S7) | U7: =IF(A7="","",IF(O7=0,"Outside audit periods; ","")&IF(F7="","No VAT category; ","")&IF(ABS(Q7)>Setup!$B$10,"VAT ≠ 15% × net; ","")&IF(AND(F7="Standard domestic 15% (Box 7)",NOT(AND(LEN(D7)=15,LEFT(D7,1)="3",RIGHT(D7,1)="3",ISNUMBER(--D7)))),"Invalid/missing supplier VAT no; ","")&IF(AND(L7="Yes",K7<>"Yes"),"VAT claimed without valid tax invoice; ","")&IF(AND(L7="Yes",ISNUMBER(SEARCH("blocked",G7))),"Blocked input VAT claimed; ","")&IF(AND(F7="Import - VAT paid at customs (Box 8)",M7=""),"Customs declaration no missing; ","")&IF(AND(F7="Import - Reverse charge (Box 9)",E7="Saudi Arabia"),"RCM used for a local supplier; ","")&IF(AND(L7="Yes",NOT(OR(F7="Standard domestic 15% (Box 7)",F7="Import - VAT paid at customs (Box 8)",F7="Import - Reverse charge (Box 9)"))),"VAT claimed on non-taxable category; ",""))
J8: =IF(A8="","",H8+I8) | O8: =IF(A8="","",SUMPRODUCT((A8>=Setup!$C$19:$C$30)*(A8<=Setup!$D$19:$D$30)*Setup!$A$19:$A$30)) | P8: =IF(A8="","",IF(OR(F8="Standard domestic 15% (Box 7)",F8="Import - VAT paid at customs (Box 8)",F8="Import - Reverse charge (Box 9)"),ROUND(H8*Setup!$B$9,2),0)) | Q8: =IF(A8="","",I8-P8) | R8: =IF(A8="","",IF(L8="Yes",I8,0)) | S8: =IF(A8="","",IF(AND(L8="Yes",K8="Yes",NOT(ISNUMBER(SEARCH("blocked",G8))),OR(F8="Standard domestic 15% (Box 7)",F8="Import - VAT paid at customs (Box 8)",F8="Import - Reverse charge (Box 9)"),OR(F8<>"Standard domestic 15% (Box 7)",AND(LEN(D8)=15,LEFT(D8,1)="3",RIGHT(D8,1)="3",ISNUMBER(--D8)))),I8,0)) | T8: =IF(A8="","",R8-S8) | U8: =IF(A8="","",IF(O8=0,"Outside audit periods; ","")&IF(F8="","No VAT category; ","")&IF(ABS(Q8)>Setup!$B$10,"VAT ≠ 15% × net; ","")&IF(AND(F8="Standard domestic 15% (Box 7)",NOT(AND(LEN(D8)=15,LEFT(D8,1)="3",RIGHT(D8,1)="3",ISNUMBER(--D8)))),"Invalid/missing supplier VAT no; ","")&IF(AND(L8="Yes",K8<>"Yes"),"VAT claimed without valid tax invoice; ","")&IF(AND(L8="Yes",ISNUMBER(SEARCH("blocked",G8))),"Blocked input VAT claimed; ","")&IF(AND(F8="Import - VAT paid at customs (Box 8)",M8=""),"Customs declaration no missing; ","")&IF(AND(F8="Import - Reverse charge (Box 9)",E8="Saudi Arabia"),"RCM used for a local supplier; ","")&IF(AND(L8="Yes",NOT(OR(F8="Standard domestic 15% (Box 7)",F8="Import - VAT paid at customs (Box 8)",F8="Import - Reverse charge (Box 9)"))),"VAT claimed on non-taxable category; ",""))
J9: =IF(A9="","",H9+I9) | O9: =IF(A9="","",SUMPRODUCT((A9>=Setup!$C$19:$C$30)*(A9<=Setup!$D$19:$D$30)*Setup!$A$19:$A$30)) | P9: =IF(A9="","",IF(OR(F9="Standard domestic 15% (Box 7)",F9="Import - VAT paid at customs (Box 8)",F9="Import - Reverse charge (Box 9)"),ROUND(H9*Setup!$B$9,2),0)) | Q9: =IF(A9="","",I9-P9) | R9: =IF(A9="","",IF(L9="Yes",I9,0)) | S9: =IF(A9="","",IF(AND(L9="Yes",K9="Yes",NOT(ISNUMBER(SEARCH("blocked",G9))),OR(F9="Standard domestic 15% (Box 7)",F9="Import - VAT paid at customs (Box 8)",F9="Import - Reverse charge (Box 9)"),OR(F9<>"Standard domestic 15% (Box 7)",AND(LEN(D9)=15,LEFT(D9,1)="3",RIGHT(D9,1)="3",ISNUMBER(--D9)))),I9,0)) | T9: =IF(A9="","",R9-S9) | U9: =IF(A9="","",IF(O9=0,"Outside audit periods; ","")&IF(F9="","No VAT category; ","")&IF(ABS(Q9)>Setup!$B$10,"VAT ≠ 15% × net; ","")&IF(AND(F9="Standard domestic 15% (Box 7)",NOT(AND(LEN(D9)=15,LEFT(D9,1)="3",RIGHT(D9,1)="3",ISNUMBER(--D9)))),"Invalid/missing supplier VAT no; ","")&IF(AND(L9="Yes",K9<>"Yes"),"VAT claimed without valid tax invoice; ","")&IF(AND(L9="Yes",ISNUMBER(SEARCH("blocked",G9))),"Blocked input VAT claimed; ","")&IF(AND(F9="Import - VAT paid at customs (Box 8)",M9=""),"Customs declaration no missing; ","")&IF(AND(F9="Import - Reverse charge (Box 9)",E9="Saudi Arabia"),"RCM used for a local supplier; ","")&IF(AND(L9="Yes",NOT(OR(F9="Standard domestic 15% (Box 7)",F9="Import - VAT paid at customs (Box 8)",F9="Import - Reverse charge (Box 9)"))),"VAT claimed on non-taxable category; ",""))
J10: =IF(A10="","",H10+I10) | O10: =IF(A10="","",SUMPRODUCT((A10>=Setup!$C$19:$C$30)*(A10<=Setup!$D$19:$D$30)*Setup!$A$19:$A$30)) | P10: =IF(A10="","",IF(OR(F10="Standard domestic 15% (Box 7)",F10="Import - VAT paid at customs (Box 8)",F10="Import - Reverse charge (Box 9)"),ROUND(H10*Setup!$B$9,2),0)) | Q10: =IF(A10="","",I10-P10) | R10: =IF(A10="","",IF(L10="Yes",I10,0)) | S10: =IF(A10="","",IF(AND(L10="Yes",K10="Yes",NOT(ISNUMBER(SEARCH("blocked",G10))),OR(F10="Standard domestic 15% (Box 7)",F10="Import - VAT paid at customs (Box 8)",F10="Import - Reverse charge (Box 9)"),OR(F10<>"Standard domestic 15% (Box 7)",AND(LEN(D10)=15,LEFT(D10,1)="3",RIGHT(D10,1)="3",ISNUMBER(--D10)))),I10,0)) | T10: =IF(A10="","",R10-S10) | U10: =IF(A10="","",IF(O10=0,"Outside audit periods; ","")&IF(F10="","No VAT category; ","")&IF(ABS(Q10)>Setup!$B$10,"VAT ≠ 15% × net; ","")&IF(AND(F10="Standard domestic 15% (Box 7)",NOT(AND(LEN(D10)=15,LEFT(D10,1)="3",RIGHT(D10,1)="3",ISNUMBER(--D10)))),"Invalid/missing supplier VAT no; ","")&IF(AND(L10="Yes",K10<>"Yes"),"VAT claimed without valid tax invoice; ","")&IF(AND(L10="Yes",ISNUMBER(SEARCH("blocked",G10))),"Blocked input VAT claimed; ","")&IF(AND(F10="Import - VAT paid at customs (Box 8)",M10=""),"Customs declaration no missing; ","")&IF(AND(F10="Import - Reverse charge (Box 9)",E10="Saudi Arabia"),"RCM used for a local supplier; ","")&IF(AND(L10="Yes",NOT(OR(F10="Standard domestic 15% (Box 7)",F10="Import - VAT paid at customs (Box 8)",F10="Import - Reverse charge (Box 9)"))),"VAT claimed on non-taxable category; ",""))
J11: =IF(A11="","",H11+I11) | O11: =IF(A11="","",SUMPRODUCT((A11>=Setup!$C$19:$C$30)*(A11<=Setup!$D$19:$D$30)*Setup!$A$19:$A$30)) | P11: =IF(A11="","",IF(OR(F11="Standard domestic 15% (Box 7)",F11="Import - VAT paid at customs (Box 8)",F11="Import - Reverse charge (Box 9)"),ROUND(H11*Setup!$B$9,2),0)) | Q11: =IF(A11="","",I11-P11) | R11: =IF(A11="","",IF(L11="Yes",I11,0)) | S11: =IF(A11="","",IF(AND(L11="Yes",K11="Yes",NOT(ISNUMBER(SEARCH("blocked",G11))),OR(F11="Standard domestic 15% (Box 7)",F11="Import - VAT paid at customs (Box 8)",F11="Import - Reverse charge (Box 9)"),OR(F11<>"Standard domestic 15% (Box 7)",AND(LEN(D11)=15,LEFT(D11,1)="3",RIGHT(D11,1)="3",ISNUMBER(--D11)))),I11,0)) | T11: =IF(A11="","",R11-S11) | U11: =IF(A11="","",IF(O11=0,"Outside audit periods; ","")&IF(F11="","No VAT category; ","")&IF(ABS(Q11)>Setup!$B$10,"VAT ≠ 15% × net; ","")&IF(AND(F11="Standard domestic 15% (Box 7)",NOT(AND(LEN(D11)=15,LEFT(D11,1)="3",RIGHT(D11,1)="3",ISNUMBER(--D11)))),"Invalid/missing supplier VAT no; ","")&IF(AND(L11="Yes",K11<>"Yes"),"VAT claimed without valid tax invoice; ","")&IF(AND(L11="Yes",ISNUMBER(SEARCH("blocked",G11))),"Blocked input VAT claimed; ","")&IF(AND(F11="Import - VAT paid at customs (Box 8)",M11=""),"Customs declaration no missing; ","")&IF(AND(F11="Import - Reverse charge (Box 9)",E11="Saudi Arabia"),"RCM used for a local supplier; ","")&IF(AND(L11="Yes",NOT(OR(F11="Standard domestic 15% (Box 7)",F11="Import - VAT paid at customs (Box 8)",F11="Import - Reverse charge (Box 9)"))),"VAT claimed on non-taxable category; ",""))
J12: =IF(A12="","",H12+I12) | O12: =IF(A12="","",SUMPRODUCT((A12>=Setup!$C$19:$C$30)*(A12<=Setup!$D$19:$D$30)*Setup!$A$19:$A$30)) | P12: =IF(A12="","",IF(OR(F12="Standard domestic 15% (Box 7)",F12="Import - VAT paid at customs (Box 8)",F12="Import - Reverse charge (Box 9)"),ROUND(H12*Setup!$B$9,2),0)) | Q12: =IF(A12="","",I12-P12) | R12: =IF(A12="","",IF(L12="Yes",I12,0)) | S12: =IF(A12="","",IF(AND(L12="Yes",K12="Yes",NOT(ISNUMBER(SEARCH("blocked",G12))),OR(F12="Standard domestic 15% (Box 7)",F12="Import - VAT paid at customs (Box 8)",F12="Import - Reverse charge (Box 9)"),OR(F12<>"Standard domestic 15% (Box 7)",AND(LEN(D12)=15,LEFT(D12,1)="3",RIGHT(D12,1)="3",ISNUMBER(--D12)))),I12,0)) | T12: =IF(A12="","",R12-S12) | U12: =IF(A12="","",IF(O12=0,"Outside audit periods; ","")&IF(F12="","No VAT category; ","")&IF(ABS(Q12)>Setup!$B$10,"VAT ≠ 15% × net; ","")&IF(AND(F12="Standard domestic 15% (Box 7)",NOT(AND(LEN(D12)=15,LEFT(D12,1)="3",RIGHT(D12,1)="3",ISNUMBER(--D12)))),"Invalid/missing supplier VAT no; ","")&IF(AND(L12="Yes",K12<>"Yes"),"VAT claimed without valid tax invoice; ","")&IF(AND(L12="Yes",ISNUMBER(SEARCH("blocked",G12))),"Blocked input VAT claimed; ","")&IF(AND(F12="Import - VAT paid at customs (Box 8)",M12=""),"Customs declaration no missing; ","")&IF(AND(F12="Import - Reverse charge (Box 9)",E12="Saudi Arabia"),"RCM used for a local supplier; ","")&IF(AND(L12="Yes",NOT(OR(F12="Standard domestic 15% (Box 7)",F12="Import - VAT paid at customs (Box 8)",F12="Import - Reverse charge (Box 9)"))),"VAT claimed on non-taxable category; ",""))
J13: =IF(A13="","",H13+I13) | O13: =IF(A13="","",SUMPRODUCT((A13>=Setup!$C$19:$C$30)*(A13<=Setup!$D$19:$D$30)*Setup!$A$19:$A$30)) | P13: =IF(A13="","",IF(OR(F13="Standard domestic 15% (Box 7)",F13="Import - VAT paid at customs (Box 8)",F13="Import - Reverse charge (Box 9)"),ROUND(H13*Setup!$B$9,2),0)) | Q13: =IF(A13="","",I13-P13) | R13: =IF(A13="","",IF(L13="Yes",I13,0)) | S13: =IF(A13="","",IF(AND(L13="Yes",K13="Yes",NOT(ISNUMBER(SEARCH("blocked",G13))),OR(F13="Standard domestic 15% (Box 7)",F13="Import - VAT paid at customs (Box 8)",F13="Import - Reverse charge (Box 9)"),OR(F13<>"Standard domestic 15% (Box 7)",AND(LEN(D13)=15,LEFT(D13,1)="3",RIGHT(D13,1)="3",ISNUMBER(--D13)))),I13,0)) | T13: =IF(A13="","",R13-S13) | U13: =IF(A13="","",IF(O13=0,"Outside audit periods; ","")&IF(F13="","No VAT category; ","")&IF(ABS(Q13)>Setup!$B$10,"VAT ≠ 15% × net; ","")&IF(AND(F13="Standard domestic 15% (Box 7)",NOT(AND(LEN(D13)=15,LEFT(D13,1)="3",RIGHT(D13,1)="3",ISNUMBER(--D13)))),"Invalid/missing supplier VAT no; ","")&IF(AND(L13="Yes",K13<>"Yes"),"VAT claimed without valid tax invoice; ","")&IF(AND(L13="Yes",ISNUMBER(SEARCH("blocked",G13))),"Blocked input VAT claimed; ","")&IF(AND(F13="Import - VAT paid at customs (Box 8)",M13=""),"Customs declaration no missing; ","")&IF(AND(F13="Import - Reverse charge (Box 9)",E13="Saudi Arabia"),"RCM used for a local supplier; ","")&IF(AND(L13="Yes",NOT(OR(F13="Standard domestic 15% (Box 7)",F13="Import - VAT paid at customs (Box 8)",F13="Import - Reverse charge (Box 9)"))),"VAT claimed on non-taxable category; ",""))
J14: =IF(A14="","",H14+I14) | O14: =IF(A14="","",SUMPRODUCT((A14>=Setup!$C$19:$C$30)*(A14<=Setup!$D$19:$D$30)*Setup!$A$19:$A$30)) | P14: =IF(A14="","",IF(OR(F14="Standard domestic 15% (Box 7)",F14="Import - VAT paid at customs (Box 8)",F14="Import - Reverse charge (Box 9)"),ROUND(H14*Setup!$B$9,2),0)) | Q14: =IF(A14="","",I14-P14) | R14: =IF(A14="","",IF(L14="Yes",I14,0)) | S14: =IF(A14="","",IF(AND(L14="Yes",K14="Yes",NOT(ISNUMBER(SEARCH("blocked",G14))),OR(F14="Standard domestic 15% (Box 7)",F14="Import - VAT paid at customs (Box 8)",F14="Import - Reverse charge (Box 9)"),OR(F14<>"Standard domestic 15% (Box 7)",AND(LEN(D14)=15,LEFT(D14,1)="3",RIGHT(D14,1)="3",ISNUMBER(--D14)))),I14,0)) | T14: =IF(A14="","",R14-S14) | U14: =IF(A14="","",IF(O14=0,"Outside audit periods; ","")&IF(F14="","No VAT category; ","")&IF(ABS(Q14)>Setup!$B$10,"VAT ≠ 15% × net; ","")&IF(AND(F14="Standard domestic 15% (Box 7)",NOT(AND(LEN(D14)=15,LEFT(D14,1)="3",RIGHT(D14,1)="3",ISNUMBER(--D14)))),"Invalid/missing supplier VAT no; ","")&IF(AND(L14="Yes",K14<>"Yes"),"VAT claimed without valid tax invoice; ","")&IF(AND(L14="Yes",ISNUMBER(SEARCH("blocked",G14))),"Blocked input VAT claimed; ","")&IF(AND(F14="Import - VAT paid at customs (Box 8)",M14=""),"Customs declaration no missing; ","")&IF(AND(F14="Import - Reverse charge (Box 9)",E14="Saudi Arabia"),"RCM used for a local supplier; ","")&IF(AND(L14="Yes",NOT(OR(F14="Standard domestic 15% (Box 7)",F14="Import - VAT paid at customs (Box 8)",F14="Import - Reverse charge (Box 9)"))),"VAT claimed on non-taxable category; ",""))
J15: =IF(A15="","",H15+I15) | O15: =IF(A15="","",SUMPRODUCT((A15>=Setup!$C$19:$C$30)*(A15<=Setup!$D$19:$D$30)*Setup!$A$19:$A$30)) | P15: =IF(A15="","",IF(OR(F15="Standard domestic 15% (Box 7)",F15="Import - VAT paid at customs (Box 8)",F15="Import - Reverse charge (Box 9)"),ROUND(H15*Setup!$B$9,2),0)) | Q15: =IF(A15="","",I15-P15) | R15: =IF(A15="","",IF(L15="Yes",I15,0)) | S15: =IF(A15="","",IF(AND(L15="Yes",K15="Yes",NOT(ISNUMBER(SEARCH("blocked",G15))),OR(F15="Standard domestic 15% (Box 7)",F15="Import - VAT paid at customs (Box 8)",F15="Import - Reverse charge (Box 9)"),OR(F15<>"Standard domestic 15% (Box 7)",AND(LEN(D15)=15,LEFT(D15,1)="3",RIGHT(D15,1)="3",ISNUMBER(--D15)))),I15,0)) | T15: =IF(A15="","",R15-S15) | U15: =IF(A15="","",IF(O15=0,"Outside audit periods; ","")&IF(F15="","No VAT category; ","")&IF(ABS(Q15)>Setup!$B$10,"VAT ≠ 15% × net; ","")&IF(AND(F15="Standard domestic 15% (Box 7)",NOT(AND(LEN(D15)=15,LEFT(D15,1)="3",RIGHT(D15,1)="3",ISNUMBER(--D15)))),"Invalid/missing supplier VAT no; ","")&IF(AND(L15="Yes",K15<>"Yes"),"VAT claimed without valid tax invoice; ","")&IF(AND(L15="Yes",ISNUMBER(SEARCH("blocked",G15))),"Blocked input VAT claimed; ","")&IF(AND(F15="Import - VAT paid at customs (Box 8)",M15=""),"Customs declaration no missing; ","")&IF(AND(F15="Import - Reverse charge (Box 9)",E15="Saudi Arabia"),"RCM used for a local supplier; ","")&IF(AND(L15="Yes",NOT(OR(F15="Standard domestic 15% (Box 7)",F15="Import - VAT paid at customs (Box 8)",F15="Import - Reverse charge (Box 9)"))),"VAT claimed on non-taxable category; ",""))
J16: =IF(A16="","",H16+I16) | O16: =IF(A16="","",SUMPRODUCT((A16>=Setup!$C$19:$C$30)*(A16<=Setup!$D$19:$D$30)*Setup!$A$19:$A$30)) | P16: =IF(A16="","",IF(OR(F16="Standard domestic 15% (Box 7)",F16="Import - VAT paid at customs (Box 8)",F16="Import - Reverse charge (Box 9)"),ROUND(H16*Setup!$B$9,2),0)) | Q16: =IF(A16="","",I16-P16) | R16: =IF(A16="","",IF(L16="Yes",I16,0)) | S16: =IF(A16="","",IF(AND(L16="Yes",K16="Yes",NOT(ISNUMBER(SEARCH("blocked",G16))),OR(F16="Standard domestic 15% (Box 7)",F16="Import - VAT paid at customs (Box 8)",F16="Import - Reverse charge (Box 9)"),OR(F16<>"Standard domestic 15% (Box 7)",AND(LEN(D16)=15,LEFT(D16,1)="3",RIGHT(D16,1)="3",ISNUMBER(--D16)))),I16,0)) | T16: =IF(A16="","",R16-S16) | U16: =IF(A16="","",IF(O16=0,"Outside audit periods; ","")&IF(F16="","No VAT category; ","")&IF(ABS(Q16)>Setup!$B$10,"VAT ≠ 15% × net; ","")&IF(AND(F16="Standard domestic 15% (Box 7)",NOT(AND(LEN(D16)=15,LEFT(D16,1)="3",RIGHT(D16,1)="3",ISNUMBER(--D16)))),"Invalid/missing supplier VAT no; ","")&IF(AND(L16="Yes",K16<>"Yes"),"VAT claimed without valid tax invoice; ","")&IF(AND(L16="Yes",ISNUMBER(SEARCH("blocked",G16))),"Blocked input VAT claimed; ","")&IF(AND(F16="Import - VAT paid at customs (Box 8)",M16=""),"Customs declaration no missing; ","")&IF(AND(F16="Import - Reverse charge (Box 9)",E16="Saudi Arabia"),"RCM used for a local supplier; ","")&IF(AND(L16="Yes",NOT(OR(F16="Standard domestic 15% (Box 7)",F16="Import - VAT paid at customs (Box 8)",F16="Import - Reverse charge (Box 9)"))),"VAT claimed on non-taxable category; ",""))
J17: =IF(A17="","",H17+I17) | O17: =IF(A17="","",SUMPRODUCT((A17>=Setup!$C$19:$C$30)*(A17<=Setup!$D$19:$D$30)*Setup!$A$19:$A$30)) | P17: =IF(A17="","",IF(OR(F17="Standard domestic 15% (Box 7)",F17="Import - VAT paid at customs (Box 8)",F17="Import - Reverse charge (Box 9)"),ROUND(H17*Setup!$B$9,2),0)) | Q17: =IF(A17="","",I17-P17) | R17: =IF(A17="","",IF(L17="Yes",I17,0)) | S17: =IF(A17="","",IF(AND(L17="Yes",K17="Yes",NOT(ISNUMBER(SEARCH("blocked",G17))),OR(F17="Standard domestic 15% (Box 7)",F17="Import - VAT paid at customs (Box 8)",F17="Import - Reverse charge (Box 9)"),OR(F17<>"Standard domestic 15% (Box 7)",AND(LEN(D17)=15,LEFT(D17,1)="3",RIGHT(D17,1)="3",ISNUMBER(--D17)))),I17,0)) | T17: =IF(A17="","",R17-S17) | U17: =IF(A17="","",IF(O17=0,"Outside audit periods; ","")&IF(F17="","No VAT category; ","")&IF(ABS(Q17)>Setup!$B$10,"VAT ≠ 15% × net; ","")&IF(AND(F17="Standard domestic 15% (Box 7)",NOT(AND(LEN(D17)=15,LEFT(D17,1)="3",RIGHT(D17,1)="3",ISNUMBER(--D17)))),"Invalid/missing supplier VAT no; ","")&IF(AND(L17="Yes",K17<>"Yes"),"VAT claimed without valid tax invoice; ","")&IF(AND(L17="Yes",ISNUMBER(SEARCH("blocked",G17))),"Blocked input VAT claimed; ","")&IF(AND(F17="Import - VAT paid at customs (Box 8)",M17=""),"Customs declaration no missing; ","")&IF(AND(F17="Import - Reverse charge (Box 9)",E17="Saudi Arabia"),"RCM used for a local supplier; ","")&IF(AND(L17="Yes",NOT(OR(F17="Standard domestic 15% (Box 7)",F17="Import - VAT paid at customs (Box 8)",F17="Import - Reverse charge (Box 9)"))),"VAT claimed on non-taxable category; ",""))
J18: =IF(A18="","",H18+I18) | O18: =IF(A18="","",SUMPRODUCT((A18>=Setup!$C$19:$C$30)*(A18<=Setup!$D$19:$D$30)*Setup!$A$19:$A$30)) | P18: =IF(A18="","",IF(OR(F18="Standard domestic 15% (Box 7)",F18="Import - VAT paid at customs (Box 8)",F18="Import - Reverse charge (Box 9)"),ROUND(H18*Setup!$B$9,2),0)) | Q18: =IF(A18="","",I18-P18) | R18: =IF(A18="","",IF(L18="Yes",I18,0)) | S18: =IF(A18="","",IF(AND(L18="Yes",K18="Yes",NOT(ISNUMBER(SEARCH("blocked",G18))),OR(F18="Standard domestic 15% (Box 7)",F18="Import - VAT paid at customs (Box 8)",F18="Import - Reverse charge (Box 9)"),OR(F18<>"Standard domestic 15% (Box 7)",AND(LEN(D18)=15,LEFT(D18,1)="3",RIGHT(D18,1)="3",ISNUMBER(--D18)))),I18,0)) | T18: =IF(A18="","",R18-S18) | U18: =IF(A18="","",IF(O18=0,"Outside audit periods; ","")&IF(F18="","No VAT category; ","")&IF(ABS(Q18)>Setup!$B$10,"VAT ≠ 15% × net; ","")&IF(AND(F18="Standard domestic 15% (Box 7)",NOT(AND(LEN(D18)=15,LEFT(D18,1)="3",RIGHT(D18,1)="3",ISNUMBER(--D18)))),"Invalid/missing supplier VAT no; ","")&IF(AND(L18="Yes",K18<>"Yes"),"VAT claimed without valid tax invoice; ","")&IF(AND(L18="Yes",ISNUMBER(SEARCH("blocked",G18))),"Blocked input VAT claimed; ","")&IF(AND(F18="Import - VAT paid at customs (Box 8)",M18=""),"Customs declaration no missing; ","")&IF(AND(F18="Import - Reverse charge (Box 9)",E18="Saudi Arabia"),"RCM used for a local supplier; ","")&IF(AND(L18="Yes",NOT(OR(F18="Standard domestic 15% (Box 7)",F18="Import - VAT paid at customs (Box 8)",F18="Import - Reverse charge (Box 9)"))),"VAT claimed on non-taxable category; ",""))
J19: =IF(A19="","",H19+I19) | O19: =IF(A19="","",SUMPRODUCT((A19>=Setup!$C$19:$C$30)*(A19<=Setup!$D$19:$D$30)*Setup!$A$19:$A$30)) | P19: =IF(A19="","",IF(OR(F19="Standard domestic 15% (Box 7)",F19="Import - VAT paid at customs (Box 8)",F19="Import - Reverse charge (Box 9)"),ROUND(H19*Setup!$B$9,2),0)) | Q19: =IF(A19="","",I19-P19) | R19: =IF(A19="","",IF(L19="Yes",I19,0)) | S19: =IF(A19="","",IF(AND(L19="Yes",K19="Yes",NOT(ISNUMBER(SEARCH("blocked",G19))),OR(F19="Standard domestic 15% (Box 7)",F19="Import - VAT paid at customs (Box 8)",F19="Import - Reverse charge (Box 9)"),OR(F19<>"Standard domestic 15% (Box 7)",AND(LEN(D19)=15,LEFT(D19,1)="3",RIGHT(D19,1)="3",ISNUMBER(--D19)))),I19,0)) | T19: =IF(A19="","",R19-S19) | U19: =IF(A19="","",IF(O19=0,"Outside audit periods; ","")&IF(F19="","No VAT category; ","")&IF(ABS(Q19)>Setup!$B$10,"VAT ≠ 15% × net; ","")&IF(AND(F19="Standard domestic 15% (Box 7)",NOT(AND(LEN(D19)=15,LEFT(D19,1)="3",RIGHT(D19,1)="3",ISNUMBER(--D19)))),"Invalid/missing supplier VAT no; ","")&IF(AND(L19="Yes",K19<>"Yes"),"VAT claimed without valid tax invoice; ","")&IF(AND(L19="Yes",ISNUMBER(SEARCH("blocked",G19))),"Blocked input VAT claimed; ","")&IF(AND(F19="Import - VAT paid at customs (Box 8)",M19=""),"Customs declaration no missing; ","")&IF(AND(F19="Import - Reverse charge (Box 9)",E19="Saudi Arabia"),"RCM used for a local supplier; ","")&IF(AND(L19="Yes",NOT(OR(F19="Standard domestic 15% (Box 7)",F19="Import - VAT paid at customs (Box 8)",F19="Import - Reverse charge (Box 9)"))),"VAT claimed on non-taxable category; ",""))
... J5005: =IF(A5005="","",H5005+I5005) | O5005: =IF(A5005="","",SUMPRODUCT((A5005>=Setup!$C$19:$C$30)*(A5005<=Setup!$D$19:$D$30)*Setup!$A$19:$A$30)) | P5005: =IF(A5005="","",IF(OR(F5005="Standard domestic 15% (Box 7)",F5005="Import - VAT paid at customs (Box 8)",F5005="Import - Reverse charge (Box 9)"),ROUND(H5005*Setup!$B$9,2),0)) | Q5005: =IF(A5005="","",I5005-P5005) | R5005: =IF(A5005="","",IF(L5005="Yes",I5005,0)) | S5005: =IF(A5005="","",IF(AND(L5005="Yes",K5005="Yes",NOT(ISNUMBER(SEARCH("blocked",G5005))),OR(F5005="Standard domestic 15% (Box 7)",F5005="Import - VAT paid at customs (Box 8)",F5005="Import - Reverse charge (Box 9)"),OR(F5005<>"Standard domestic 15% (Box 7)",AND(LEN(D5005)=15,LEFT(D5005,1)="3",RIGHT(D5005,1)="3",ISNUMBER(--D5005)))),I5005,0)) | T5005: =IF(A5005="","",R5005-S5005) | U5005: =IF(A5005="","",IF(O5005=0,"Outside audit periods; ","")&IF(F5005="","No VAT category; ","")&IF(ABS(Q5005)>Setup!$B$10,"VAT ≠ 15% × net; ","")&IF(AND(F5005="Standard domestic 15% (Box 7)",NOT(AND(LEN(D5005)=15,LEFT(D5005,1)="3",RIGHT(D5005,1)="3",ISNUMBER(--D5005)))),"Invalid/missing supplier VAT no; ","")&IF(AND(L5005="Yes",K5005<>"Yes"),"VAT claimed without valid tax invoice; ","")&IF(AND(L5005="Yes",ISNUMBER(SEARCH("blocked",G5005))),"Blocked input VAT claimed; ","")&IF(AND(F5005="Import - VAT paid at customs (Box 8)",M5005=""),"Customs declaration no missing; ","")&IF(AND(F5005="Import - Reverse charge (Box 9)",E5005="Saudi Arabia"),"RCM used for a local supplier; ","")&IF(AND(L5005="Yes",NOT(OR(F5005="Standard domestic 15% (Box 7)",F5005="Import - VAT paid at customs (Box 8)",F5005="Import - Reverse charge (Box 9)"))),"VAT claimed on non-taxable category; ",""))

Sheet ZATCA_Payments
A1: Payments to / Refunds from ZATCA (المدفوعات)
A2: One row per SADAD payment. Refunds received as NEGATIVE. Use Period # 0 for payments of periods before the audit year.
A5: Period # | B5: Payment Date | C5: SADAD / Payment Ref | D5: Amount (SAR) | E5: Notes | F5: Period | G5: Due Date | H5: Days Late | I5: Months Late (or part) | J5: Est. Late Payment Penalty
A6: 1 | B6: 45715 | C6: SADAD-90012345 | D6: 9000 | E6: Jan 2025 VAT | F6: =IF(OR(A6="",B6=""),"",IFERROR(INDEX(Setup!$B$19:$B$30,A6),"Prior period")) | G6: =IF(OR(A6="",B6=""),"",IFERROR(INDEX(Setup!$E$19:$E$30,A6)+0,"")) | H6: =IF(OR(G6="",B6=""),"",MAX(0,B6-G6)) | I6: =IF(H6="","",IF(H6=0,0,(YEAR(B6)-YEAR(G6))*12+MONTH(B6)-MONTH(G6)+IF(DAY(B6)>DAY(G6),1,0))) | J6: =IF(I6="","",IF(D6>0,D6*Setup!$B$12*I6,0))
F7: =IF(OR(A7="",B7=""),"",IFERROR(INDEX(Setup!$B$19:$B$30,A7),"Prior period")) | G7: =IF(OR(A7="",B7=""),"",IFERROR(INDEX(Setup!$E$19:$E$30,A7)+0,"")) | H7: =IF(OR(G7="",B7=""),"",MAX(0,B7-G7)) | I7: =IF(H7="","",IF(H7=0,0,(YEAR(B7)-YEAR(G7))*12+MONTH(B7)-MONTH(G7)+IF(DAY(B7)>DAY(G7),1,0))) | J7: =IF(I7="","",IF(D7>0,D7*Setup!$B$12*I7,0))
F8: =IF(OR(A8="",B8=""),"",IFERROR(INDEX(Setup!$B$19:$B$30,A8),"Prior period")) | G8: =IF(OR(A8="",B8=""),"",IFERROR(INDEX(Setup!$E$19:$E$30,A8)+0,"")) | H8: =IF(OR(G8="",B8=""),"",MAX(0,B8-G8)) | I8: =IF(H8="","",IF(H8=0,0,(YEAR(B8)-YEAR(G8))*12+MONTH(B8)-MONTH(G8)+IF(DAY(B8)>DAY(G8),1,0))) | J8: =IF(I8="","",IF(D8>0,D8*Setup!$B$12*I8,0))
F9: =IF(OR(A9="",B9=""),"",IFERROR(INDEX(Setup!$B$19:$B$30,A9),"Prior period")) | G9: =IF(OR(A9="",B9=""),"",IFERROR(INDEX(Setup!$E$19:$E$30,A9)+0,"")) | H9: =IF(OR(G9="",B9=""),"",MAX(0,B9-G9)) | I9: =IF(H9="","",IF(H9=0,0,(YEAR(B9)-YEAR(G9))*12+MONTH(B9)-MONTH(G9)+IF(DAY(B9)>DAY(G9),1,0))) | J9: =IF(I9="","",IF(D9>0,D9*Setup!$B$12*I9,0))
F10: =IF(OR(A10="",B10=""),"",IFERROR(INDEX(Setup!$B$19:$B$30,A10),"Prior period")) | G10: =IF(OR(A10="",B10=""),"",IFERROR(INDEX(Setup!$E$19:$E$30,A10)+0,"")) | H10: =IF(OR(G10="",B10=""),"",MAX(0,B10-G10)) | I10: =IF(H10="","",IF(H10=0,0,(YEAR(B10)-YEAR(G10))*12+MONTH(B10)-MONTH(G10)+IF(DAY(B10)>DAY(G10),1,0))) | J10: =IF(I10="","",IF(D10>0,D10*Setup!$B$12*I10,0))
F11: =IF(OR(A11="",B11=""),"",IFERROR(INDEX(Setup!$B$19:$B$30,A11),"Prior period")) | G11: =IF(OR(A11="",B11=""),"",IFERROR(INDEX(Setup!$E$19:$E$30,A11)+0,"")) | H11: =IF(OR(G11="",B11=""),"",MAX(0,B11-G11)) | I11: =IF(H11="","",IF(H11=0,0,(YEAR(B11)-YEAR(G11))*12+MONTH(B11)-MONTH(G11)+IF(DAY(B11)>DAY(G11),1,0))) | J11: =IF(I11="","",IF(D11>0,D11*Setup!$B$12*I11,0))
F12: =IF(OR(A12="",B12=""),"",IFERROR(INDEX(Setup!$B$19:$B$30,A12),"Prior period")) | G12: =IF(OR(A12="",B12=""),"",IFERROR(INDEX(Setup!$E$19:$E$30,A12)+0,"")) | H12: =IF(OR(G12="",B12=""),"",MAX(0,B12-G12)) | I12: =IF(H12="","",IF(H12=0,0,(YEAR(B12)-YEAR(G12))*12+MONTH(B12)-MONTH(G12)+IF(DAY(B12)>DAY(G12),1,0))) | J12: =IF(I12="","",IF(D12>0,D12*Setup!$B$12*I12,0))
F13: =IF(OR(A13="",B13=""),"",IFERROR(INDEX(Setup!$B$19:$B$30,A13),"Prior period")) | G13: =IF(OR(A13="",B13=""),"",IFERROR(INDEX(Setup!$E$19:$E$30,A13)+0,"")) | H13: =IF(OR(G13="",B13=""),"",MAX(0,B13-G13)) | I13: =IF(H13="","",IF(H13=0,0,(YEAR(B13)-YEAR(G13))*12+MONTH(B13)-MONTH(G13)+IF(DAY(B13)>DAY(G13),1,0))) | J13: =IF(I13="","",IF(D13>0,D13*Setup!$B$12*I13,0))
F14: =IF(OR(A14="",B14=""),"",IFERROR(INDEX(Setup!$B$19:$B$30,A14),"Prior period")) | G14: =IF(OR(A14="",B14=""),"",IFERROR(INDEX(Setup!$E$19:$E$30,A14)+0,"")) | H14: =IF(OR(G14="",B14=""),"",MAX(0,B14-G14)) | I14: =IF(H14="","",IF(H14=0,0,(YEAR(B14)-YEAR(G14))*12+MONTH(B14)-MONTH(G14)+IF(DAY(B14)>DAY(G14),1,0))) | J14: =IF(I14="","",IF(D14>0,D14*Setup!$B$12*I14,0))
F15: =IF(OR(A15="",B15=""),"",IFERROR(INDEX(Setup!$B$19:$B$30,A15),"Prior period")) | G15: =IF(OR(A15="",B15=""),"",IFERROR(INDEX(Setup!$E$19:$E$30,A15)+0,"")) | H15: =IF(OR(G15="",B15=""),"",MAX(0,B15-G15)) | I15: =IF(H15="","",IF(H15=0,0,(YEAR(B15)-YEAR(G15))*12+MONTH(B15)-MONTH(G15)+IF(DAY(B15)>DAY(G15),1,0))) | J15: =IF(I15="","",IF(D15>0,D15*Setup!$B$12*I15,0))
F16: =IF(OR(A16="",B16=""),"",IFERROR(INDEX(Setup!$B$19:$B$30,A16),"Prior period")) | G16: =IF(OR(A16="",B16=""),"",IFERROR(INDEX(Setup!$E$19:$E$30,A16)+0,"")) | H16: =IF(OR(G16="",B16=""),"",MAX(0,B16-G16)) | I16: =IF(H16="","",IF(H16=0,0,(YEAR(B16)-YEAR(G16))*12+MONTH(B16)-MONTH(G16)+IF(DAY(B16)>DAY(G16),1,0))) | J16: =IF(I16="","",IF(D16>0,D16*Setup!$B$12*I16,0))
F17: =IF(OR(A17="",B17=""),"",IFERROR(INDEX(Setup!$B$19:$B$30,A17),"Prior period")) | G17: =IF(OR(A17="",B17=""),"",IFERROR(INDEX(Setup!$E$19:$E$30,A17)+0,"")) | H17: =IF(OR(G17="",B17=""),"",MAX(0,B17-G17)) | I17: =IF(H17="","",IF(H17=0,0,(YEAR(B17)-YEAR(G17))*12+MONTH(B17)-MONTH(G17)+IF(DAY(B17)>DAY(G17),1,0))) | J17: =IF(I17="","",IF(D17>0,D17*Setup!$B$12*I17,0))
F18: =IF(OR(A18="",B18=""),"",IFERROR(INDEX(Setup!$B$19:$B$30,A18),"Prior period")) | G18: =IF(OR(A18="",B18=""),"",IFERROR(INDEX(Setup!$E$19:$E$30,A18)+0,"")) | H18: =IF(OR(G18="",B18=""),"",MAX(0,B18-G18)) | I18: =IF(H18="","",IF(H18=0,0,(YEAR(B18)-YEAR(G18))*12+MONTH(B18)-MONTH(G18)+IF(DAY(B18)>DAY(G18),1,0))) | J18: =IF(I18="","",IF(D18>0,D18*Setup!$B$12*I18,0))
... F505: =IF(OR(A505="",B505=""),"",IFERROR(INDEX(Setup!$B$19:$B$30,A505),"Prior period")) | G505: =IF(OR(A505="",B505=""),"",IFERROR(INDEX(Setup!$E$19:$E$30,A505)+0,"")) | H505: =IF(OR(G505="",B505=""),"",MAX(0,B505-G505)) | I505: =IF(H505="","",IF(H505=0,0,(YEAR(B505)-YEAR(G505))*12+MONTH(B505)-MONTH(G505)+IF(DAY(B505)>DAY(G505),1,0))) | J505: =IF(I505="","",IF(D505>0,D505*Setup!$B$12*I505,0))

Sheet Recon_Sales
A1: Sales Reconciliation – Returns vs Register vs Trial Balance
A2: For each VAT box: what you DECLARED vs what you INVOICED vs what you BOOKED. ZATCA starts its audit here.
A4: Box 1 – Standard 15% (Box 1)
A5: Period # | B5: Period | C5: Per VAT Return (net) | D5: Per Sales Register | E5: Per Trial Balance | F5: Return − Register | G5: Return − TB | H5: Status
A6: =IF(Setup!C19="","",Setup!A19) | B6: =Setup!B19 | C6: =IF($A6="","",VAT_Returns!F6+VAT_Returns!G6) | D6: =IF($A6="","",SUMIFS(Sales_Register!$H$6:$H$5005,Sales_Register!$O$6:$O$5005,$A6,Sales_Register!$G$6:$G$5005,"Standard 15% (Box 1)")) | E6: =IF($A6="","",-SUMPRODUCT((TB_Monthly!$D$6:$D$505="Standard 15% (Box 1)")*(TB_Monthly!$F$4:$Q$4>=Setup!$C$19)*(TB_Monthly!$F$4:$Q$4<=Setup!$D$19)*TB_Monthly!$F$6:$Q$505)) | F6: =IF($A6="","",C6-D6) | G6: =IF($A6="","",C6-E6) | H6: =IF($A6="","",IF(AND(C6=0,D6=0,E6=0),"– No activity",IF(AND(ABS(F6)<=Setup!$B$10,ABS(G6)<=Setup!$B$10),"✓ Matched","✗ Investigate")))
A7: =IF(Setup!C20="","",Setup!A20) | B7: =Setup!B20 | C7: =IF($A7="","",VAT_Returns!F7+VAT_Returns!G7) | D7: =IF($A7="","",SUMIFS(Sales_Register!$H$6:$H$5005,Sales_Register!$O$6:$O$5005,$A7,Sales_Register!$G$6:$G$5005,"Standard 15% (Box 1)")) | E7: =IF($A7="","",-SUMPRODUCT((TB_Monthly!$D$6:$D$505="Standard 15% (Box 1)")*(TB_Monthly!$F$4:$Q$4>=Setup!$C$20)*(TB_Monthly!$F$4:$Q$4<=Setup!$D$20)*TB_Monthly!$F$6:$Q$505)) | F7: =IF($A7="","",C7-D7) | G7: =IF($A7="","",C7-E7) | H7: =IF($A7="","",IF(AND(C7=0,D7=0,E7=0),"– No activity",IF(AND(ABS(F7)<=Setup!$B$10,ABS(G7)<=Setup!$B$10),"✓ Matched","✗ Investigate")))
A8: =IF(Setup!C21="","",Setup!A21) | B8: =Setup!B21 | C8: =IF($A8="","",VAT_Returns!F8+VAT_Returns!G8) | D8: =IF($A8="","",SUMIFS(Sales_Register!$H$6:$H$5005,Sales_Register!$O$6:$O$5005,$A8,Sales_Register!$G$6:$G$5005,"Standard 15% (Box 1)")) | E8: =IF($A8="","",-SUMPRODUCT((TB_Monthly!$D$6:$D$505="Standard 15% (Box 1)")*(TB_Monthly!$F$4:$Q$4>=Setup!$C$21)*(TB_Monthly!$F$4:$Q$4<=Setup!$D$21)*TB_Monthly!$F$6:$Q$505)) | F8: =IF($A8="","",C8-D8) | G8: =IF($A8="","",C8-E8) | H8: =IF($A8="","",IF(AND(C8=0,D8=0,E8=0),"– No activity",IF(AND(ABS(F8)<=Setup!$B$10,ABS(G8)<=Setup!$B$10),"✓ Matched","✗ Investigate")))
A9: =IF(Setup!C22="","",Setup!A22) | B9: =Setup!B22 | C9: =IF($A9="","",VAT_Returns!F9+VAT_Returns!G9) | D9: =IF($A9="","",SUMIFS(Sales_Register!$H$6:$H$5005,Sales_Register!$O$6:$O$5005,$A9,Sales_Register!$G$6:$G$5005,"Standard 15% (Box 1)")) | E9: =IF($A9="","",-SUMPRODUCT((TB_Monthly!$D$6:$D$505="Standard 15% (Box 1)")*(TB_Monthly!$F$4:$Q$4>=Setup!$C$22)*(TB_Monthly!$F$4:$Q$4<=Setup!$D$22)*TB_Monthly!$F$6:$Q$505)) | F9: =IF($A9="","",C9-D9) | G9: =IF($A9="","",C9-E9) | H9: =IF($A9="","",IF(AND(C9=0,D9=0,E9=0),"– No activity",IF(AND(ABS(F9)<=Setup!$B$10,ABS(G9)<=Setup!$B$10),"✓ Matched","✗ Investigate")))
A10: =IF(Setup!C23="","",Setup!A23) | B10: =Setup!B23 | C10: =IF($A10="","",VAT_Returns!F10+VAT_Returns!G10) | D10: =IF($A10="","",SUMIFS(Sales_Register!$H$6:$H$5005,Sales_Register!$O$6:$O$5005,$A10,Sales_Register!$G$6:$G$5005,"Standard 15% (Box 1)")) | E10: =IF($A10="","",-SUMPRODUCT((TB_Monthly!$D$6:$D$505="Standard 15% (Box 1)")*(TB_Monthly!$F$4:$Q$4>=Setup!$C$23)*(TB_Monthly!$F$4:$Q$4<=Setup!$D$23)*TB_Monthly!$F$6:$Q$505)) | F10: =IF($A10="","",C10-D10) | G10: =IF($A10="","",C10-E10) | H10: =IF($A10="","",IF(AND(C10=0,D10=0,E10=0),"– No activity",IF(AND(ABS(F10)<=Setup!$B$10,ABS(G10)<=Setup!$B$10),"✓ Matched","✗ Investigate")))
A11: =IF(Setup!C24="","",Setup!A24) | B11: =Setup!B24 | C11: =IF($A11="","",VAT_Returns!F11+VAT_Returns!G11) | D11: =IF($A11="","",SUMIFS(Sales_Register!$H$6:$H$5005,Sales_Register!$O$6:$O$5005,$A11,Sales_Register!$G$6:$G$5005,"Standard 15% (Box 1)")) | E11: =IF($A11="","",-SUMPRODUCT((TB_Monthly!$D$6:$D$505="Standard 15% (Box 1)")*(TB_Monthly!$F$4:$Q$4>=Setup!$C$24)*(TB_Monthly!$F$4:$Q$4<=Setup!$D$24)*TB_Monthly!$F$6:$Q$505)) | F11: =IF($A11="","",C11-D11) | G11: =IF($A11="","",C11-E11) | H11: =IF($A11="","",IF(AND(C11=0,D11=0,E11=0),"– No activity",IF(AND(ABS(F11)<=Setup!$B$10,ABS(G11)<=Setup!$B$10),"✓ Matched","✗ Investigate")))
A12: =IF(Setup!C25="","",Setup!A25) | B12: =Setup!B25 | C12: =IF($A12="","",VAT_Returns!F12+VAT_Returns!G12) | D12: =IF($A12="","",SUMIFS(Sales_Register!$H$6:$H$5005,Sales_Register!$O$6:$O$5005,$A12,Sales_Register!$G$6:$G$5005,"Standard 15% (Box 1)")) | E12: =IF($A12="","",-SUMPRODUCT((TB_Monthly!$D$6:$D$505="Standard 15% (Box 1)")*(TB_Monthly!$F$4:$Q$4>=Setup!$C$25)*(TB_Monthly!$F$4:$Q$4<=Setup!$D$25)*TB_Monthly!$F$6:$Q$505)) | F12: =IF($A12="","",C12-D12) | G12: =IF($A12="","",C12-E12) | H12: =IF($A12="","",IF(AND(C12=0,D12=0,E12=0),"– No activity",IF(AND(ABS(F12)<=Setup!$B$10,ABS(G12)<=Setup!$B$10),"✓ Matched","✗ Investigate")))
A13: =IF(Setup!C26="","",Setup!A26) | B13: =Setup!B26 | C13: =IF($A13="","",VAT_Returns!F13+VAT_Returns!G13) | D13: =IF($A13="","",SUMIFS(Sales_Register!$H$6:$H$5005,Sales_Register!$O$6:$O$5005,$A13,Sales_Register!$G$6:$G$5005,"Standard 15% (Box 1)")) | E13: =IF($A13="","",-SUMPRODUCT((TB_Monthly!$D$6:$D$505="Standard 15% (Box 1)")*(TB_Monthly!$F$4:$Q$4>=Setup!$C$26)*(TB_Monthly!$F$4:$Q$4<=Setup!$D$26)*TB_Monthly!$F$6:$Q$505)) | F13: =IF($A13="","",C13-D13) | G13: =IF($A13="","",C13-E13) | H13: =IF($A13="","",IF(AND(C13=0,D13=0,E13=0),"– No activity",IF(AND(ABS(F13)<=Setup!$B$10,ABS(G13)<=Setup!$B$10),"✓ Matched","✗ Investigate")))
A14: =IF(Setup!C27="","",Setup!A27) | B14: =Setup!B27 | C14: =IF($A14="","",VAT_Returns!F14+VAT_Returns!G14) | D14: =IF($A14="","",SUMIFS(Sales_Register!$H$6:$H$5005,Sales_Register!$O$6:$O$5005,$A14,Sales_Register!$G$6:$G$5005,"Standard 15% (Box 1)")) | E14: =IF($A14="","",-SUMPRODUCT((TB_Monthly!$D$6:$D$505="Standard 15% (Box 1)")*(TB_Monthly!$F$4:$Q$4>=Setup!$C$27)*(TB_Monthly!$F$4:$Q$4<=Setup!$D$27)*TB_Monthly!$F$6:$Q$505)) | F14: =IF($A14="","",C14-D14) | G14: =IF($A14="","",C14-E14) | H14: =IF($A14="","",IF(AND(C14=0,D14=0,E14=0),"– No activity",IF(AND(ABS(F14)<=Setup!$B$10,ABS(G14)<=Setup!$B$10),"✓ Matched","✗ Investigate")))
A15: =IF(Setup!C28="","",Setup!A28) | B15: =Setup!B28 | C15: =IF($A15="","",VAT_Returns!F15+VAT_Returns!G15) | D15: =IF($A15="","",SUMIFS(Sales_Register!$H$6:$H$5005,Sales_Register!$O$6:$O$5005,$A15,Sales_Register!$G$6:$G$5005,"Standard 15% (Box 1)")) | E15: =IF($A15="","",-SUMPRODUCT((TB_Monthly!$D$6:$D$505="Standard 15% (Box 1)")*(TB_Monthly!$F$4:$Q$4>=Setup!$C$28)*(TB_Monthly!$F$4:$Q$4<=Setup!$D$28)*TB_Monthly!$F$6:$Q$505)) | F15: =IF($A15="","",C15-D15) | G15: =IF($A15="","",C15-E15) | H15: =IF($A15="","",IF(AND(C15=0,D15=0,E15=0),"– No activity",IF(AND(ABS(F15)<=Setup!$B$10,ABS(G15)<=Setup!$B$10),"✓ Matched","✗ Investigate")))
A16: =IF(Setup!C29="","",Setup!A29) | B16: =Setup!B29 | C16: =IF($A16="","",VAT_Returns!F16+VAT_Returns!G16) | D16: =IF($A16="","",SUMIFS(Sales_Register!$H$6:$H$5005,Sales_Register!$O$6:$O$5005,$A16,Sales_Register!$G$6:$G$5005,"Standard 15% (Box 1)")) | E16: =IF($A16="","",-SUMPRODUCT((TB_Monthly!$D$6:$D$505="Standard 15% (Box 1)")*(TB_Monthly!$F$4:$Q$4>=Setup!$C$29)*(TB_Monthly!$F$4:$Q$4<=Setup!$D$29)*TB_Monthly!$F$6:$Q$505)) | F16: =IF($A16="","",C16-D16) | G16: =IF($A16="","",C16-E16) | H16: =IF($A16="","",IF(AND(C16=0,D16=0,E16=0),"– No activity",IF(AND(ABS(F16)<=Setup!$B$10,ABS(G16)<=Setup!$B$10),"✓ Matched","✗ Investigate")))
A17: =IF(Setup!C30="","",Setup!A30) | B17: =Setup!B30 | C17: =IF($A17="","",VAT_Returns!F17+VAT_Returns!G17) | D17: =IF($A17="","",SUMIFS(Sales_Register!$H$6:$H$5005,Sales_Register!$O$6:$O$5005,$A17,Sales_Register!$G$6:$G$5005,"Standard 15% (Box 1)")) | E17: =IF($A17="","",-SUMPRODUCT((TB_Monthly!$D$6:$D$505="Standard 15% (Box 1)")*(TB_Monthly!$F$4:$Q$4>=Setup!$C$30)*(TB_Monthly!$F$4:$Q$4<=Setup!$D$30)*TB_Monthly!$F$6:$Q$505)) | F17: =IF($A17="","",C17-D17) | G17: =IF($A17="","",C17-E17) | H17: =IF($A17="","",IF(AND(C17=0,D17=0,E17=0),"– No activity",IF(AND(ABS(F17)<=Setup!$B$10,ABS(G17)<=Setup!$B$10),"✓ Matched","✗ Investigate")))
B18: TOTAL | C18: =SUM(C6:C17) | D18: =SUM(D6:D17) | E18: =SUM(E6:E17) | F18: =SUM(F6:F17) | G18: =SUM(G6:G17) | H18: =IF(AND(ABS(F18)<=Setup!$B$10,ABS(G18)<=Setup!$B$10),"✓ Matched","✗ Investigate")
A20: Box 2 – Citizens - Healthcare/Education (Box 2)
A21: Period # | B21: Period | C21: Per VAT Return (net) | D21: Per Sales Register | E21: Per Trial Balance | F21: Return − Register | G21: Return − TB | H21: Status
A22: =IF(Setup!C19="","",Setup!A19) | B22: =Setup!B19 | C22: =IF($A22="","",VAT_Returns!I6+VAT_Returns!J6) | D22: =IF($A22="","",SUMIFS(Sales_Register!$H$6:$H$5005,Sales_Register!$O$6:$O$5005,$A22,Sales_Register!$G$6:$G$5005,"Citizens - Healthcare/Education (Box 2)")) | E22: =IF($A22="","",-SUMPRODUCT((TB_Monthly!$D$6:$D$505="Citizens - Healthcare/Education (Box 2)")*(TB_Monthly!$F$4:$Q$4>=Setup!$C$19)*(TB_Monthly!$F$4:$Q$4<=Setup!$D$19)*TB_Monthly!$F$6:$Q$505)) | F22: =IF($A22="","",C22-D22) | G22: =IF($A22="","",C22-E22) | H22: =IF($A22="","",IF(AND(C22=0,D22=0,E22=0),"– No activity",IF(AND(ABS(F22)<=Setup!$B$10,ABS(G22)<=Setup!$B$10),"✓ Matched","✗ Investigate")))
A23: =IF(Setup!C20="","",Setup!A20) | B23: =Setup!B20 | C23: =IF($A23="","",VAT_Returns!I7+VAT_Returns!J7) | D23: =IF($A23="","",SUMIFS(Sales_Register!$H$6:$H$5005,Sales_Register!$O$6:$O$5005,$A23,Sales_Register!$G$6:$G$5005,"Citizens - Healthcare/Education (Box 2)")) | E23: =IF($A23="","",-SUMPRODUCT((TB_Monthly!$D$6:$D$505="Citizens - Healthcare/Education (Box 2)")*(TB_Monthly!$F$4:$Q$4>=Setup!$C$20)*(TB_Monthly!$F$4:$Q$4<=Setup!$D$20)*TB_Monthly!$F$6:$Q$505)) | F23: =IF($A23="","",C23-D23) | G23: =IF($A23="","",C23-E23) | H23: =IF($A23="","",IF(AND(C23=0,D23=0,E23=0),"– No activity",IF(AND(ABS(F23)<=Setup!$B$10,ABS(G23)<=Setup!$B$10),"✓ Matched","✗ Investigate")))
A24: =IF(Setup!C21="","",Setup!A21) | B24: =Setup!B21 | C24: =IF($A24="","",VAT_Returns!I8+VAT_Returns!J8) | D24: =IF($A24="","",SUMIFS(Sales_Register!$H$6:$H$5005,Sales_Register!$O$6:$O$5005,$A24,Sales_Register!$G$6:$G$5005,"Citizens - Healthcare/Education (Box 2)")) | E24: =IF($A24="","",-SUMPRODUCT((TB_Monthly!$D$6:$D$505="Citizens - Healthcare/Education (Box 2)")*(TB_Monthly!$F$4:$Q$4>=Setup!$C$21)*(TB_Monthly!$F$4:$Q$4<=Setup!$D$21)*TB_Monthly!$F$6:$Q$505)) | F24: =IF($A24="","",C24-D24) | G24: =IF($A24="","",C24-E24) | H24: =IF($A24="","",IF(AND(C24=0,D24=0,E24=0),"– No activity",IF(AND(ABS(F24)<=Setup!$B$10,ABS(G24)<=Setup!$B$10),"✓ Matched","✗ Investigate")))
A25: =IF(Setup!C22="","",Setup!A22) | B25: =Setup!B22 | C25: =IF($A25="","",VAT_Returns!I9+VAT_Returns!J9) | D25: =IF($A25="","",SUMIFS(Sales_Register!$H$6:$H$5005,Sales_Register!$O$6:$O$5005,$A25,Sales_Register!$G$6:$G$5005,"Citizens - Healthcare/Education (Box 2)")) | E25: =IF($A25="","",-SUMPRODUCT((TB_Monthly!$D$6:$D$505="Citizens - Healthcare/Education (Box 2)")*(TB_Monthly!$F$4:$Q$4>=Setup!$C$22)*(TB_Monthly!$F$4:$Q$4<=Setup!$D$22)*TB_Monthly!$F$6:$Q$505)) | F25: =IF($A25="","",C25-D25) | G25: =IF($A25="","",C25-E25) | H25: =IF($A25="","",IF(AND(C25=0,D25=0,E25=0),"– No activity",IF(AND(ABS(F25)<=Setup!$B$10,ABS(G25)<=Setup!$B$10),"✓ Matched","✗ Investigate")))
A26: =IF(Setup!C23="","",Setup!A23) | B26: =Setup!B23 | C26: =IF($A26="","",VAT_Returns!I10+VAT_Returns!J10) | D26: =IF($A26="","",SUMIFS(Sales_Register!$H$6:$H$5005,Sales_Register!$O$6:$O$5005,$A26,Sales_Register!$G$6:$G$5005,"Citizens - Healthcare/Education (Box 2)")) | E26: =IF($A26="","",-SUMPRODUCT((TB_Monthly!$D$6:$D$505="Citizens - Healthcare/Education (Box 2)")*(TB_Monthly!$F$4:$Q$4>=Setup!$C$23)*(TB_Monthly!$F$4:$Q$4<=Setup!$D$23)*TB_Monthly!$F$6:$Q$505)) | F26: =IF($A26="","",C26-D26) | G26: =IF($A26="","",C26-E26) | H26: =IF($A26="","",IF(AND(C26=0,D26=0,E26=0),"– No activity",IF(AND(ABS(F26)<=Setup!$B$10,ABS(G26)<=Setup!$B$10),"✓ Matched","✗ Investigate")))
A27: =IF(Setup!C24="","",Setup!A24) | B27: =Setup!B24 | C27: =IF($A27="","",VAT_Returns!I11+VAT_Returns!J11) | D27: =IF($A27="","",SUMIFS(Sales_Register!$H$6:$H$5005,Sales_Register!$O$6:$O$5005,$A27,Sales_Register!$G$6:$G$5005,"Citizens - Healthcare/Education (Box 2)")) | E27: =IF($A27="","",-SUMPRODUCT((TB_Monthly!$D$6:$D$505="Citizens - Healthcare/Education (Box 2)")*(TB_Monthly!$F$4:$Q$4>=Setup!$C$24)*(TB_Monthly!$F$4:$Q$4<=Setup!$D$24)*TB_Monthly!$F$6:$Q$505)) | F27: =IF($A27="","",C27-D27) | G27: =IF($A27="","",C27-E27) | H27: =IF($A27="","",IF(AND(C27=0,D27=0,E27=0),"– No activity",IF(AND(ABS(F27)<=Setup!$B$10,ABS(G27)<=Setup!$B$10),"✓ Matched","✗ Investigate")))
A28: =IF(Setup!C25="","",Setup!A25) | B28: =Setup!B25 | C28: =IF($A28="","",VAT_Returns!I12+VAT_Returns!J12) | D28: =IF($A28="","",SUMIFS(Sales_Register!$H$6:$H$5005,Sales_Register!$O$6:$O$5005,$A28,Sales_Register!$G$6:$G$5005,"Citizens - Healthcare/Education (Box 2)")) | E28: =IF($A28="","",-SUMPRODUCT((TB_Monthly!$D$6:$D$505="Citizens - Healthcare/Education (Box 2)")*(TB_Monthly!$F$4:$Q$4>=Setup!$C$25)*(TB_Monthly!$F$4:$Q$4<=Setup!$D$25)*TB_Monthly!$F$6:$Q$505)) | F28: =IF($A28="","",C28-D28) | G28: =IF($A28="","",C28-E28) | H28: =IF($A28="","",IF(AND(C28=0,D28=0,E28=0),"– No activity",IF(AND(ABS(F28)<=Setup!$B$10,ABS(G28)<=Setup!$B$10),"✓ Matched","✗ Investigate")))
A29: =IF(Setup!C26="","",Setup!A26) | B29: =Setup!B26 | C29: =IF($A29="","",VAT_Returns!I13+VAT_Returns!J13) | D29: =IF($A29="","",SUMIFS(Sales_Register!$H$6:$H$5005,Sales_Register!$O$6:$O$5005,$A29,Sales_Register!$G$6:$G$5005,"Citizens - Healthcare/Education (Box 2)")) | E29: =IF($A29="","",-SUMPRODUCT((TB_Monthly!$D$6:$D$505="Citizens - Healthcare/Education (Box 2)")*(TB_Monthly!$F$4:$Q$4>=Setup!$C$26)*(TB_Monthly!$F$4:$Q$4<=Setup!$D$26)*TB_Monthly!$F$6:$Q$505)) | F29: =IF($A29="","",C29-D29) | G29: =IF($A29="","",C29-E29) | H29: =IF($A29="","",IF(AND(C29=0,D29=0,E29=0),"– No activity",IF(AND(ABS(F29)<=Setup!$B$10,ABS(G29)<=Setup!$B$10),"✓ Matched","✗ Investigate")))
A30: =IF(Setup!C27="","",Setup!A27) | B30: =Setup!B27 | C30: =IF($A30="","",VAT_Returns!I14+VAT_Returns!J14) | D30: =IF($A30="","",SUMIFS(Sales_Register!$H$6:$H$5005,Sales_Register!$O$6:$O$5005,$A30,Sales_Register!$G$6:$G$5005,"Citizens - Healthcare/Education (Box 2)")) | E30: =IF($A30="","",-SUMPRODUCT((TB_Monthly!$D$6:$D$505="Citizens - Healthcare/Education (Box 2)")*(TB_Monthly!$F$4:$Q$4>=Setup!$C$27)*(TB_Monthly!$F$4:$Q$4<=Setup!$D$27)*TB_Monthly!$F$6:$Q$505)) | F30: =IF($A30="","",C30-D30) | G30: =IF($A30="","",C30-E30) | H30: =IF($A30="","",IF(AND(C30=0,D30=0,E30=0),"– No activity",IF(AND(ABS(F30)<=Setup!$B$10,ABS(G30)<=Setup!$B$10),"✓ Matched","✗ Investigate")))
A31: =IF(Setup!C28="","",Setup!A28) | B31: =Setup!B28 | C31: =IF($A31="","",VAT_Returns!I15+VAT_Returns!J15) | D31: =IF($A31="","",SUMIFS(Sales_Register!$H$6:$H$5005,Sales_Register!$O$6:$O$5005,$A31,Sales_Register!$G$6:$G$5005,"Citizens - Healthcare/Education (Box 2)")) | E31: =IF($A31="","",-SUMPRODUCT((TB_Monthly!$D$6:$D$505="Citizens - Healthcare/Education (Box 2)")*(TB_Monthly!$F$4:$Q$4>=Setup!$C$28)*(TB_Monthly!$F$4:$Q$4<=Setup!$D$28)*TB_Monthly!$F$6:$Q$505)) | F31: =IF($A31="","",C31-D31) | G31: =IF($A31="","",C31-E31) | H31: =IF($A31="","",IF(AND(C31=0,D31=0,E31=0),"– No activity",IF(AND(ABS(F31)<=Setup!$B$10,ABS(G31)<=Setup!$B$10),"✓ Matched","✗ Investigate")))
A32: =IF(Setup!C29="","",Setup!A29) | B32: =Setup!B29 | C32: =IF($A32="","",VAT_Returns!I16+VAT_Returns!J16) | D32: =IF($A32="","",SUMIFS(Sales_Register!$H$6:$H$5005,Sales_Register!$O$6:$O$5005,$A32,Sales_Register!$G$6:$G$5005,"Citizens - Healthcare/Education (Box 2)")) | E32: =IF($A32="","",-SUMPRODUCT((TB_Monthly!$D$6:$D$505="Citizens - Healthcare/Education (Box 2)")*(TB_Monthly!$F$4:$Q$4>=Setup!$C$29)*(TB_Monthly!$F$4:$Q$4<=Setup!$D$29)*TB_Monthly!$F$6:$Q$505)) | F32: =IF($A32="","",C32-D32) | G32: =IF($A32="","",C32-E32) | H32: =IF($A32="","",IF(AND(C32=0,D32=0,E32=0),"– No activity",IF(AND(ABS(F32)<=Setup!$B$10,ABS(G32)<=Setup!$B$10),"✓ Matched","✗ Investigate")))
A33: =IF(Setup!C30="","",Setup!A30) | B33: =Setup!B30 | C33: =IF($A33="","",VAT_Returns!I17+VAT_Returns!J17) | D33: =IF($A33="","",SUMIFS(Sales_Register!$H$6:$H$5005,Sales_Register!$O$6:$O$5005,$A33,Sales_Register!$G$6:$G$5005,"Citizens - Healthcare/Education (Box 2)")) | E33: =IF($A33="","",-SUMPRODUCT((TB_Monthly!$D$6:$D$505="Citizens - Healthcare/Education (Box 2)")*(TB_Monthly!$F$4:$Q$4>=Setup!$C$30)*(TB_Monthly!$F$4:$Q$4<=Setup!$D$30)*TB_Monthly!$F$6:$Q$505)) | F33: =IF($A33="","",C33-D33) | G33: =IF($A33="","",C33-E33) | H33: =IF($A33="","",IF(AND(C33=0,D33=0,E33=0),"– No activity",IF(AND(ABS(F33)<=Setup!$B$10,ABS(G33)<=Setup!$B$10),"✓ Matched","✗ Investigate")))
B34: TOTAL | C34: =SUM(C22:C33) | D34: =SUM(D22:D33) | E34: =SUM(E22:E33) | F34: =SUM(F22:F33) | G34: =SUM(G22:G33) | H34: =IF(AND(ABS(F34)<=Setup!$B$10,ABS(G34)<=Setup!$B$10),"✓ Matched","✗ Investigate")
A36: Box 3 – Zero-rated domestic (Box 3)
A37: Period # | B37: Period | C37: Per VAT Return (net) | D37: Per Sales Register | E37: Per Trial Balance | F37: Return − Register | G37: Return − TB | H37: Status
A38: =IF(Setup!C19="","",Setup!A19) | B38: =Setup!B19 | C38: =IF($A38="","",VAT_Returns!L6+VAT_Returns!M6) | D38: =IF($A38="","",SUMIFS(Sales_Register!$H$6:$H$5005,Sales_Register!$O$6:$O$5005,$A38,Sales_Register!$G$6:$G$5005,"Zero-rated domestic (Box 3)")) | E38: =IF($A38="","",-SUMPRODUCT((TB_Monthly!$D$6:$D$505="Zero-rated domestic (Box 3)")*(TB_Monthly!$F$4:$Q$4>=Setup!$C$19)*(TB_Monthly!$F$4:$Q$4<=Setup!$D$19)*TB_Monthly!$F$6:$Q$505)) | F38: =IF($A38="","",C38-D38) | G38: =IF($A38="","",C38-E38) | H38: =IF($A38="","",IF(AND(C38=0,D38=0,E38=0),"– No activity",IF(AND(ABS(F38)<=Setup!$B$10,ABS(G38)<=Setup!$B$10),"✓ Matched","✗ Investigate")))
A39: =IF(Setup!C20="","",Setup!A20) | B39: =Setup!B20 | C39: =IF($A39="","",VAT_Returns!L7+VAT_Returns!M7) | D39: =IF($A39="","",SUMIFS(Sales_Register!$H$6:$H$5005,Sales_Register!$O$6:$O$5005,$A39,Sales_Register!$G$6:$G$5005,"Zero-rated domestic (Box 3)")) | E39: =IF($A39="","",-SUMPRODUCT((TB_Monthly!$D$6:$D$505="Zero-rated domestic (Box 3)")*(TB_Monthly!$F$4:$Q$4>=Setup!$C$20)*(TB_Monthly!$F$4:$Q$4<=Setup!$D$20)*TB_Monthly!$F$6:$Q$505)) | F39: =IF($A39="","",C39-D39) | G39: =IF($A39="","",C39-E39) | H39: =IF($A39="","",IF(AND(C39=0,D39=0,E39=0),"– No activity",IF(AND(ABS(F39)<=Setup!$B$10,ABS(G39)<=Setup!$B$10),"✓ Matched","✗ Investigate")))
A40: =IF(Setup!C21="","",Setup!A21) | B40: =Setup!B21 | C40: =IF($A40="","",VAT_Returns!L8+VAT_Returns!M8) | D40: =IF($A40="","",SUMIFS(Sales_Register!$H$6:$H$5005,Sales_Register!$O$6:$O$5005,$A40,Sales_Register!$G$6:$G$5005,"Zero-rated domestic (Box 3)")) | E40: =IF($A40="","",-SUMPRODUCT((TB_Monthly!$D$6:$D$505="Zero-rated domestic (Box 3)")*(TB_Monthly!$F$4:$Q$4>=Setup!$C$21)*(TB_Monthly!$F$4:$Q$4<=Setup!$D$21)*TB_Monthly!$F$6:$Q$505)) | F40: =IF($A40="","",C40-D40) | G40: =IF($A40="","",C40-E40) | H40: =IF($A40="","",IF(AND(C40=0,D40=0,E40=0),"– No activity",IF(AND(ABS(F40)<=Setup!$B$10,ABS(G40)<=Setup!$B$10),"✓ Matched","✗ Investigate")))
A41: =IF(Setup!C22="","",Setup!A22) | B41: =Setup!B22 | C41: =IF($A41="","",VAT_Returns!L9+VAT_Returns!M9) | D41: =IF($A41="","",SUMIFS(Sales_Register!$H$6:$H$5005,Sales_Register!$O$6:$O$5005,$A41,Sales_Register!$G$6:$G$5005,"Zero-rated domestic (Box 3)")) | E41: =IF($A41="","",-SUMPRODUCT((TB_Monthly!$D$6:$D$505="Zero-rated domestic (Box 3)")*(TB_Monthly!$F$4:$Q$4>=Setup!$C$22)*(TB_Monthly!$F$4:$Q$4<=Setup!$D$22)*TB_Monthly!$F$6:$Q$505)) | F41: =IF($A41="","",C41-D41) | G41: =IF($A41="","",C41-E41) | H41: =IF($A41="","",IF(AND(C41=0,D41=0,E41=0),"– No activity",IF(AND(ABS(F41)<=Setup!$B$10,ABS(G41)<=Setup!$B$10),"✓ Matched","✗ Investigate")))
A42: =IF(Setup!C23="","",Setup!A23) | B42: =Setup!B23 | C42: =IF($A42="","",VAT_Returns!L10+VAT_Returns!M10) | D42: =IF($A42="","",SUMIFS(Sales_Register!$H$6:$H$5005,Sales_Register!$O$6:$O$5005,$A42,Sales_Register!$G$6:$G$5005,"Zero-rated domestic (Box 3)")) | E42: =IF($A42="","",-SUMPRODUCT((TB_Monthly!$D$6:$D$505="Zero-rated domestic (Box 3)")*(TB_Monthly!$F$4:$Q$4>=Setup!$C$23)*(TB_Monthly!$F$4:$Q$4<=Setup!$D$23)*TB_Monthly!$F$6:$Q$505)) | F42: =IF($A42="","",C42-D42) | G42: =IF($A42="","",C42-E42) | H42: =IF($A42="","",IF(AND(C42=0,D42=0,E42=0),"– No activity",IF(AND(ABS(F42)<=Setup!$B$10,ABS(G42)<=Setup!$B$10),"✓ Matched","✗ Investigate")))
A43: =IF(Setup!C24="","",Setup!A24) | B43: =Setup!B24 | C43: =IF($A43="","",VAT_Returns!L11+VAT_Returns!M11) | D43: =IF($A43="","",SUMIFS(Sales_Register!$H$6:$H$5005,Sales_Register!$O$6:$O$5005,$A43,Sales_Register!$G$6:$G$5005,"Zero-rated domestic (Box 3)")) | E43: =IF($A43="","",-SUMPRODUCT((TB_Monthly!$D$6:$D$505="Zero-rated domestic (Box 3)")*(TB_Monthly!$F$4:$Q$4>=Setup!$C$24)*(TB_Monthly!$F$4:$Q$4<=Setup!$D$24)*TB_Monthly!$F$6:$Q$505)) | F43: =IF($A43="","",C43-D43) | G43: =IF($A43="","",C43-E43) | H43: =IF($A43="","",IF(AND(C43=0,D43=0,E43=0),"– No activity",IF(AND(ABS(F43)<=Setup!$B$10,ABS(G43)<=Setup!$B$10),"✓ Matched","✗ Investigate")))
A44: =IF(Setup!C25="","",Setup!A25) | B44: =Setup!B25 | C44: =IF($A44="","",VAT_Returns!L12+VAT_Returns!M12) | D44: =IF($A44="","",SUMIFS(Sales_Register!$H$6:$H$5005,Sales_Register!$O$6:$O$5005,$A44,Sales_Register!$G$6:$G$5005,"Zero-rated domestic (Box 3)")) | E44: =IF($A44="","",-SUMPRODUCT((TB_Monthly!$D$6:$D$505="Zero-rated domestic (Box 3)")*(TB_Monthly!$F$4:$Q$4>=Setup!$C$25)*(TB_Monthly!$F$4:$Q$4<=Setup!$D$25)*TB_Monthly!$F$6:$Q$505)) | F44: =IF($A44="","",C44-D44) | G44: =IF($A44="","",C44-E44) | H44: =IF($A44="","",IF(AND(C44=0,D44=0,E44=0),"– No activity",IF(AND(ABS(F44)<=Setup!$B$10,ABS(G44)<=Setup!$B$10),"✓ Matched","✗ Investigate")))
A45: =IF(Setup!C26="","",Setup!A26) | B45: =Setup!B26 | C45: =IF($A45="","",VAT_Returns!L13+VAT_Returns!M13) | D45: =IF($A45="","",SUMIFS(Sales_Register!$H$6:$H$5005,Sales_Register!$O$6:$O$5005,$A45,Sales_Register!$G$6:$G$5005,"Zero-rated domestic (Box 3)")) | E45: =IF($A45="","",-SUMPRODUCT((TB_Monthly!$D$6:$D$505="Zero-rated domestic (Box 3)")*(TB_Monthly!$F$4:$Q$4>=Setup!$C$26)*(TB_Monthly!$F$4:$Q$4<=Setup!$D$26)*TB_Monthly!$F$6:$Q$505)) | F45: =IF($A45="","",C45-D45) | G45: =IF($A45="","",C45-E45) | H45: =IF($A45="","",IF(AND(C45=0,D45=0,E45=0),"– No activity",IF(AND(ABS(F45)<=Setup!$B$10,ABS(G45)<=Setup!$B$10),"✓ Matched","✗ Investigate")))
A46: =IF(Setup!C27="","",Setup!A27) | B46: =Setup!B27 | C46: =IF($A46="","",VAT_Returns!L14+VAT_Returns!M14) | D46: =IF($A46="","",SUMIFS(Sales_Register!$H$6:$H$5005,Sales_Register!$O$6:$O$5005,$A46,Sales_Register!$G$6:$G$5005,"Zero-rated domestic (Box 3)")) | E46: =IF($A46="","",-SUMPRODUCT((TB_Monthly!$D$6:$D$505="Zero-rated domestic (Box 3)")*(TB_Monthly!$F$4:$Q$4>=Setup!$C$27)*(TB_Monthly!$F$4:$Q$4<=Setup!$D$27)*TB_Monthly!$F$6:$Q$505)) | F46: =IF($A46="","",C46-D46) | G46: =IF($A46="","",C46-E46) | H46: =IF($A46="","",IF(AND(C46=0,D46=0,E46=0),"– No activity",IF(AND(ABS(F46)<=Setup!$B$10,ABS(G46)<=Setup!$B$10),"✓ Matched","✗ Investigate")))
A47: =IF(Setup!C28="","",Setup!A28) | B47: =Setup!B28 | C47: =IF($A47="","",VAT_Returns!L15+VAT_Returns!M15) | D47: =IF($A47="","",SUMIFS(Sales_Register!$H$6:$H$5005,Sales_Register!$O$6:$O$5005,$A47,Sales_Register!$G$6:$G$5005,"Zero-rated domestic (Box 3)")) | E47: =IF($A47="","",-SUMPRODUCT((TB_Monthly!$D$6:$D$505="Zero-rated domestic (Box 3)")*(TB_Monthly!$F$4:$Q$4>=Setup!$C$28)*(TB_Monthly!$F$4:$Q$4<=Setup!$D$28)*TB_Monthly!$F$6:$Q$505)) | F47: =IF($A47="","",C47-D47) | G47: =IF($A47="","",C47-E47) | H47: =IF($A47="","",IF(AND(C47=0,D47=0,E47=0),"– No activity",IF(AND(ABS(F47)<=Setup!$B$10,ABS(G47)<=Setup!$B$10),"✓ Matched","✗ Investigate")))
A48: =IF(Setup!C29="","",Setup!A29) | B48: =Setup!B29 | C48: =IF($A48="","",VAT_Returns!L16+VAT_Returns!M16) | D48: =IF($A48="","",SUMIFS(Sales_Register!$H$6:$H$5005,Sales_Register!$O$6:$O$5005,$A48,Sales_Register!$G$6:$G$5005,"Zero-rated domestic (Box 3)")) | E48: =IF($A48="","",-SUMPRODUCT((TB_Monthly!$D$6:$D$505="Zero-rated domestic (Box 3)")*(TB_Monthly!$F$4:$Q$4>=Setup!$C$29)*(TB_Monthly!$F$4:$Q$4<=Setup!$D$29)*TB_Monthly!$F$6:$Q$505)) | F48: =IF($A48="","",C48-D48) | G48: =IF($A48="","",C48-E48) | H48: =IF($A48="","",IF(AND(C48=0,D48=0,E48=0),"– No activity",IF(AND(ABS(F48)<=Setup!$B$10,ABS(G48)<=Setup!$B$10),"✓ Matched","✗ Investigate")))
A49: =IF(Setup!C30="","",Setup!A30) | B49: =Setup!B30 | C49: =IF($A49="","",VAT_Returns!L17+VAT_Returns!M17) | D49: =IF($A49="","",SUMIFS(Sales_Register!$H$6:$H$5005,Sales_Register!$O$6:$O$5005,$A49,Sales_Register!$G$6:$G$5005,"Zero-rated domestic (Box 3)")) | E49: =IF($A49="","",-SUMPRODUCT((TB_Monthly!$D$6:$D$505="Zero-rated domestic (Box 3)")*(TB_Monthly!$F$4:$Q$4>=Setup!$C$30)*(TB_Monthly!$F$4:$Q$4<=Setup!$D$30)*TB_Monthly!$F$6:$Q$505)) | F49: =IF($A49="","",C49-D49) | G49: =IF($A49="","",C49-E49) | H49: =IF($A49="","",IF(AND(C49=0,D49=0,E49=0),"– No activity",IF(AND(ABS(F49)<=Setup!$B$10,ABS(G49)<=Setup!$B$10),"✓ Matched","✗ Investigate")))
B50: TOTAL | C50: =SUM(C38:C49) | D50: =SUM(D38:D49) | E50: =SUM(E38:E49) | F50: =SUM(F38:F49) | G50: =SUM(G38:G49) | H50: =IF(AND(ABS(F50)<=Setup!$B$10,ABS(G50)<=Setup!$B$10),"✓ Matched","✗ Investigate")
A52: Box 4 – Export (Box 4)
A53: Period # | B53: Period | C53: Per VAT Return (net) | D53: Per Sales Register | E53: Per Trial Balance | F53: Return − Register | G53: Return − TB | H53: Status
A54: =IF(Setup!C19="","",Setup!A19) | B54: =Setup!B19 | C54: =IF($A54="","",VAT_Returns!O6+VAT_Returns!P6) | D54: =IF($A54="","",SUMIFS(Sales_Register!$H$6:$H$5005,Sales_Register!$O$6:$O$5005,$A54,Sales_Register!$G$6:$G$5005,"Export (Box 4)")) | E54: =IF($A54="","",-SUMPRODUCT((TB_Monthly!$D$6:$D$505="Export (Box 4)")*(TB_Monthly!$F$4:$Q$4>=Setup!$C$19)*(TB_Monthly!$F$4:$Q$4<=Setup!$D$19)*TB_Monthly!$F$6:$Q$505)) | F54: =IF($A54="","",C54-D54) | G54: =IF($A54="","",C54-E54) | H54: =IF($A54="","",IF(AND(C54=0,D54=0,E54=0),"– No activity",IF(AND(ABS(F54)<=Setup!$B$10,ABS(G54)<=Setup!$B$10),"✓ Matched","✗ Investigate")))
A55: =IF(Setup!C20="","",Setup!A20) | B55: =Setup!B20 | C55: =IF($A55="","",VAT_Returns!O7+VAT_Returns!P7) | D55: =IF($A55="","",SUMIFS(Sales_Register!$H$6:$H$5005,Sales_Register!$O$6:$O$5005,$A55,Sales_Register!$G$6:$G$5005,"Export (Box 4)")) | E55: =IF($A55="","",-SUMPRODUCT((TB_Monthly!$D$6:$D$505="Export (Box 4)")*(TB_Monthly!$F$4:$Q$4>=Setup!$C$20)*(TB_Monthly!$F$4:$Q$4<=Setup!$D$20)*TB_Monthly!$F$6:$Q$505)) | F55: =IF($A55="","",C55-D55) | G55: =IF($A55="","",C55-E55) | H55: =IF($A55="","",IF(AND(C55=0,D55=0,E55=0),"– No activity",IF(AND(ABS(F55)<=Setup!$B$10,ABS(G55)<=Setup!$B$10),"✓ Matched","✗ Investigate")))
A56: =IF(Setup!C21="","",Setup!A21) | B56: =Setup!B21 | C56: =IF($A56="","",VAT_Returns!O8+VAT_Returns!P8) | D56: =IF($A56="","",SUMIFS(Sales_Register!$H$6:$H$5005,Sales_Register!$O$6:$O$5005,$A56,Sales_Register!$G$6:$G$5005,"Export (Box 4)")) | E56: =IF($A56="","",-SUMPRODUCT((TB_Monthly!$D$6:$D$505="Export (Box 4)")*(TB_Monthly!$F$4:$Q$4>=Setup!$C$21)*(TB_Monthly!$F$4:$Q$4<=Setup!$D$21)*TB_Monthly!$F$6:$Q$505)) | F56: =IF($A56="","",C56-D56) | G56: =IF($A56="","",C56-E56) | H56: =IF($A56="","",IF(AND(C56=0,D56=0,E56=0),"– No activity",IF(AND(ABS(F56)<=Setup!$B$10,ABS(G56)<=Setup!$B$10),"✓ Matched","✗ Investigate")))
A57: =IF(Setup!C22="","",Setup!A22) | B57: =Setup!B22 | C57: =IF($A57="","",VAT_Returns!O9+VAT_Returns!P9) | D57: =IF($A57="","",SUMIFS(Sales_Register!$H$6:$H$5005,Sales_Register!$O$6:$O$5005,$A57,Sales_Register!$G$6:$G$5005,"Export (Box 4)")) | E57: =IF($A57="","",-SUMPRODUCT((TB_Monthly!$D$6:$D$505="Export (Box 4)")*(TB_Monthly!$F$4:$Q$4>=Setup!$C$22)*(TB_Monthly!$F$4:$Q$4<=Setup!$D$22)*TB_Monthly!$F$6:$Q$505)) | F57: =IF($A57="","",C57-D57) | G57: =IF($A57="","",C57-E57) | H57: =IF($A57="","",IF(AND(C57=0,D57=0,E57=0),"– No activity",IF(AND(ABS(F57)<=Setup!$B$10,ABS(G57)<=Setup!$B$10),"✓ Matched","✗ Investigate")))
A58: =IF(Setup!C23="","",Setup!A23) | B58: =Setup!B23 | C58: =IF($A58="","",VAT_Returns!O10+VAT_Returns!P10) | D58: =IF($A58="","",SUMIFS(Sales_Register!$H$6:$H$5005,Sales_Register!$O$6:$O$5005,$A58,Sales_Register!$G$6:$G$5005,"Export (Box 4)")) | E58: =IF($A58="","",-SUMPRODUCT((TB_Monthly!$D$6:$D$505="Export (Box 4)")*(TB_Monthly!$F$4:$Q$4>=Setup!$C$23)*(TB_Monthly!$F$4:$Q$4<=Setup!$D$23)*TB_Monthly!$F$6:$Q$505)) | F58: =IF($A58="","",C58-D58) | G58: =IF($A58="","",C58-E58) | H58: =IF($A58="","",IF(AND(C58=0,D58=0,E58=0),"– No activity",IF(AND(ABS(F58)<=Setup!$B$10,ABS(G58)<=Setup!$B$10),"✓ Matched","✗ Investigate")))
A59: =IF(Setup!C24="","",Setup!A24) | B59: =Setup!B24 | C59: =IF($A59="","",VAT_Returns!O11+VAT_Returns!P11) | D59: =IF($A59="","",SUMIFS(Sales_Register!$H$6:$H$5005,Sales_Register!$O$6:$O$5005,$A59,Sales_Register!$G$6:$G$5005,"Export (Box 4)")) | E59: =IF($A59="","",-SUMPRODUCT((TB_Monthly!$D$6:$D$505="Export (Box 4)")*(TB_Monthly!$F$4:$Q$4>=Setup!$C$24)*(TB_Monthly!$F$4:$Q$4<=Setup!$D$24)*TB_Monthly!$F$6:$Q$505)) | F59: =IF($A59="","",C59-D59) | G59: =IF($A59="","",C59-E59) | H59: =IF($A59="","",IF(AND(C59=0,D59=0,E59=0),"– No activity",IF(AND(ABS(F59)<=Setup!$B$10,ABS(G59)<=Setup!$B$10),"✓ Matched","✗ Investigate")))
A60: =IF(Setup!C25="","",Setup!A25) | B60: =Setup!B25 | C60: =IF($A60="","",VAT_Returns!O12+VAT_Returns!P12) | D60: =IF($A60="","",SUMIFS(Sales_Register!$H$6:$H$5005,Sales_Register!$O$6:$O$5005,$A60,Sales_Register!$G$6:$G$5005,"Export (Box 4)")) | E60: =IF($A60="","",-SUMPRODUCT((TB_Monthly!$D$6:$D$505="Export (Box 4)")*(TB_Monthly!$F$4:$Q$4>=Setup!$C$25)*(TB_Monthly!$F$4:$Q$4<=Setup!$D$25)*TB_Monthly!$F$6:$Q$505)) | F60: =IF($A60="","",C60-D60) | G60: =IF($A60="","",C60-E60) | H60: =IF($A60="","",IF(AND(C60=0,D60=0,E60=0),"– No activity",IF(AND(ABS(F60)<=Setup!$B$10,ABS(G60)<=Setup!$B$10),"✓ Matched","✗ Investigate")))
A61: =IF(Setup!C26="","",Setup!A26) | B61: =Setup!B26 | C61: =IF($A61="","",VAT_Returns!O13+VAT_Returns!P13) | D61: =IF($A61="","",SUMIFS(Sales_Register!$H$6:$H$5005,Sales_Register!$O$6:$O$5005,$A61,Sales_Register!$G$6:$G$5005,"Export (Box 4)")) | E61: =IF($A61="","",-SUMPRODUCT((TB_Monthly!$D$6:$D$505="Export (Box 4)")*(TB_Monthly!$F$4:$Q$4>=Setup!$C$26)*(TB_Monthly!$F$4:$Q$4<=Setup!$D$26)*TB_Monthly!$F$6:$Q$505)) | F61: =IF($A61="","",C61-D61) | G61: =IF($A61="","",C61-E61) | H61: =IF($A61="","",IF(AND(C61=0,D61=0,E61=0),"– No activity",IF(AND(ABS(F61)<=Setup!$B$10,ABS(G61)<=Setup!$B$10),"✓ Matched","✗ Investigate")))
A62: =IF(Setup!C27="","",Setup!A27) | B62: =Setup!B27 | C62: =IF($A62="","",VAT_Returns!O14+VAT_Returns!P14) | D62: =IF($A62="","",SUMIFS(Sales_Register!$H$6:$H$5005,Sales_Register!$O$6:$O$5005,$A62,Sales_Register!$G$6:$G$5005,"Export (Box 4)")) | E62: =IF($A62="","",-SUMPRODUCT((TB_Monthly!$D$6:$D$505="Export (Box 4)")*(TB_Monthly!$F$4:$Q$4>=Setup!$C$27)*(TB_Monthly!$F$4:$Q$4<=Setup!$D$27)*TB_Monthly!$F$6:$Q$505)) | F62: =IF($A62="","",C62-D62) | G62: =IF($A62="","",C62-E62) | H62: =IF($A62="","",IF(AND(C62=0,D62=0,E62=0),"– No activity",IF(AND(ABS(F62)<=Setup!$B$10,ABS(G62)<=Setup!$B$10),"✓ Matched","✗ Investigate")))
A63: =IF(Setup!C28="","",Setup!A28) | B63: =Setup!B28 | C63: =IF($A63="","",VAT_Returns!O15+VAT_Returns!P15) | D63: =IF($A63="","",SUMIFS(Sales_Register!$H$6:$H$5005,Sales_Register!$O$6:$O$5005,$A63,Sales_Register!$G$6:$G$5005,"Export (Box 4)")) | E63: =IF($A63="","",-SUMPRODUCT((TB_Monthly!$D$6:$D$505="Export (Box 4)")*(TB_Monthly!$F$4:$Q$4>=Setup!$C$28)*(TB_Monthly!$F$4:$Q$4<=Setup!$D$28)*TB_Monthly!$F$6:$Q$505)) | F63: =IF($A63="","",C63-D63) | G63: =IF($A63="","",C63-E63) | H63: =IF($A63="","",IF(AND(C63=0,D63=0,E63=0),"– No activity",IF(AND(ABS(F63)<=Setup!$B$10,ABS(G63)<=Setup!$B$10),"✓ Matched","✗ Investigate")))
A64: =IF(Setup!C29="","",Setup!A29) | B64: =Setup!B29 | C64: =IF($A64="","",VAT_Returns!O16+VAT_Returns!P16) | D64: =IF($A64="","",SUMIFS(Sales_Register!$H$6:$H$5005,Sales_Register!$O$6:$O$5005,$A64,Sales_Register!$G$6:$G$5005,"Export (Box 4)")) | E64: =IF($A64="","",-SUMPRODUCT((TB_Monthly!$D$6:$D$505="Export (Box 4)")*(TB_Monthly!$F$4:$Q$4>=Setup!$C$29)*(TB_Monthly!$F$4:$Q$4<=Setup!$D$29)*TB_Monthly!$F$6:$Q$505)) | F64: =IF($A64="","",C64-D64) | G64: =IF($A64="","",C64-E64) | H64: =IF($A64="","",IF(AND(C64=0,D64=0,E64=0),"– No activity",IF(AND(ABS(F64)<=Setup!$B$10,ABS(G64)<=Setup!$B$10),"✓ Matched","✗ Investigate")))
A65: =IF(Setup!C30="","",Setup!A30) | B65: =Setup!B30 | C65: =IF($A65="","",VAT_Returns!O17+VAT_Returns!P17) | D65: =IF($A65="","",SUMIFS(Sales_Register!$H$6:$H$5005,Sales_Register!$O$6:$O$5005,$A65,Sales_Register!$G$6:$G$5005,"Export (Box 4)")) | E65: =IF($A65="","",-SUMPRODUCT((TB_Monthly!$D$6:$D$505="Export (Box 4)")*(TB_Monthly!$F$4:$Q$4>=Setup!$C$30)*(TB_Monthly!$F$4:$Q$4<=Setup!$D$30)*TB_Monthly!$F$6:$Q$505)) | F65: =IF($A65="","",C65-D65) | G65: =IF($A65="","",C65-E65) | H65: =IF($A65="","",IF(AND(C65=0,D65=0,E65=0),"– No activity",IF(AND(ABS(F65)<=Setup!$B$10,ABS(G65)<=Setup!$B$10),"✓ Matched","✗ Investigate")))
B66: TOTAL | C66: =SUM(C54:C65) | D66: =SUM(D54:D65) | E66: =SUM(E54:E65) | F66: =SUM(F54:F65) | G66: =SUM(G54:G65) | H66: =IF(AND(ABS(F66)<=Setup!$B$10,ABS(G66)<=Setup!$B$10),"✓ Matched","✗ Investigate")
A68: Box 5 – Exempt (Box 5)
A69: Period # | B69: Period | C69: Per VAT Return (net) | D69: Per Sales Register | E69: Per Trial Balance | F69: Return − Register | G69: Return − TB | H69: Status
A70: =IF(Setup!C19="","",Setup!A19) | B70: =Setup!B19 | C70: =IF($A70="","",VAT_Returns!R6+VAT_Returns!S6) | D70: =IF($A70="","",SUMIFS(Sales_Register!$H$6:$H$5005,Sales_Register!$O$6:$O$5005,$A70,Sales_Register!$G$6:$G$5005,"Exempt (Box 5)")) | E70: =IF($A70="","",-SUMPRODUCT((TB_Monthly!$D$6:$D$505="Exempt (Box 5)")*(TB_Monthly!$F$4:$Q$4>=Setup!$C$19)*(TB_Monthly!$F$4:$Q$4<=Setup!$D$19)*TB_Monthly!$F$6:$Q$505)) | F70: =IF($A70="","",C70-D70) | G70: =IF($A70="","",C70-E70) | H70: =IF($A70="","",IF(AND(C70=0,D70=0,E70=0),"– No activity",IF(AND(ABS(F70)<=Setup!$B$10,ABS(G70)<=Setup!$B$10),"✓ Matched","✗ Investigate")))
A71: =IF(Setup!C20="","",Setup!A20) | B71: =Setup!B20 | C71: =IF($A71="","",VAT_Returns!R7+VAT_Returns!S7) | D71: =IF($A71="","",SUMIFS(Sales_Register!$H$6:$H$5005,Sales_Register!$O$6:$O$5005,$A71,Sales_Register!$G$6:$G$5005,"Exempt (Box 5)")) | E71: =IF($A71="","",-SUMPRODUCT((TB_Monthly!$D$6:$D$505="Exempt (Box 5)")*(TB_Monthly!$F$4:$Q$4>=Setup!$C$20)*(TB_Monthly!$F$4:$Q$4<=Setup!$D$20)*TB_Monthly!$F$6:$Q$505)) | F71: =IF($A71="","",C71-D71) | G71: =IF($A71="","",C71-E71) | H71: =IF($A71="","",IF(AND(C71=0,D71=0,E71=0),"– No activity",IF(AND(ABS(F71)<=Setup!$B$10,ABS(G71)<=Setup!$B$10),"✓ Matched","✗ Investigate")))
A72: =IF(Setup!C21="","",Setup!A21) | B72: =Setup!B21 | C72: =IF($A72="","",VAT_Returns!R8+VAT_Returns!S8) | D72: =IF($A72="","",SUMIFS(Sales_Register!$H$6:$H$5005,Sales_Register!$O$6:$O$5005,$A72,Sales_Register!$G$6:$G$5005,"Exempt (Box 5)")) | E72: =IF($A72="","",-SUMPRODUCT((TB_Monthly!$D$6:$D$505="Exempt (Box 5)")*(TB_Monthly!$F$4:$Q$4>=Setup!$C$21)*(TB_Monthly!$F$4:$Q$4<=Setup!$D$21)*TB_Monthly!$F$6:$Q$505)) | F72: =IF($A72="","",C72-D72) | G72: =IF($A72="","",C72-E72) | H72: =IF($A72="","",IF(AND(C72=0,D72=0,E72=0),"– No activity",IF(AND(ABS(F72)<=Setup!$B$10,ABS(G72)<=Setup!$B$10),"✓ Matched","✗ Investigate")))
A73: =IF(Setup!C22="","",Setup!A22) | B73: =Setup!B22 | C73: =IF($A73="","",VAT_Returns!R9+VAT_Returns!S9) | D73: =IF($A73="","",SUMIFS(Sales_Register!$H$6:$H$5005,Sales_Register!$O$6:$O$5005,$A73,Sales_Register!$G$6:$G$5005,"Exempt (Box 5)")) | E73: =IF($A73="","",-SUMPRODUCT((TB_Monthly!$D$6:$D$505="Exempt (Box 5)")*(TB_Monthly!$F$4:$Q$4>=Setup!$C$22)*(TB_Monthly!$F$4:$Q$4<=Setup!$D$22)*TB_Monthly!$F$6:$Q$505)) | F73: =IF($A73="","",C73-D73) | G73: =IF($A73="","",C73-E73) | H73: =IF($A73="","",IF(AND(C73=0,D73=0,E73=0),"– No activity",IF(AND(ABS(F73)<=Setup!$B$10,ABS(G73)<=Setup!$B$10),"✓ Matched","✗ Investigate")))
A74: =IF(Setup!C23="","",Setup!A23) | B74: =Setup!B23 | C74: =IF($A74="","",VAT_Returns!R10+VAT_Returns!S10) | D74: =IF($A74="","",SUMIFS(Sales_Register!$H$6:$H$5005,Sales_Register!$O$6:$O$5005,$A74,Sales_Register!$G$6:$G$5005,"Exempt (Box 5)")) | E74: =IF($A74="","",-SUMPRODUCT((TB_Monthly!$D$6:$D$505="Exempt (Box 5)")*(TB_Monthly!$F$4:$Q$4>=Setup!$C$23)*(TB_Monthly!$F$4:$Q$4<=Setup!$D$23)*TB_Monthly!$F$6:$Q$505)) | F74: =IF($A74="","",C74-D74) | G74: =IF($A74="","",C74-E74) | H74: =IF($A74="","",IF(AND(C74=0,D74=0,E74=0),"– No activity",IF(AND(ABS(F74)<=Setup!$B$10,ABS(G74)<=Setup!$B$10),"✓ Matched","✗ Investigate")))
A75: =IF(Setup!C24="","",Setup!A24) | B75: =Setup!B24 | C75: =IF($A75="","",VAT_Returns!R11+VAT_Returns!S11) | D75: =IF($A75="","",SUMIFS(Sales_Register!$H$6:$H$5005,Sales_Register!$O$6:$O$5005,$A75,Sales_Register!$G$6:$G$5005,"Exempt (Box 5)")) | E75: =IF($A75="","",-SUMPRODUCT((TB_Monthly!$D$6:$D$505="Exempt (Box 5)")*(TB_Monthly!$F$4:$Q$4>=Setup!$C$24)*(TB_Monthly!$F$4:$Q$4<=Setup!$D$24)*TB_Monthly!$F$6:$Q$505)) | F75: =IF($A75="","",C75-D75) | G75: =IF($A75="","",C75-E75) | H75: =IF($A75="","",IF(AND(C75=0,D75=0,E75=0),"– No activity",IF(AND(ABS(F75)<=Setup!$B$10,ABS(G75)<=Setup!$B$10),"✓ Matched","✗ Investigate")))
A76: =IF(Setup!C25="","",Setup!A25) | B76: =Setup!B25 | C76: =IF($A76="","",VAT_Returns!R12+VAT_Returns!S12) | D76: =IF($A76="","",SUMIFS(Sales_Register!$H$6:$H$5005,Sales_Register!$O$6:$O$5005,$A76,Sales_Register!$G$6:$G$5005,"Exempt (Box 5)")) | E76: =IF($A76="","",-SUMPRODUCT((TB_Monthly!$D$6:$D$505="Exempt (Box 5)")*(TB_Monthly!$F$4:$Q$4>=Setup!$C$25)*(TB_Monthly!$F$4:$Q$4<=Setup!$D$25)*TB_Monthly!$F$6:$Q$505)) | F76: =IF($A76="","",C76-D76) | G76: =IF($A76="","",C76-E76) | H76: =IF($A76="","",IF(AND(C76=0,D76=0,E76=0),"– No activity",IF(AND(ABS(F76)<=Setup!$B$10,ABS(G76)<=Setup!$B$10),"✓ Matched","✗ Investigate")))
A77: =IF(Setup!C26="","",Setup!A26) | B77: =Setup!B26 | C77: =IF($A77="","",VAT_Returns!R13+VAT_Returns!S13) | D77: =IF($A77="","",SUMIFS(Sales_Register!$H$6:$H$5005,Sales_Register!$O$6:$O$5005,$A77,Sales_Register!$G$6:$G$5005,"Exempt (Box 5)")) | E77: =IF($A77="","",-SUMPRODUCT((TB_Monthly!$D$6:$D$505="Exempt (Box 5)")*(TB_Monthly!$F$4:$Q$4>=Setup!$C$26)*(TB_Monthly!$F$4:$Q$4<=Setup!$D$26)*TB_Monthly!$F$6:$Q$505)) | F77: =IF($A77="","",C77-D77) | G77: =IF($A77="","",C77-E77) | H77: =IF($A77="","",IF(AND(C77=0,D77=0,E77=0),"– No activity",IF(AND(ABS(F77)<=Setup!$B$10,ABS(G77)<=Setup!$B$10),"✓ Matched","✗ Investigate")))
A78: =IF(Setup!C27="","",Setup!A27) | B78: =Setup!B27 | C78: =IF($A78="","",VAT_Returns!R14+VAT_Returns!S14) | D78: =IF($A78="","",SUMIFS(Sales_Register!$H$6:$H$5005,Sales_Register!$O$6:$O$5005,$A78,Sales_Register!$G$6:$G$5005,"Exempt (Box 5)")) | E78: =IF($A78="","",-SUMPRODUCT((TB_Monthly!$D$6:$D$505="Exempt (Box 5)")*(TB_Monthly!$F$4:$Q$4>=Setup!$C$27)*(TB_Monthly!$F$4:$Q$4<=Setup!$D$27)*TB_Monthly!$F$6:$Q$505)) | F78: =IF($A78="","",C78-D78) | G78: =IF($A78="","",C78-E78) | H78: =IF($A78="","",IF(AND(C78=0,D78=0,E78=0),"– No activity",IF(AND(ABS(F78)<=Setup!$B$10,ABS(G78)<=Setup!$B$10),"✓ Matched","✗ Investigate")))
A79: =IF(Setup!C28="","",Setup!A28) | B79: =Setup!B28 | C79: =IF($A79="","",VAT_Returns!R15+VAT_Returns!S15) | D79: =IF($A79="","",SUMIFS(Sales_Register!$H$6:$H$5005,Sales_Register!$O$6:$O$5005,$A79,Sales_Register!$G$6:$G$5005,"Exempt (Box 5)")) | E79: =IF($A79="","",-SUMPRODUCT((TB_Monthly!$D$6:$D$505="Exempt (Box 5)")*(TB_Monthly!$F$4:$Q$4>=Setup!$C$28)*(TB_Monthly!$F$4:$Q$4<=Setup!$D$28)*TB_Monthly!$F$6:$Q$505)) | F79: =IF($A79="","",C79-D79) | G79: =IF($A79="","",C79-E79) | H79: =IF($A79="","",IF(AND(C79=0,D79=0,E79=0),"– No activity",IF(AND(ABS(F79)<=Setup!$B$10,ABS(G79)<=Setup!$B$10),"✓ Matched","✗ Investigate")))
A80: =IF(Setup!C29="","",Setup!A29) | B80: =Setup!B29 | C80: =IF($A80="","",VAT_Returns!R16+VAT_Returns!S16) | D80: =IF($A80="","",SUMIFS(Sales_Register!$H$6:$H$5005,Sales_Register!$O$6:$O$5005,$A80,Sales_Register!$G$6:$G$5005,"Exempt (Box 5)")) | E80: =IF($A80="","",-SUMPRODUCT((TB_Monthly!$D$6:$D$505="Exempt (Box 5)")*(TB_Monthly!$F$4:$Q$4>=Setup!$C$29)*(TB_Monthly!$F$4:$Q$4<=Setup!$D$29)*TB_Monthly!$F$6:$Q$505)) | F80: =IF($A80="","",C80-D80) | G80: =IF($A80="","",C80-E80) | H80: =IF($A80="","",IF(AND(C80=0,D80=0,E80=0),"– No activity",IF(AND(ABS(F80)<=Setup!$B$10,ABS(G80)<=Setup!$B$10),"✓ Matched","✗ Investigate")))
A81: =IF(Setup!C30="","",Setup!A30) | B81: =Setup!B30 | C81: =IF($A81="","",VAT_Returns!R17+VAT_Returns!S17) | D81: =IF($A81="","",SUMIFS(Sales_Register!$H$6:$H$5005,Sales_Register!$O$6:$O$5005,$A81,Sales_Register!$G$6:$G$5005,"Exempt (Box 5)")) | E81: =IF($A81="","",-SUMPRODUCT((TB_Monthly!$D$6:$D$505="Exempt (Box 5)")*(TB_Monthly!$F$4:$Q$4>=Setup!$C$30)*(TB_Monthly!$F$4:$Q$4<=Setup!$D$30)*TB_Monthly!$F$6:$Q$505)) | F81: =IF($A81="","",C81-D81) | G81: =IF($A81="","",C81-E81) | H81: =IF($A81="","",IF(AND(C81=0,D81=0,E81=0),"– No activity",IF(AND(ABS(F81)<=Setup!$B$10,ABS(G81)<=Setup!$B$10),"✓ Matched","✗ Investigate")))
B82: TOTAL | C82: =SUM(C70:C81) | D82: =SUM(D70:D81) | E82: =SUM(E70:E81) | F82: =SUM(F70:F81) | G82: =SUM(G70:G81) | H82: =IF(AND(ABS(F82)<=Setup!$B$10,ABS(G82)<=Setup!$B$10),"✓ Matched","✗ Investigate")
A84: Annual Revenue Reconciliation – Financial Statements vs VAT Returns (مطابقة الإيرادات)
A85: Total revenue per Trial Balance (all accounts with FS Class = Revenue) | E85: =-SUMIF(TB_Monthly!$C$6:$C$505,"Revenue",TB_Monthly!$R$6:$R$505)
A86: Less: revenue mapped as Out of scope / Other income | E86: =-SUMIF(TB_Monthly!$D$6:$D$505,"Revenue - Out of scope / Other income",TB_Monthly!$R$6:$R$505)
A87: Revenue subject to VAT reporting per TB | E87: =E85-E86
A88: Total sales per VAT returns (Box 6, full year) | E88: =VAT_Returns!AM18
A89: Difference before reconciling items | E89: =E87-E88
A90: Explained reconciling items (enter, with + / − sign that reduces the difference):
A91: e.g. Timing – December invoices booked in January | E91: 0
A92: e.g. Revenue accruals not yet invoiced | E92: 0
A93: e.g. Advance payments invoiced (VAT due on receipt) | E93: 0
A94: e.g. Deemed supplies declared but not in revenue | E94: 0
A95: Other (describe) | E95: 0
A96: UNEXPLAINED DIFFERENCE | E96: =E89-SUM(E91:E95) | F96: =IF(ABS(E96)<=Setup!$B$10,"✓ Fully reconciled","✗ Unexplained – ZATCA will treat as undeclared sales")

Sheet Recon_OutputVAT
A1: Output VAT Reconciliation (مطابقة ضريبة المخرجات)
A2: Output VAT declared vs invoiced vs booked in GL vs 15% recomputation. Positive 'Potential under-declaration' = likely assessment.
A4: Period # | B4: Period | C4: Per Return (Box 6 VAT incl. RCM) | D4: Register – Sales VAT | E4: Register – RCM VAT | F4: Register Total | G4: Recomputed 15% × (Box 1 + Box 9) | H4: Per GL (Output VAT accounts) | I4: Return − Register | J4: Return − Recomputed | K4: Return − GL | L4: Status | M4: Potential Under-declaration
A5: =IF(Setup!C19="","",Setup!A19) | B5: =Setup!B19 | C5: =IF($A5="","",VAT_Returns!AN6) | D5: =IF($A5="","",SUMIFS(Sales_Register!$I$6:$I$5005,Sales_Register!$O$6:$O$5005,$A5)) | E5: =IF($A5="","",SUMIFS(Purchase_Register!$I$6:$I$5005,Purchase_Register!$O$6:$O$5005,$A5,Purchase_Register!$F$6:$F$5005,"Import - Reverse charge (Box 9)")) | F5: =IF($A5="","",D5+E5) | G5: =IF($A5="","",ROUND((VAT_Returns!F6+VAT_Returns!G6+VAT_Returns!AA6+VAT_Returns!AB6)*Setup!$B$9,2)) | H5: =IF($A5="","",-SUMPRODUCT((TB_Monthly!$D$6:$D$505="Output VAT")*(TB_Monthly!$F$4:$Q$4>=Setup!$C$19)*(TB_Monthly!$F$4:$Q$4<=Setup!$D$19)*TB_Monthly!$F$6:$Q$505)) | I5: =IF($A5="","",C5-F5) | J5: =IF($A5="","",C5-G5) | K5: =IF($A5="","",C5-H5) | L5: =IF($A5="","",IF(AND(C5=0,F5=0,H5=0),"– No activity",IF(AND(ABS(I5)<=Setup!$B$10,ABS(J5)<=Setup!$B$10,ABS(K5)<=Setup!$B$10),"✓ Matched","✗ Investigate"))) | M5: =IF($A5="","",MAX(0,F5-C5,H5-C5))
A6: =IF(Setup!C20="","",Setup!A20) | B6: =Setup!B20 | C6: =IF($A6="","",VAT_Returns!AN7) | D6: =IF($A6="","",SUMIFS(Sales_Register!$I$6:$I$5005,Sales_Register!$O$6:$O$5005,$A6)) | E6: =IF($A6="","",SUMIFS(Purchase_Register!$I$6:$I$5005,Purchase_Register!$O$6:$O$5005,$A6,Purchase_Register!$F$6:$F$5005,"Import - Reverse charge (Box 9)")) | F6: =IF($A6="","",D6+E6) | G6: =IF($A6="","",ROUND((VAT_Returns!F7+VAT_Returns!G7+VAT_Returns!AA7+VAT_Returns!AB7)*Setup!$B$9,2)) | H6: =IF($A6="","",-SUMPRODUCT((TB_Monthly!$D$6:$D$505="Output VAT")*(TB_Monthly!$F$4:$Q$4>=Setup!$C$20)*(TB_Monthly!$F$4:$Q$4<=Setup!$D$20)*TB_Monthly!$F$6:$Q$505)) | I6: =IF($A6="","",C6-F6) | J6: =IF($A6="","",C6-G6) | K6: =IF($A6="","",C6-H6) | L6: =IF($A6="","",IF(AND(C6=0,F6=0,H6=0),"– No activity",IF(AND(ABS(I6)<=Setup!$B$10,ABS(J6)<=Setup!$B$10,ABS(K6)<=Setup!$B$10),"✓ Matched","✗ Investigate"))) | M6: =IF($A6="","",MAX(0,F6-C6,H6-C6))
A7: =IF(Setup!C21="","",Setup!A21) | B7: =Setup!B21 | C7: =IF($A7="","",VAT_Returns!AN8) | D7: =IF($A7="","",SUMIFS(Sales_Register!$I$6:$I$5005,Sales_Register!$O$6:$O$5005,$A7)) | E7: =IF($A7="","",SUMIFS(Purchase_Register!$I$6:$I$5005,Purchase_Register!$O$6:$O$5005,$A7,Purchase_Register!$F$6:$F$5005,"Import - Reverse charge (Box 9)")) | F7: =IF($A7="","",D7+E7) | G7: =IF($A7="","",ROUND((VAT_Returns!F8+VAT_Returns!G8+VAT_Returns!AA8+VAT_Returns!AB8)*Setup!$B$9,2)) | H7: =IF($A7="","",-SUMPRODUCT((TB_Monthly!$D$6:$D$505="Output VAT")*(TB_Monthly!$F$4:$Q$4>=Setup!$C$21)*(TB_Monthly!$F$4:$Q$4<=Setup!$D$21)*TB_Monthly!$F$6:$Q$505)) | I7: =IF($A7="","",C7-F7) | J7: =IF($A7="","",C7-G7) | K7: =IF($A7="","",C7-H7) | L7: =IF($A7="","",IF(AND(C7=0,F7=0,H7=0),"– No activity",IF(AND(ABS(I7)<=Setup!$B$10,ABS(J7)<=Setup!$B$10,ABS(K7)<=Setup!$B$10),"✓ Matched","✗ Investigate"))) | M7: =IF($A7="","",MAX(0,F7-C7,H7-C7))
A8: =IF(Setup!C22="","",Setup!A22) | B8: =Setup!B22 | C8: =IF($A8="","",VAT_Returns!AN9) | D8: =IF($A8="","",SUMIFS(Sales_Register!$I$6:$I$5005,Sales_Register!$O$6:$O$5005,$A8)) | E8: =IF($A8="","",SUMIFS(Purchase_Register!$I$6:$I$5005,Purchase_Register!$O$6:$O$5005,$A8,Purchase_Register!$F$6:$F$5005,"Import - Reverse charge (Box 9)")) | F8: =IF($A8="","",D8+E8) | G8: =IF($A8="","",ROUND((VAT_Returns!F9+VAT_Returns!G9+VAT_Returns!AA9+VAT_Returns!AB9)*Setup!$B$9,2)) | H8: =IF($A8="","",-SUMPRODUCT((TB_Monthly!$D$6:$D$505="Output VAT")*(TB_Monthly!$F$4:$Q$4>=Setup!$C$22)*(TB_Monthly!$F$4:$Q$4<=Setup!$D$22)*TB_Monthly!$F$6:$Q$505)) | I8: =IF($A8="","",C8-F8) | J8: =IF($A8="","",C8-G8) | K8: =IF($A8="","",C8-H8) | L8: =IF($A8="","",IF(AND(C8=0,F8=0,H8=0),"– No activity",IF(AND(ABS(I8)<=Setup!$B$10,ABS(J8)<=Setup!$B$10,ABS(K8)<=Setup!$B$10),"✓ Matched","✗ Investigate"))) | M8: =IF($A8="","",MAX(0,F8-C8,H8-C8))
A9: =IF(Setup!C23="","",Setup!A23) | B9: =Setup!B23 | C9: =IF($A9="","",VAT_Returns!AN10) | D9: =IF($A9="","",SUMIFS(Sales_Register!$I$6:$I$5005,Sales_Register!$O$6:$O$5005,$A9)) | E9: =IF($A9="","",SUMIFS(Purchase_Register!$I$6:$I$5005,Purchase_Register!$O$6:$O$5005,$A9,Purchase_Register!$F$6:$F$5005,"Import - Reverse charge (Box 9)")) | F9: =IF($A9="","",D9+E9) | G9: =IF($A9="","",ROUND((VAT_Returns!F10+VAT_Returns!G10+VAT_Returns!AA10+VAT_Returns!AB10)*Setup!$B$9,2)) | H9: =IF($A9="","",-SUMPRODUCT((TB_Monthly!$D$6:$D$505="Output VAT")*(TB_Monthly!$F$4:$Q$4>=Setup!$C$23)*(TB_Monthly!$F$4:$Q$4<=Setup!$D$23)*TB_Monthly!$F$6:$Q$505)) | I9: =IF($A9="","",C9-F9) | J9: =IF($A9="","",C9-G9) | K9: =IF($A9="","",C9-H9) | L9: =IF($A9="","",IF(AND(C9=0,F9=0,H9=0),"– No activity",IF(AND(ABS(I9)<=Setup!$B$10,ABS(J9)<=Setup!$B$10,ABS(K9)<=Setup!$B$10),"✓ Matched","✗ Investigate"))) | M9: =IF($A9="","",MAX(0,F9-C9,H9-C9))
A10: =IF(Setup!C24="","",Setup!A24) | B10: =Setup!B24 | C10: =IF($A10="","",VAT_Returns!AN11) | D10: =IF($A10="","",SUMIFS(Sales_Register!$I$6:$I$5005,Sales_Register!$O$6:$O$5005,$A10)) | E10: =IF($A10="","",SUMIFS(Purchase_Register!$I$6:$I$5005,Purchase_Register!$O$6:$O$5005,$A10,Purchase_Register!$F$6:$F$5005,"Import - Reverse charge (Box 9)")) | F10: =IF($A10="","",D10+E10) | G10: =IF($A10="","",ROUND((VAT_Returns!F11+VAT_Returns!G11+VAT_Returns!AA11+VAT_Returns!AB11)*Setup!$B$9,2)) | H10: =IF($A10="","",-SUMPRODUCT((TB_Monthly!$D$6:$D$505="Output VAT")*(TB_Monthly!$F$4:$Q$4>=Setup!$C$24)*(TB_Monthly!$F$4:$Q$4<=Setup!$D$24)*TB_Monthly!$F$6:$Q$505)) | I10: =IF($A10="","",C10-F10) | J10: =IF($A10="","",C10-G10) | K10: =IF($A10="","",C10-H10) | L10: =IF($A10="","",IF(AND(C10=0,F10=0,H10=0),"– No activity",IF(AND(ABS(I10)<=Setup!$B$10,ABS(J10)<=Setup!$B$10,ABS(K10)<=Setup!$B$10),"✓ Matched","✗ Investigate"))) | M10: =IF($A10="","",MAX(0,F10-C10,H10-C10))
A11: =IF(Setup!C25="","",Setup!A25) | B11: =Setup!B25 | C11: =IF($A11="","",VAT_Returns!AN12) | D11: =IF($A11="","",SUMIFS(Sales_Register!$I$6:$I$5005,Sales_Register!$O$6:$O$5005,$A11)) | E11: =IF($A11="","",SUMIFS(Purchase_Register!$I$6:$I$5005,Purchase_Register!$O$6:$O$5005,$A11,Purchase_Register!$F$6:$F$5005,"Import - Reverse charge (Box 9)")) | F11: =IF($A11="","",D11+E11) | G11: =IF($A11="","",ROUND((VAT_Returns!F12+VAT_Returns!G12+VAT_Returns!AA12+VAT_Returns!AB12)*Setup!$B$9,2)) | H11: =IF($A11="","",-SUMPRODUCT((TB_Monthly!$D$6:$D$505="Output VAT")*(TB_Monthly!$F$4:$Q$4>=Setup!$C$25)*(TB_Monthly!$F$4:$Q$4<=Setup!$D$25)*TB_Monthly!$F$6:$Q$505)) | I11: =IF($A11="","",C11-F11) | J11: =IF($A11="","",C11-G11) | K11: =IF($A11="","",C11-H11) | L11: =IF($A11="","",IF(AND(C11=0,F11=0,H11=0),"– No activity",IF(AND(ABS(I11)<=Setup!$B$10,ABS(J11)<=Setup!$B$10,ABS(K11)<=Setup!$B$10),"✓ Matched","✗ Investigate"))) | M11: =IF($A11="","",MAX(0,F11-C11,H11-C11))
A12: =IF(Setup!C26="","",Setup!A26) | B12: =Setup!B26 | C12: =IF($A12="","",VAT_Returns!AN13) | D12: =IF($A12="","",SUMIFS(Sales_Register!$I$6:$I$5005,Sales_Register!$O$6:$O$5005,$A12)) | E12: =IF($A12="","",SUMIFS(Purchase_Register!$I$6:$I$5005,Purchase_Register!$O$6:$O$5005,$A12,Purchase_Register!$F$6:$F$5005,"Import - Reverse charge (Box 9)")) | F12: =IF($A12="","",D12+E12) | G12: =IF($A12="","",ROUND((VAT_Returns!F13+VAT_Returns!G13+VAT_Returns!AA13+VAT_Returns!AB13)*Setup!$B$9,2)) | H12: =IF($A12="","",-SUMPRODUCT((TB_Monthly!$D$6:$D$505="Output VAT")*(TB_Monthly!$F$4:$Q$4>=Setup!$C$26)*(TB_Monthly!$F$4:$Q$4<=Setup!$D$26)*TB_Monthly!$F$6:$Q$505)) | I12: =IF($A12="","",C12-F12) | J12: =IF($A12="","",C12-G12) | K12: =IF($A12="","",C12-H12) | L12: =IF($A12="","",IF(AND(C12=0,F12=0,H12=0),"– No activity",IF(AND(ABS(I12)<=Setup!$B$10,ABS(J12)<=Setup!$B$10,ABS(K12)<=Setup!$B$10),"✓ Matched","✗ Investigate"))) | M12: =IF($A12="","",MAX(0,F12-C12,H12-C12))
A13: =IF(Setup!C27="","",Setup!A27) | B13: =Setup!B27 | C13: =IF($A13="","",VAT_Returns!AN14) | D13: =IF($A13="","",SUMIFS(Sales_Register!$I$6:$I$5005,Sales_Register!$O$6:$O$5005,$A13)) | E13: =IF($A13="","",SUMIFS(Purchase_Register!$I$6:$I$5005,Purchase_Register!$O$6:$O$5005,$A13,Purchase_Register!$F$6:$F$5005,"Import - Reverse charge (Box 9)")) | F13: =IF($A13="","",D13+E13) | G13: =IF($A13="","",ROUND((VAT_Returns!F14+VAT_Returns!G14+VAT_Returns!AA14+VAT_Returns!AB14)*Setup!$B$9,2)) | H13: =IF($A13="","",-SUMPRODUCT((TB_Monthly!$D$6:$D$505="Output VAT")*(TB_Monthly!$F$4:$Q$4>=Setup!$C$27)*(TB_Monthly!$F$4:$Q$4<=Setup!$D$27)*TB_Monthly!$F$6:$Q$505)) | I13: =IF($A13="","",C13-F13) | J13: =IF($A13="","",C13-G13) | K13: =IF($A13="","",C13-H13) | L13: =IF($A13="","",IF(AND(C13=0,F13=0,H13=0),"– No activity",IF(AND(ABS(I13)<=Setup!$B$10,ABS(J13)<=Setup!$B$10,ABS(K13)<=Setup!$B$10),"✓ Matched","✗ Investigate"))) | M13: =IF($A13="","",MAX(0,F13-C13,H13-C13))
A14: =IF(Setup!C28="","",Setup!A28) | B14: =Setup!B28 | C14: =IF($A14="","",VAT_Returns!AN15) | D14: =IF($A14="","",SUMIFS(Sales_Register!$I$6:$I$5005,Sales_Register!$O$6:$O$5005,$A14)) | E14: =IF($A14="","",SUMIFS(Purchase_Register!$I$6:$I$5005,Purchase_Register!$O$6:$O$5005,$A14,Purchase_Register!$F$6:$F$5005,"Import - Reverse charge (Box 9)")) | F14: =IF($A14="","",D14+E14) | G14: =IF($A14="","",ROUND((VAT_Returns!F15+VAT_Returns!G15+VAT_Returns!AA15+VAT_Returns!AB15)*Setup!$B$9,2)) | H14: =IF($A14="","",-SUMPRODUCT((TB_Monthly!$D$6:$D$505="Output VAT")*(TB_Monthly!$F$4:$Q$4>=Setup!$C$28)*(TB_Monthly!$F$4:$Q$4<=Setup!$D$28)*TB_Monthly!$F$6:$Q$505)) | I14: =IF($A14="","",C14-F14) | J14: =IF($A14="","",C14-G14) | K14: =IF($A14="","",C14-H14) | L14: =IF($A14="","",IF(AND(C14=0,F14=0,H14=0),"– No activity",IF(AND(ABS(I14)<=Setup!$B$10,ABS(J14)<=Setup!$B$10,ABS(K14)<=Setup!$B$10),"✓ Matched","✗ Investigate"))) | M14: =IF($A14="","",MAX(0,F14-C14,H14-C14))
A15: =IF(Setup!C29="","",Setup!A29) | B15: =Setup!B29 | C15: =IF($A15="","",VAT_Returns!AN16) | D15: =IF($A15="","",SUMIFS(Sales_Register!$I$6:$I$5005,Sales_Register!$O$6:$O$5005,$A15)) | E15: =IF($A15="","",SUMIFS(Purchase_Register!$I$6:$I$5005,Purchase_Register!$O$6:$O$5005,$A15,Purchase_Register!$F$6:$F$5005,"Import - Reverse charge (Box 9)")) | F15: =IF($A15="","",D15+E15) | G15: =IF($A15="","",ROUND((VAT_Returns!F16+VAT_Returns!G16+VAT_Returns!AA16+VAT_Returns!AB16)*Setup!$B$9,2)) | H15: =IF($A15="","",-SUMPRODUCT((TB_Monthly!$D$6:$D$505="Output VAT")*(TB_Monthly!$F$4:$Q$4>=Setup!$C$29)*(TB_Monthly!$F$4:$Q$4<=Setup!$D$29)*TB_Monthly!$F$6:$Q$505)) | I15: =IF($A15="","",C15-F15) | J15: =IF($A15="","",C15-G15) | K15: =IF($A15="","",C15-H15) | L15: =IF($A15="","",IF(AND(C15=0,F15=0,H15=0),"– No activity",IF(AND(ABS(I15)<=Setup!$B$10,ABS(J15)<=Setup!$B$10,ABS(K15)<=Setup!$B$10),"✓ Matched","✗ Investigate"))) | M15: =IF($A15="","",MAX(0,F15-C15,H15-C15))
A16: =IF(Setup!C30="","",Setup!A30) | B16: =Setup!B30 | C16: =IF($A16="","",VAT_Returns!AN17) | D16: =IF($A16="","",SUMIFS(Sales_Register!$I$6:$I$5005,Sales_Register!$O$6:$O$5005,$A16)) | E16: =IF($A16="","",SUMIFS(Purchase_Register!$I$6:$I$5005,Purchase_Register!$O$6:$O$5005,$A16,Purchase_Register!$F$6:$F$5005,"Import - Reverse charge (Box 9)")) | F16: =IF($A16="","",D16+E16) | G16: =IF($A16="","",ROUND((VAT_Returns!F17+VAT_Returns!G17+VAT_Returns!AA17+VAT_Returns!AB17)*Setup!$B$9,2)) | H16: =IF($A16="","",-SUMPRODUCT((TB_Monthly!$D$6:$D$505="Output VAT")*(TB_Monthly!$F$4:$Q$4>=Setup!$C$30)*(TB_Monthly!$F$4:$Q$4<=Setup!$D$30)*TB_Monthly!$F$6:$Q$505)) | I16: =IF($A16="","",C16-F16) | J16: =IF($A16="","",C16-G16) | K16: =IF($A16="","",C16-H16) | L16: =IF($A16="","",IF(AND(C16=0,F16=0,H16=0),"– No activity",IF(AND(ABS(I16)<=Setup!$B$10,ABS(J16)<=Setup!$B$10,ABS(K16)<=Setup!$B$10),"✓ Matched","✗ Investigate"))) | M16: =IF($A16="","",MAX(0,F16-C16,H16-C16))
B17: TOTAL | C17: =SUM(C5:C16) | D17: =SUM(D5:D16) | E17: =SUM(E5:E16) | F17: =SUM(F5:F16) | G17: =SUM(G5:G16) | H17: =SUM(H5:H16) | I17: =SUM(I5:I16) | J17: =SUM(J5:J16) | K17: =SUM(K5:K16) | L17: =IF(COUNTIF(L5:L16,"✗*")=0,"✓ Matched","✗ Investigate") | M17: =SUM(M5:M16)
A19: Note: Box 2 (citizens' private healthcare/education) VAT is borne by the State and is excluded from the 15% recomputation. GL Output VAT should include RCM output VAT; if you book RCM in a separate account, map it to 'Output VAT' too.

Sheet Recon_InputVAT
A1: Input VAT Reconciliation (مطابقة ضريبة المدخلات)
A2: Input VAT claimed vs register vs GL, plus the portion ZATCA is likely to disallow (no valid invoice, blocked, invalid supplier VAT no).
A4: Period # | B4: Period | C4: Per Return (Box 12 VAT) | D4: Register – VAT Claimed | E4: Register – Defensible VAT | F4: Register – VAT at Risk | G4: Per GL (Input VAT accounts) | H4: Return − Register Claimed | I4: Return − GL | J4: Status | K4: Potential Over-claim (Return − Defensible) | L4: Box 8 VAT per Return | M4: Customs VAT per Register | N4: Box 8 Difference | O4: Box 9 VAT per Return | P4: RCM VAT per Register | Q4: Box 9 Difference
A5: =IF(Setup!C19="","",Setup!A19) | B5: =Setup!B19 | C5: =IF($A5="","",VAT_Returns!AP6) | D5: =IF($A5="","",SUMIFS(Purchase_Register!$R$6:$R$5005,Purchase_Register!$O$6:$O$5005,$A5)) | E5: =IF($A5="","",SUMIFS(Purchase_Register!$S$6:$S$5005,Purchase_Register!$O$6:$O$5005,$A5)) | F5: =IF($A5="","",SUMIFS(Purchase_Register!$T$6:$T$5005,Purchase_Register!$O$6:$O$5005,$A5)) | G5: =IF($A5="","",SUMPRODUCT((TB_Monthly!$D$6:$D$505="Input VAT")*(TB_Monthly!$F$4:$Q$4>=Setup!$C$19)*(TB_Monthly!$F$4:$Q$4<=Setup!$D$19)*TB_Monthly!$F$6:$Q$505)) | H5: =IF($A5="","",C5-D5) | I5: =IF($A5="","",C5-G5) | J5: =IF($A5="","",IF(AND(C5=0,D5=0,G5=0),"– No activity",IF(AND(ABS(H5)<=Setup!$B$10,ABS(I5)<=Setup!$B$10),"✓ Matched","✗ Investigate"))) | K5: =IF($A5="","",MAX(0,C5-E5)) | L5: =IF($A5="","",VAT_Returns!Z6) | M5: =IF($A5="","",SUMIFS(Purchase_Register!$I$6:$I$5005,Purchase_Register!$O$6:$O$5005,$A5,Purchase_Register!$F$6:$F$5005,"Import - VAT paid at customs (Box 8)")) | N5: =IF($A5="","",L5-M5) | O5: =IF($A5="","",VAT_Returns!AC6) | P5: =IF($A5="","",SUMIFS(Purchase_Register!$I$6:$I$5005,Purchase_Register!$O$6:$O$5005,$A5,Purchase_Register!$F$6:$F$5005,"Import - Reverse charge (Box 9)")) | Q5: =IF($A5="","",O5-P5)
A6: =IF(Setup!C20="","",Setup!A20) | B6: =Setup!B20 | C6: =IF($A6="","",VAT_Returns!AP7) | D6: =IF($A6="","",SUMIFS(Purchase_Register!$R$6:$R$5005,Purchase_Register!$O$6:$O$5005,$A6)) | E6: =IF($A6="","",SUMIFS(Purchase_Register!$S$6:$S$5005,Purchase_Register!$O$6:$O$5005,$A6)) | F6: =IF($A6="","",SUMIFS(Purchase_Register!$T$6:$T$5005,Purchase_Register!$O$6:$O$5005,$A6)) | G6: =IF($A6="","",SUMPRODUCT((TB_Monthly!$D$6:$D$505="Input VAT")*(TB_Monthly!$F$4:$Q$4>=Setup!$C$20)*(TB_Monthly!$F$4:$Q$4<=Setup!$D$20)*TB_Monthly!$F$6:$Q$505)) | H6: =IF($A6="","",C6-D6) | I6: =IF($A6="","",C6-G6) | J6: =IF($A6="","",IF(AND(C6=0,D6=0,G6=0),"– No activity",IF(AND(ABS(H6)<=Setup!$B$10,ABS(I6)<=Setup!$B$10),"✓ Matched","✗ Investigate"))) | K6: =IF($A6="","",MAX(0,C6-E6)) | L6: =IF($A6="","",VAT_Returns!Z7) | M6: =IF($A6="","",SUMIFS(Purchase_Register!$I$6:$I$5005,Purchase_Register!$O$6:$O$5005,$A6,Purchase_Register!$F$6:$F$5005,"Import - VAT paid at customs (Box 8)")) | N6: =IF($A6="","",L6-M6) | O6: =IF($A6="","",VAT_Returns!AC7) | P6: =IF($A6="","",SUMIFS(Purchase_Register!$I$6:$I$5005,Purchase_Register!$O$6:$O$5005,$A6,Purchase_Register!$F$6:$F$5005,"Import - Reverse charge (Box 9)")) | Q6: =IF($A6="","",O6-P6)
A7: =IF(Setup!C21="","",Setup!A21) | B7: =Setup!B21 | C7: =IF($A7="","",VAT_Returns!AP8) | D7: =IF($A7="","",SUMIFS(Purchase_Register!$R$6:$R$5005,Purchase_Register!$O$6:$O$5005,$A7)) | E7: =IF($A7="","",SUMIFS(Purchase_Register!$S$6:$S$5005,Purchase_Register!$O$6:$O$5005,$A7)) | F7: =IF($A7="","",SUMIFS(Purchase_Register!$T$6:$T$5005,Purchase_Register!$O$6:$O$5005,$A7)) | G7: =IF($A7="","",SUMPRODUCT((TB_Monthly!$D$6:$D$505="Input VAT")*(TB_Monthly!$F$4:$Q$4>=Setup!$C$21)*(TB_Monthly!$F$4:$Q$4<=Setup!$D$21)*TB_Monthly!$F$6:$Q$505)) | H7: =IF($A7="","",C7-D7) | I7: =IF($A7="","",C7-G7) | J7: =IF($A7="","",IF(AND(C7=0,D7=0,G7=0),"– No activity",IF(AND(ABS(H7)<=Setup!$B$10,ABS(I7)<=Setup!$B$10),"✓ Matched","✗ Investigate"))) | K7: =IF($A7="","",MAX(0,C7-E7)) | L7: =IF($A7="","",VAT_Returns!Z8) | M7: =IF($A7="","",SUMIFS(Purchase_Register!$I$6:$I$5005,Purchase_Register!$O$6:$O$5005,$A7,Purchase_Register!$F$6:$F$5005,"Import - VAT paid at customs (Box 8)")) | N7: =IF($A7="","",L7-M7) | O7: =IF($A7="","",VAT_Returns!AC8) | P7: =IF($A7="","",SUMIFS(Purchase_Register!$I$6:$I$5005,Purchase_Register!$O$6:$O$5005,$A7,Purchase_Register!$F$6:$F$5005,"Import - Reverse charge (Box 9)")) | Q7: =IF($A7="","",O7-P7)
A8: =IF(Setup!C22="","",Setup!A22) | B8: =Setup!B22 | C8: =IF($A8="","",VAT_Returns!AP9) | D8: =IF($A8="","",SUMIFS(Purchase_Register!$R$6:$R$5005,Purchase_Register!$O$6:$O$5005,$A8)) | E8: =IF($A8="","",SUMIFS(Purchase_Register!$S$6:$S$5005,Purchase_Register!$O$6:$O$5005,$A8)) | F8: =IF($A8="","",SUMIFS(Purchase_Register!$T$6:$T$5005,Purchase_Register!$O$6:$O$5005,$A8)) | G8: =IF($A8="","",SUMPRODUCT((TB_Monthly!$D$6:$D$505="Input VAT")*(TB_Monthly!$F$4:$Q$4>=Setup!$C$22)*(TB_Monthly!$F$4:$Q$4<=Setup!$D$22)*TB_Monthly!$F$6:$Q$505)) | H8: =IF($A8="","",C8-D8) | I8: =IF($A8="","",C8-G8) | J8: =IF($A8="","",IF(AND(C8=0,D8=0,G8=0),"– No activity",IF(AND(ABS(H8)<=Setup!$B$10,ABS(I8)<=Setup!$B$10),"✓ Matched","✗ Investigate"))) | K8: =IF($A8="","",MAX(0,C8-E8)) | L8: =IF($A8="","",VAT_Returns!Z9) | M8: =IF($A8="","",SUMIFS(Purchase_Register!$I$6:$I$5005,Purchase_Register!$O$6:$O$5005,$A8,Purchase_Register!$F$6:$F$5005,"Import - VAT paid at customs (Box 8)")) | N8: =IF($A8="","",L8-M8) | O8: =IF($A8="","",VAT_Returns!AC9) | P8: =IF($A8="","",SUMIFS(Purchase_Register!$I$6:$I$5005,Purchase_Register!$O$6:$O$5005,$A8,Purchase_Register!$F$6:$F$5005,"Import - Reverse charge (Box 9)")) | Q8: =IF($A8="","",O8-P8)
A9: =IF(Setup!C23="","",Setup!A23) | B9: =Setup!B23 | C9: =IF($A9="","",VAT_Returns!AP10) | D9: =IF($A9="","",SUMIFS(Purchase_Register!$R$6:$R$5005,Purchase_Register!$O$6:$O$5005,$A9)) | E9: =IF($A9="","",SUMIFS(Purchase_Register!$S$6:$S$5005,Purchase_Register!$O$6:$O$5005,$A9)) | F9: =IF($A9="","",SUMIFS(Purchase_Register!$T$6:$T$5005,Purchase_Register!$O$6:$O$5005,$A9)) | G9: =IF($A9="","",SUMPRODUCT((TB_Monthly!$D$6:$D$505="Input VAT")*(TB_Monthly!$F$4:$Q$4>=Setup!$C$23)*(TB_Monthly!$F$4:$Q$4<=Setup!$D$23)*TB_Monthly!$F$6:$Q$505)) | H9: =IF($A9="","",C9-D9) | I9: =IF($A9="","",C9-G9) | J9: =IF($A9="","",IF(AND(C9=0,D9=0,G9=0),"– No activity",IF(AND(ABS(H9)<=Setup!$B$10,ABS(I9)<=Setup!$B$10),"✓ Matched","✗ Investigate"))) | K9: =IF($A9="","",MAX(0,C9-E9)) | L9: =IF($A9="","",VAT_Returns!Z10) | M9: =IF($A9="","",SUMIFS(Purchase_Register!$I$6:$I$5005,Purchase_Register!$O$6:$O$5005,$A9,Purchase_Register!$F$6:$F$5005,"Import - VAT paid at customs (Box 8)")) | N9: =IF($A9="","",L9-M9) | O9: =IF($A9="","",VAT_Returns!AC10) | P9: =IF($A9="","",SUMIFS(Purchase_Register!$I$6:$I$5005,Purchase_Register!$O$6:$O$5005,$A9,Purchase_Register!$F$6:$F$5005,"Import - Reverse charge (Box 9)")) | Q9: =IF($A9="","",O9-P9)
A10: =IF(Setup!C24="","",Setup!A24) | B10: =Setup!B24 | C10: =IF($A10="","",VAT_Returns!AP11) | D10: =IF($A10="","",SUMIFS(Purchase_Register!$R$6:$R$5005,Purchase_Register!$O$6:$O$5005,$A10)) | E10: =IF($A10="","",SUMIFS(Purchase_Register!$S$6:$S$5005,Purchase_Register!$O$6:$O$5005,$A10)) | F10: =IF($A10="","",SUMIFS(Purchase_Register!$T$6:$T$5005,Purchase_Register!$O$6:$O$5005,$A10)) | G10: =IF($A10="","",SUMPRODUCT((TB_Monthly!$D$6:$D$505="Input VAT")*(TB_Monthly!$F$4:$Q$4>=Setup!$C$24)*(TB_Monthly!$F$4:$Q$4<=Setup!$D$24)*TB_Monthly!$F$6:$Q$505)) | H10: =IF($A10="","",C10-D10) | I10: =IF($A10="","",C10-G10) | J10: =IF($A10="","",IF(AND(C10=0,D10=0,G10=0),"– No activity",IF(AND(ABS(H10)<=Setup!$B$10,ABS(I10)<=Setup!$B$10),"✓ Matched","✗ Investigate"))) | K10: =IF($A10="","",MAX(0,C10-E10)) | L10: =IF($A10="","",VAT_Returns!Z11) | M10: =IF($A10="","",SUMIFS(Purchase_Register!$I$6:$I$5005,Purchase_Register!$O$6:$O$5005,$A10,Purchase_Register!$F$6:$F$5005,"Import - VAT paid at customs (Box 8)")) | N10: =IF($A10="","",L10-M10) | O10: =IF($A10="","",VAT_Returns!AC11) | P10: =IF($A10="","",SUMIFS(Purchase_Register!$I$6:$I$5005,Purchase_Register!$O$6:$O$5005,$A10,Purchase_Register!$F$6:$F$5005,"Import - Reverse charge (Box 9)")) | Q10: =IF($A10="","",O10-P10)
A11: =IF(Setup!C25="","",Setup!A25) | B11: =Setup!B25 | C11: =IF($A11="","",VAT_Returns!AP12) | D11: =IF($A11="","",SUMIFS(Purchase_Register!$R$6:$R$5005,Purchase_Register!$O$6:$O$5005,$A11)) | E11: =IF($A11="","",SUMIFS(Purchase_Register!$S$6:$S$5005,Purchase_Register!$O$6:$O$5005,$A11)) | F11: =IF($A11="","",SUMIFS(Purchase_Register!$T$6:$T$5005,Purchase_Register!$O$6:$O$5005,$A11)) | G11: =IF($A11="","",SUMPRODUCT((TB_Monthly!$D$6:$D$505="Input VAT")*(TB_Monthly!$F$4:$Q$4>=Setup!$C$25)*(TB_Monthly!$F$4:$Q$4<=Setup!$D$25)*TB_Monthly!$F$6:$Q$505)) | H11: =IF($A11="","",C11-D11) | I11: =IF($A11="","",C11-G11) | J11: =IF($A11="","",IF(AND(C11=0,D11=0,G11=0),"– No activity",IF(AND(ABS(H11)<=Setup!$B$10,ABS(I11)<=Setup!$B$10),"✓ Matched","✗ Investigate"))) | K11: =IF($A11="","",MAX(0,C11-E11)) | L11: =IF($A11="","",VAT_Returns!Z12) | M11: =IF($A11="","",SUMIFS(Purchase_Register!$I$6:$I$5005,Purchase_Register!$O$6:$O$5005,$A11,Purchase_Register!$F$6:$F$5005,"Import - VAT paid at customs (Box 8)")) | N11: =IF($A11="","",L11-M11) | O11: =IF($A11="","",VAT_Returns!AC12) | P11: =IF($A11="","",SUMIFS(Purchase_Register!$I$6:$I$5005,Purchase_Register!$O$6:$O$5005,$A11,Purchase_Register!$F$6:$F$5005,"Import - Reverse charge (Box 9)")) | Q11: =IF($A11="","",O11-P11)
A12: =IF(Setup!C26="","",Setup!A26) | B12: =Setup!B26 | C12: =IF($A12="","",VAT_Returns!AP13) | D12: =IF($A12="","",SUMIFS(Purchase_Register!$R$6:$R$5005,Purchase_Register!$O$6:$O$5005,$A12)) | E12: =IF($A12="","",SUMIFS(Purchase_Register!$S$6:$S$5005,Purchase_Register!$O$6:$O$5005,$A12)) | F12: =IF($A12="","",SUMIFS(Purchase_Register!$T$6:$T$5005,Purchase_Register!$O$6:$O$5005,$A12)) | G12: =IF($A12="","",SUMPRODUCT((TB_Monthly!$D$6:$D$505="Input VAT")*(TB_Monthly!$F$4:$Q$4>=Setup!$C$26)*(TB_Monthly!$F$4:$Q$4<=Setup!$D$26)*TB_Monthly!$F$6:$Q$505)) | H12: =IF($A12="","",C12-D12) | I12: =IF($A12="","",C12-G12) | J12: =IF($A12="","",IF(AND(C12=0,D12=0,G12=0),"– No activity",IF(AND(ABS(H12)<=Setup!$B$10,ABS(I12)<=Setup!$B$10),"✓ Matched","✗ Investigate"))) | K12: =IF($A12="","",MAX(0,C12-E12)) | L12: =IF($A12="","",VAT_Returns!Z13) | M12: =IF($A12="","",SUMIFS(Purchase_Register!$I$6:$I$5005,Purchase_Register!$O$6:$O$5005,$A12,Purchase_Register!$F$6:$F$5005,"Import - VAT paid at customs (Box 8)")) | N12: =IF($A12="","",L12-M12) | O12: =IF($A12="","",VAT_Returns!AC13) | P12: =IF($A12="","",SUMIFS(Purchase_Register!$I$6:$I$5005,Purchase_Register!$O$6:$O$5005,$A12,Purchase_Register!$F$6:$F$5005,"Import - Reverse charge (Box 9)")) | Q12: =IF($A12="","",O12-P12)
A13: =IF(Setup!C27="","",Setup!A27) | B13: =Setup!B27 | C13: =IF($A13="","",VAT_Returns!AP14) | D13: =IF($A13="","",SUMIFS(Purchase_Register!$R$6:$R$5005,Purchase_Register!$O$6:$O$5005,$A13)) | E13: =IF($A13="","",SUMIFS(Purchase_Register!$S$6:$S$5005,Purchase_Register!$O$6:$O$5005,$A13)) | F13: =IF($A13="","",SUMIFS(Purchase_Register!$T$6:$T$5005,Purchase_Register!$O$6:$O$5005,$A13)) | G13: =IF($A13="","",SUMPRODUCT((TB_Monthly!$D$6:$D$505="Input VAT")*(TB_Monthly!$F$4:$Q$4>=Setup!$C$27)*(TB_Monthly!$F$4:$Q$4<=Setup!$D$27)*TB_Monthly!$F$6:$Q$505)) | H13: =IF($A13="","",C13-D13) | I13: =IF($A13="","",C13-G13) | J13: =IF($A13="","",IF(AND(C13=0,D13=0,G13=0),"– No activity",IF(AND(ABS(H13)<=Setup!$B$10,ABS(I13)<=Setup!$B$10),"✓ Matched","✗ Investigate"))) | K13: =IF($A13="","",MAX(0,C13-E13)) | L13: =IF($A13="","",VAT_Returns!Z14) | M13: =IF($A13="","",SUMIFS(Purchase_Register!$I$6:$I$5005,Purchase_Register!$O$6:$O$5005,$A13,Purchase_Register!$F$6:$F$5005,"Import - VAT paid at customs (Box 8)")) | N13: =IF($A13="","",L13-M13) | O13: =IF($A13="","",VAT_Returns!AC14) | P13: =IF($A13="","",SUMIFS(Purchase_Register!$I$6:$I$5005,Purchase_Register!$O$6:$O$5005,$A13,Purchase_Register!$F$6:$F$5005,"Import - Reverse charge (Box 9)")) | Q13: =IF($A13="","",O13-P13)
A14: =IF(Setup!C28="","",Setup!A28) | B14: =Setup!B28 | C14: =IF($A14="","",VAT_Returns!AP15) | D14: =IF($A14="","",SUMIFS(Purchase_Register!$R$6:$R$5005,Purchase_Register!$O$6:$O$5005,$A14)) | E14: =IF($A14="","",SUMIFS(Purchase_Register!$S$6:$S$5005,Purchase_Register!$O$6:$O$5005,$A14)) | F14: =IF($A14="","",SUMIFS(Purchase_Register!$T$6:$T$5005,Purchase_Register!$O$6:$O$5005,$A14)) | G14: =IF($A14="","",SUMPRODUCT((TB_Monthly!$D$6:$D$505="Input VAT")*(TB_Monthly!$F$4:$Q$4>=Setup!$C$28)*(TB_Monthly!$F$4:$Q$4<=Setup!$D$28)*TB_Monthly!$F$6:$Q$505)) | H14: =IF($A14="","",C14-D14) | I14: =IF($A14="","",C14-G14) | J14: =IF($A14="","",IF(AND(C14=0,D14=0,G14=0),"– No activity",IF(AND(ABS(H14)<=Setup!$B$10,ABS(I14)<=Setup!$B$10),"✓ Matched","✗ Investigate"))) | K14: =IF($A14="","",MAX(0,C14-E14)) | L14: =IF($A14="","",VAT_Returns!Z15) | M14: =IF($A14="","",SUMIFS(Purchase_Register!$I$6:$I$5005,Purchase_Register!$O$6:$O$5005,$A14,Purchase_Register!$F$6:$F$5005,"Import - VAT paid at customs (Box 8)")) | N14: =IF($A14="","",L14-M14) | O14: =IF($A14="","",VAT_Returns!AC15) | P14: =IF($A14="","",SUMIFS(Purchase_Register!$I$6:$I$5005,Purchase_Register!$O$6:$O$5005,$A14,Purchase_Register!$F$6:$F$5005,"Import - Reverse charge (Box 9)")) | Q14: =IF($A14="","",O14-P14)
A15: =IF(Setup!C29="","",Setup!A29) | B15: =Setup!B29 | C15: =IF($A15="","",VAT_Returns!AP16) | D15: =IF($A15="","",SUMIFS(Purchase_Register!$R$6:$R$5005,Purchase_Register!$O$6:$O$5005,$A15)) | E15: =IF($A15="","",SUMIFS(Purchase_Register!$S$6:$S$5005,Purchase_Register!$O$6:$O$5005,$A15)) | F15: =IF($A15="","",SUMIFS(Purchase_Register!$T$6:$T$5005,Purchase_Register!$O$6:$O$5005,$A15)) | G15: =IF($A15="","",SUMPRODUCT((TB_Monthly!$D$6:$D$505="Input VAT")*(TB_Monthly!$F$4:$Q$4>=Setup!$C$29)*(TB_Monthly!$F$4:$Q$4<=Setup!$D$29)*TB_Monthly!$F$6:$Q$505)) | H15: =IF($A15="","",C15-D15) | I15: =IF($A15="","",C15-G15) | J15: =IF($A15="","",IF(AND(C15=0,D15=0,G15=0),"– No activity",IF(AND(ABS(H15)<=Setup!$B$10,ABS(I15)<=Setup!$B$10),"✓ Matched","✗ Investigate"))) | K15: =IF($A15="","",MAX(0,C15-E15)) | L15: =IF($A15="","",VAT_Returns!Z16) | M15: =IF($A15="","",SUMIFS(Purchase_Register!$I$6:$I$5005,Purchase_Register!$O$6:$O$5005,$A15,Purchase_Register!$F$6:$F$5005,"Import - VAT paid at customs (Box 8)")) | N15: =IF($A15="","",L15-M15) | O15: =IF($A15="","",VAT_Returns!AC16) | P15: =IF($A15="","",SUMIFS(Purchase_Register!$I$6:$I$5005,Purchase_Register!$O$6:$O$5005,$A15,Purchase_Register!$F$6:$F$5005,"Import - Reverse charge (Box 9)")) | Q15: =IF($A15="","",O15-P15)
A16: =IF(Setup!C30="","",Setup!A30) | B16: =Setup!B30 | C16: =IF($A16="","",VAT_Returns!AP17) | D16: =IF($A16="","",SUMIFS(Purchase_Register!$R$6:$R$5005,Purchase_Register!$O$6:$O$5005,$A16)) | E16: =IF($A16="","",SUMIFS(Purchase_Register!$S$6:$S$5005,Purchase_Register!$O$6:$O$5005,$A16)) | F16: =IF($A16="","",SUMIFS(Purchase_Register!$T$6:$T$5005,Purchase_Register!$O$6:$O$5005,$A16)) | G16: =IF($A16="","",SUMPRODUCT((TB_Monthly!$D$6:$D$505="Input VAT")*(TB_Monthly!$F$4:$Q$4>=Setup!$C$30)*(TB_Monthly!$F$4:$Q$4<=Setup!$D$30)*TB_Monthly!$F$6:$Q$505)) | H16: =IF($A16="","",C16-D16) | I16: =IF($A16="","",C16-G16) | J16: =IF($A16="","",IF(AND(C16=0,D16=0,G16=0),"– No activity",IF(AND(ABS(H16)<=Setup!$B$10,ABS(I16)<=Setup!$B$10),"✓ Matched","✗ Investigate"))) | K16: =IF($A16="","",MAX(0,C16-E16)) | L16: =IF($A16="","",VAT_Returns!Z17) | M16: =IF($A16="","",SUMIFS(Purchase_Register!$I$6:$I$5005,Purchase_Register!$O$6:$O$5005,$A16,Purchase_Register!$F$6:$F$5005,"Import - VAT paid at customs (Box 8)")) | N16: =IF($A16="","",L16-M16) | O16: =IF($A16="","",VAT_Returns!AC17) | P16: =IF($A16="","",SUMIFS(Purchase_Register!$I$6:$I$5005,Purchase_Register!$O$6:$O$5005,$A16,Purchase_Register!$F$6:$F$5005,"Import - Reverse charge (Box 9)")) | Q16: =IF($A16="","",O16-P16)
B17: TOTAL | C17: =SUM(C5:C16) | D17: =SUM(D5:D16) | E17: =SUM(E5:E16) | F17: =SUM(F5:F16) | G17: =SUM(G5:G16) | H17: =SUM(H5:H16) | I17: =SUM(I5:I16) | J17: =IF(COUNTIF(J5:J16,"✗*")=0,"✓ Matched","✗ Investigate") | K17: =SUM(K5:K16) | L17: =SUM(L5:L16) | M17: =SUM(M5:M16) | N17: =SUM(N5:N16) | O17: =SUM(O5:O16) | P17: =SUM(P5:P16) | Q17: =SUM(Q5:Q16)
A19: Box 8 should also be matched to ZATCA's customs import data (request the importer statement from ZATCA/customs). Customs VAT is only deductible when the company is the importer of record on the Bayan.

Sheet Recon_VAT_Account
A1: VAT Control Account & Payments (مطابقة حساب الضريبة والسداد)
A2: Proves the GL VAT liability = returns filed − payments made. Also estimates late filing / payment exposure.
A3: Opening GL VAT liability (credit = positive): | E3: =-SUMPRODUCT(((TB_Monthly!$D$6:$D$505="Output VAT")+(TB_Monthly!$D$6:$D$505="Input VAT")+(TB_Monthly!$D$6:$D$505="VAT Payable / Settlement"))*TB_Monthly!$E$6:$E$505)
A5: Period # | B5: Period | C5: Period End | D5: Net VAT (Box 13 + Box 14) | E5: Box 16 as Filed | F5: Paid / (Refunded) for Period | G5: Outstanding for Period | H5: Due Date | I5: Penalty on Late Payments Made | J5: Penalty on Amount Still Unpaid (to As-of date) | K5: Filed on time? | L5: GL VAT Liability at Period End | M5: Expected Liability (Opening + Returns − Payments) | N5: Difference GL − Expected | O5: Status
A6: =IF(Setup!C19="","",Setup!A19) | B6: =Setup!B19 | C6: =Setup!D19 | D6: =IF($A6="","",VAT_Returns!AQ6+VAT_Returns!AJ6) | E6: =IF($A6="","",N(VAT_Returns!AL6)) | F6: =IF($A6="","",SUMIFS(ZATCA_Payments!$D$6:$D$505,ZATCA_Payments!$A$6:$A$505,$A6)) | G6: =IF($A6="","",MAX(E6,0)-F6) | H6: =Setup!E19 | I6: =IF($A6="","",SUMIFS(ZATCA_Payments!$J$6:$J$505,ZATCA_Payments!$A$6:$A$505,$A6)) | J6: =IF($A6="","",IF(AND(G6>Setup!$B$10,Setup!$B$11>H6),G6*Setup!$B$12*((YEAR(Setup!$B$11)-YEAR(H6))*12+MONTH(Setup!$B$11)-MONTH(H6)+IF(DAY(Setup!$B$11)>DAY(H6),1,0)),0)) | K6: =IF($A6="","",VAT_Returns!AT6) | L6: =IF($A6="","",-(SUMPRODUCT(((TB_Monthly!$D$6:$D$505="Output VAT")+(TB_Monthly!$D$6:$D$505="Input VAT")+(TB_Monthly!$D$6:$D$505="VAT Payable / Settlement"))*TB_Monthly!$E$6:$E$505)+SUMPRODUCT(((TB_Monthly!$D$6:$D$505="Output VAT")+(TB_Monthly!$D$6:$D$505="Input VAT")+(TB_Monthly!$D$6:$D$505="VAT Payable / Settlement"))*(TB_Monthly!$F$4:$Q$4<=C6)*TB_Monthly!$F$6:$Q$505))) | M6: =IF($A6="","",$E$3+SUM(D$6:D6)-SUMIFS(ZATCA_Payments!$D$6:$D$505,ZATCA_Payments!$B$6:$B$505,"<="&C6)) | N6: =IF($A6="","",L6-M6) | O6: =IF($A6="","",IF(ABS(N6)<=Setup!$B$10,"✓ Agrees","✗ Investigate"))
A7: =IF(Setup!C20="","",Setup!A20) | B7: =Setup!B20 | C7: =Setup!D20 | D7: =IF($A7="","",VAT_Returns!AQ7+VAT_Returns!AJ7) | E7: =IF($A7="","",N(VAT_Returns!AL7)) | F7: =IF($A7="","",SUMIFS(ZATCA_Payments!$D$6:$D$505,ZATCA_Payments!$A$6:$A$505,$A7)) | G7: =IF($A7="","",MAX(E7,0)-F7) | H7: =Setup!E20 | I7: =IF($A7="","",SUMIFS(ZATCA_Payments!$J$6:$J$505,ZATCA_Payments!$A$6:$A$505,$A7)) | J7: =IF($A7="","",IF(AND(G7>Setup!$B$10,Setup!$B$11>H7),G7*Setup!$B$12*((YEAR(Setup!$B$11)-YEAR(H7))*12+MONTH(Setup!$B$11)-MONTH(H7)+IF(DAY(Setup!$B$11)>DAY(H7),1,0)),0)) | K7: =IF($A7="","",VAT_Returns!AT7) | L7: =IF($A7="","",-(SUMPRODUCT(((TB_Monthly!$D$6:$D$505="Output VAT")+(TB_Monthly!$D$6:$D$505="Input VAT")+(TB_Monthly!$D$6:$D$505="VAT Payable / Settlement"))*TB_Monthly!$E$6:$E$505)+SUMPRODUCT(((TB_Monthly!$D$6:$D$505="Output VAT")+(TB_Monthly!$D$6:$D$505="Input VAT")+(TB_Monthly!$D$6:$D$505="VAT Payable / Settlement"))*(TB_Monthly!$F$4:$Q$4<=C7)*TB_Monthly!$F$6:$Q$505))) | M7: =IF($A7="","",$E$3+SUM(D$6:D7)-SUMIFS(ZATCA_Payments!$D$6:$D$505,ZATCA_Payments!$B$6:$B$505,"<="&C7)) | N7: =IF($A7="","",L7-M7) | O7: =IF($A7="","",IF(ABS(N7)<=Setup!$B$10,"✓ Agrees","✗ Investigate"))
A8: =IF(Setup!C21="","",Setup!A21) | B8: =Setup!B21 | C8: =Setup!D21 | D8: =IF($A8="","",VAT_Returns!AQ8+VAT_Returns!AJ8) | E8: =IF($A8="","",N(VAT_Returns!AL8)) | F8: =IF($A8="","",SUMIFS(ZATCA_Payments!$D$6:$D$505,ZATCA_Payments!$A$6:$A$505,$A8)) | G8: =IF($A8="","",MAX(E8,0)-F8) | H8: =Setup!E21 | I8: =IF($A8="","",SUMIFS(ZATCA_Payments!$J$6:$J$505,ZATCA_Payments!$A$6:$A$505,$A8)) | J8: =IF($A8="","",IF(AND(G8>Setup!$B$10,Setup!$B$11>H8),G8*Setup!$B$12*((YEAR(Setup!$B$11)-YEAR(H8))*12+MONTH(Setup!$B$11)-MONTH(H8)+IF(DAY(Setup!$B$11)>DAY(H8),1,0)),0)) | K8: =IF($A8="","",VAT_Returns!AT8) | L8: =IF($A8="","",-(SUMPRODUCT(((TB_Monthly!$D$6:$D$505="Output VAT")+(TB_Monthly!$D$6:$D$505="Input VAT")+(TB_Monthly!$D$6:$D$505="VAT Payable / Settlement"))*TB_Monthly!$E$6:$E$505)+SUMPRODUCT(((TB_Monthly!$D$6:$D$505="Output VAT")+(TB_Monthly!$D$6:$D$505="Input VAT")+(TB_Monthly!$D$6:$D$505="VAT Payable / Settlement"))*(TB_Monthly!$F$4:$Q$4<=C8)*TB_Monthly!$F$6:$Q$505))) | M8: =IF($A8="","",$E$3+SUM(D$6:D8)-SUMIFS(ZATCA_Payments!$D$6:$D$505,ZATCA_Payments!$B$6:$B$505,"<="&C8)) | N8: =IF($A8="","",L8-M8) | O8: =IF($A8="","",IF(ABS(N8)<=Setup!$B$10,"✓ Agrees","✗ Investigate"))
A9: =IF(Setup!C22="","",Setup!A22) | B9: =Setup!B22 | C9: =Setup!D22 | D9: =IF($A9="","",VAT_Returns!AQ9+VAT_Returns!AJ9) | E9: =IF($A9="","",N(VAT_Returns!AL9)) | F9: =IF($A9="","",SUMIFS(ZATCA_Payments!$D$6:$D$505,ZATCA_Payments!$A$6:$A$505,$A9)) | G9: =IF($A9="","",MAX(E9,0)-F9) | H9: =Setup!E22 | I9: =IF($A9="","",SUMIFS(ZATCA_Payments!$J$6:$J$505,ZATCA_Payments!$A$6:$A$505,$A9)) | J9: =IF($A9="","",IF(AND(G9>Setup!$B$10,Setup!$B$11>H9),G9*Setup!$B$12*((YEAR(Setup!$B$11)-YEAR(H9))*12+MONTH(Setup!$B$11)-MONTH(H9)+IF(DAY(Setup!$B$11)>DAY(H9),1,0)),0)) | K9: =IF($A9="","",VAT_Returns!AT9) | L9: =IF($A9="","",-(SUMPRODUCT(((TB_Monthly!$D$6:$D$505="Output VAT")+(TB_Monthly!$D$6:$D$505="Input VAT")+(TB_Monthly!$D$6:$D$505="VAT Payable / Settlement"))*TB_Monthly!$E$6:$E$505)+SUMPRODUCT(((TB_Monthly!$D$6:$D$505="Output VAT")+(TB_Monthly!$D$6:$D$505="Input VAT")+(TB_Monthly!$D$6:$D$505="VAT Payable / Settlement"))*(TB_Monthly!$F$4:$Q$4<=C9)*TB_Monthly!$F$6:$Q$505))) | M9: =IF($A9="","",$E$3+SUM(D$6:D9)-SUMIFS(ZATCA_Payments!$D$6:$D$505,ZATCA_Payments!$B$6:$B$505,"<="&C9)) | N9: =IF($A9="","",L9-M9) | O9: =IF($A9="","",IF(ABS(N9)<=Setup!$B$10,"✓ Agrees","✗ Investigate"))
A10: =IF(Setup!C23="","",Setup!A23) | B10: =Setup!B23 | C10: =Setup!D23 | D10: =IF($A10="","",VAT_Returns!AQ10+VAT_Returns!AJ10) | E10: =IF($A10="","",N(VAT_Returns!AL10)) | F10: =IF($A10="","",SUMIFS(ZATCA_Payments!$D$6:$D$505,ZATCA_Payments!$A$6:$A$505,$A10)) | G10: =IF($A10="","",MAX(E10,0)-F10) | H10: =Setup!E23 | I10: =IF($A10="","",SUMIFS(ZATCA_Payments!$J$6:$J$505,ZATCA_Payments!$A$6:$A$505,$A10)) | J10: =IF($A10="","",IF(AND(G10>Setup!$B$10,Setup!$B$11>H10),G10*Setup!$B$12*((YEAR(Setup!$B$11)-YEAR(H10))*12+MONTH(Setup!$B$11)-MONTH(H10)+IF(DAY(Setup!$B$11)>DAY(H10),1,0)),0)) | K10: =IF($A10="","",VAT_Returns!AT10) | L10: =IF($A10="","",-(SUMPRODUCT(((TB_Monthly!$D$6:$D$505="Output VAT")+(TB_Monthly!$D$6:$D$505="Input VAT")+(TB_Monthly!$D$6:$D$505="VAT Payable / Settlement"))*TB_Monthly!$E$6:$E$505)+SUMPRODUCT(((TB_Monthly!$D$6:$D$505="Output VAT")+(TB_Monthly!$D$6:$D$505="Input VAT")+(TB_Monthly!$D$6:$D$505="VAT Payable / Settlement"))*(TB_Monthly!$F$4:$Q$4<=C10)*TB_Monthly!$F$6:$Q$505))) | M10: =IF($A10="","",$E$3+SUM(D$6:D10)-SUMIFS(ZATCA_Payments!$D$6:$D$505,ZATCA_Payments!$B$6:$B$505,"<="&C10)) | N10: =IF($A10="","",L10-M10) | O10: =IF($A10="","",IF(ABS(N10)<=Setup!$B$10,"✓ Agrees","✗ Investigate"))
A11: =IF(Setup!C24="","",Setup!A24) | B11: =Setup!B24 | C11: =Setup!D24 | D11: =IF($A11="","",VAT_Returns!AQ11+VAT_Returns!AJ11) | E11: =IF($A11="","",N(VAT_Returns!AL11)) | F11: =IF($A11="","",SUMIFS(ZATCA_Payments!$D$6:$D$505,ZATCA_Payments!$A$6:$A$505,$A11)) | G11: =IF($A11="","",MAX(E11,0)-F11) | H11: =Setup!E24 | I11: =IF($A11="","",SUMIFS(ZATCA_Payments!$J$6:$J$505,ZATCA_Payments!$A$6:$A$505,$A11)) | J11: =IF($A11="","",IF(AND(G11>Setup!$B$10,Setup!$B$11>H11),G11*Setup!$B$12*((YEAR(Setup!$B$11)-YEAR(H11))*12+MONTH(Setup!$B$11)-MONTH(H11)+IF(DAY(Setup!$B$11)>DAY(H11),1,0)),0)) | K11: =IF($A11="","",VAT_Returns!AT11) | L11: =IF($A11="","",-(SUMPRODUCT(((TB_Monthly!$D$6:$D$505="Output VAT")+(TB_Monthly!$D$6:$D$505="Input VAT")+(TB_Monthly!$D$6:$D$505="VAT Payable / Settlement"))*TB_Monthly!$E$6:$E$505)+SUMPRODUCT(((TB_Monthly!$D$6:$D$505="Output VAT")+(TB_Monthly!$D$6:$D$505="Input VAT")+(TB_Monthly!$D$6:$D$505="VAT Payable / Settlement"))*(TB_Monthly!$F$4:$Q$4<=C11)*TB_Monthly!$F$6:$Q$505))) | M11: =IF($A11="","",$E$3+SUM(D$6:D11)-SUMIFS(ZATCA_Payments!$D$6:$D$505,ZATCA_Payments!$B$6:$B$505,"<="&C11)) | N11: =IF($A11="","",L11-M11) | O11: =IF($A11="","",IF(ABS(N11)<=Setup!$B$10,"✓ Agrees","✗ Investigate"))
A12: =IF(Setup!C25="","",Setup!A25) | B12: =Setup!B25 | C12: =Setup!D25 | D12: =IF($A12="","",VAT_Returns!AQ12+VAT_Returns!AJ12) | E12: =IF($A12="","",N(VAT_Returns!AL12)) | F12: =IF($A12="","",SUMIFS(ZATCA_Payments!$D$6:$D$505,ZATCA_Payments!$A$6:$A$505,$A12)) | G12: =IF($A12="","",MAX(E12,0)-F12) | H12: =Setup!E25 | I12: =IF($A12="","",SUMIFS(ZATCA_Payments!$J$6:$J$505,ZATCA_Payments!$A$6:$A$505,$A12)) | J12: =IF($A12="","",IF(AND(G12>Setup!$B$10,Setup!$B$11>H12),G12*Setup!$B$12*((YEAR(Setup!$B$11)-YEAR(H12))*12+MONTH(Setup!$B$11)-MONTH(H12)+IF(DAY(Setup!$B$11)>DAY(H12),1,0)),0)) | K12: =IF($A12="","",VAT_Returns!AT12) | L12: =IF($A12="","",-(SUMPRODUCT(((TB_Monthly!$D$6:$D$505="Output VAT")+(TB_Monthly!$D$6:$D$505="Input VAT")+(TB_Monthly!$D$6:$D$505="VAT Payable / Settlement"))*TB_Monthly!$E$6:$E$505)+SUMPRODUCT(((TB_Monthly!$D$6:$D$505="Output VAT")+(TB_Monthly!$D$6:$D$505="Input VAT")+(TB_Monthly!$D$6:$D$505="VAT Payable / Settlement"))*(TB_Monthly!$F$4:$Q$4<=C12)*TB_Monthly!$F$6:$Q$505))) | M12: =IF($A12="","",$E$3+SUM(D$6:D12)-SUMIFS(ZATCA_Payments!$D$6:$D$505,ZATCA_Payments!$B$6:$B$505,"<="&C12)) | N12: =IF($A12="","",L12-M12) | O12: =IF($A12="","",IF(ABS(N12)<=Setup!$B$10,"✓ Agrees","✗ Investigate"))
A13: =IF(Setup!C26="","",Setup!A26) | B13: =Setup!B26 | C13: =Setup!D26 | D13: =IF($A13="","",VAT_Returns!AQ13+VAT_Returns!AJ13) | E13: =IF($A13="","",N(VAT_Returns!AL13)) | F13: =IF($A13="","",SUMIFS(ZATCA_Payments!$D$6:$D$505,ZATCA_Payments!$A$6:$A$505,$A13)) | G13: =IF($A13="","",MAX(E13,0)-F13) | H13: =Setup!E26 | I13: =IF($A13="","",SUMIFS(ZATCA_Payments!$J$6:$J$505,ZATCA_Payments!$A$6:$A$505,$A13)) | J13: =IF($A13="","",IF(AND(G13>Setup!$B$10,Setup!$B$11>H13),G13*Setup!$B$12*((YEAR(Setup!$B$11)-YEAR(H13))*12+MONTH(Setup!$B$11)-MONTH(H13)+IF(DAY(Setup!$B$11)>DAY(H13),1,0)),0)) | K13: =IF($A13="","",VAT_Returns!AT13) | L13: =IF($A13="","",-(SUMPRODUCT(((TB_Monthly!$D$6:$D$505="Output VAT")+(TB_Monthly!$D$6:$D$505="Input VAT")+(TB_Monthly!$D$6:$D$505="VAT Payable / Settlement"))*TB_Monthly!$E$6:$E$505)+SUMPRODUCT(((TB_Monthly!$D$6:$D$505="Output VAT")+(TB_Monthly!$D$6:$D$505="Input VAT")+(TB_Monthly!$D$6:$D$505="VAT Payable / Settlement"))*(TB_Monthly!$F$4:$Q$4<=C13)*TB_Monthly!$F$6:$Q$505))) | M13: =IF($A13="","",$E$3+SUM(D$6:D13)-SUMIFS(ZATCA_Payments!$D$6:$D$505,ZATCA_Payments!$B$6:$B$505,"<="&C13)) | N13: =IF($A13="","",L13-M13) | O13: =IF($A13="","",IF(ABS(N13)<=Setup!$B$10,"✓ Agrees","✗ Investigate"))
A14: =IF(Setup!C27="","",Setup!A27) | B14: =Setup!B27 | C14: =Setup!D27 | D14: =IF($A14="","",VAT_Returns!AQ14+VAT_Returns!AJ14) | E14: =IF($A14="","",N(VAT_Returns!AL14)) | F14: =IF($A14="","",SUMIFS(ZATCA_Payments!$D$6:$D$505,ZATCA_Payments!$A$6:$A$505,$A14)) | G14: =IF($A14="","",MAX(E14,0)-F14) | H14: =Setup!E27 | I14: =IF($A14="","",SUMIFS(ZATCA_Payments!$J$6:$J$505,ZATCA_Payments!$A$6:$A$505,$A14)) | J14: =IF($A14="","",IF(AND(G14>Setup!$B$10,Setup!$B$11>H14),G14*Setup!$B$12*((YEAR(Setup!$B$11)-YEAR(H14))*12+MONTH(Setup!$B$11)-MONTH(H14)+IF(DAY(Setup!$B$11)>DAY(H14),1,0)),0)) | K14: =IF($A14="","",VAT_Returns!AT14) | L14: =IF($A14="","",-(SUMPRODUCT(((TB_Monthly!$D$6:$D$505="Output VAT")+(TB_Monthly!$D$6:$D$505="Input VAT")+(TB_Monthly!$D$6:$D$505="VAT Payable / Settlement"))*TB_Monthly!$E$6:$E$505)+SUMPRODUCT(((TB_Monthly!$D$6:$D$505="Output VAT")+(TB_Monthly!$D$6:$D$505="Input VAT")+(TB_Monthly!$D$6:$D$505="VAT Payable / Settlement"))*(TB_Monthly!$F$4:$Q$4<=C14)*TB_Monthly!$F$6:$Q$505))) | M14: =IF($A14="","",$E$3+SUM(D$6:D14)-SUMIFS(ZATCA_Payments!$D$6:$D$505,ZATCA_Payments!$B$6:$B$505,"<="&C14)) | N14: =IF($A14="","",L14-M14) | O14: =IF($A14="","",IF(ABS(N14)<=Setup!$B$10,"✓ Agrees","✗ Investigate"))
A15: =IF(Setup!C28="","",Setup!A28) | B15: =Setup!B28 | C15: =Setup!D28 | D15: =IF($A15="","",VAT_Returns!AQ15+VAT_Returns!AJ15) | E15: =IF($A15="","",N(VAT_Returns!AL15)) | F15: =IF($A15="","",SUMIFS(ZATCA_Payments!$D$6:$D$505,ZATCA_Payments!$A$6:$A$505,$A15)) | G15: =IF($A15="","",MAX(E15,0)-F15) | H15: =Setup!E28 | I15: =IF($A15="","",SUMIFS(ZATCA_Payments!$J$6:$J$505,ZATCA_Payments!$A$6:$A$505,$A15)) | J15: =IF($A15="","",IF(AND(G15>Setup!$B$10,Setup!$B$11>H15),G15*Setup!$B$12*((YEAR(Setup!$B$11)-YEAR(H15))*12+MONTH(Setup!$B$11)-MONTH(H15)+IF(DAY(Setup!$B$11)>DAY(H15),1,0)),0)) | K15: =IF($A15="","",VAT_Returns!AT15) | L15: =IF($A15="","",-(SUMPRODUCT(((TB_Monthly!$D$6:$D$505="Output VAT")+(TB_Monthly!$D$6:$D$505="Input VAT")+(TB_Monthly!$D$6:$D$505="VAT Payable / Settlement"))*TB_Monthly!$E$6:$E$505)+SUMPRODUCT(((TB_Monthly!$D$6:$D$505="Output VAT")+(TB_Monthly!$D$6:$D$505="Input VAT")+(TB_Monthly!$D$6:$D$505="VAT Payable / Settlement"))*(TB_Monthly!$F$4:$Q$4<=C15)*TB_Monthly!$F$6:$Q$505))) | M15: =IF($A15="","",$E$3+SUM(D$6:D15)-SUMIFS(ZATCA_Payments!$D$6:$D$505,ZATCA_Payments!$B$6:$B$505,"<="&C15)) | N15: =IF($A15="","",L15-M15) | O15: =IF($A15="","",IF(ABS(N15)<=Setup!$B$10,"✓ Agrees","✗ Investigate"))
A16: =IF(Setup!C29="","",Setup!A29) | B16: =Setup!B29 | C16: =Setup!D29 | D16: =IF($A16="","",VAT_Returns!AQ16+VAT_Returns!AJ16) | E16: =IF($A16="","",N(VAT_Returns!AL16)) | F16: =IF($A16="","",SUMIFS(ZATCA_Payments!$D$6:$D$505,ZATCA_Payments!$A$6:$A$505,$A16)) | G16: =IF($A16="","",MAX(E16,0)-F16) | H16: =Setup!E29 | I16: =IF($A16="","",SUMIFS(ZATCA_Payments!$J$6:$J$505,ZATCA_Payments!$A$6:$A$505,$A16)) | J16: =IF($A16="","",IF(AND(G16>Setup!$B$10,Setup!$B$11>H16),G16*Setup!$B$12*((YEAR(Setup!$B$11)-YEAR(H16))*12+MONTH(Setup!$B$11)-MONTH(H16)+IF(DAY(Setup!$B$11)>DAY(H16),1,0)),0)) | K16: =IF($A16="","",VAT_Returns!AT16) | L16: =IF($A16="","",-(SUMPRODUCT(((TB_Monthly!$D$6:$D$505="Output VAT")+(TB_Monthly!$D$6:$D$505="Input VAT")+(TB_Monthly!$D$6:$D$505="VAT Payable / Settlement"))*TB_Monthly!$E$6:$E$505)+SUMPRODUCT(((TB_Monthly!$D$6:$D$505="Output VAT")+(TB_Monthly!$D$6:$D$505="Input VAT")+(TB_Monthly!$D$6:$D$505="VAT Payable / Settlement"))*(TB_Monthly!$F$4:$Q$4<=C16)*TB_Monthly!$F$6:$Q$505))) | M16: =IF($A16="","",$E$3+SUM(D$6:D16)-SUMIFS(ZATCA_Payments!$D$6:$D$505,ZATCA_Payments!$B$6:$B$505,"<="&C16)) | N16: =IF($A16="","",L16-M16) | O16: =IF($A16="","",IF(ABS(N16)<=Setup!$B$10,"✓ Agrees","✗ Investigate"))
A17: =IF(Setup!C30="","",Setup!A30) | B17: =Setup!B30 | C17: =Setup!D30 | D17: =IF($A17="","",VAT_Returns!AQ17+VAT_Returns!AJ17) | E17: =IF($A17="","",N(VAT_Returns!AL17)) | F17: =IF($A17="","",SUMIFS(ZATCA_Payments!$D$6:$D$505,ZATCA_Payments!$A$6:$A$505,$A17)) | G17: =IF($A17="","",MAX(E17,0)-F17) | H17: =Setup!E30 | I17: =IF($A17="","",SUMIFS(ZATCA_Payments!$J$6:$J$505,ZATCA_Payments!$A$6:$A$505,$A17)) | J17: =IF($A17="","",IF(AND(G17>Setup!$B$10,Setup!$B$11>H17),G17*Setup!$B$12*((YEAR(Setup!$B$11)-YEAR(H17))*12+MONTH(Setup!$B$11)-MONTH(H17)+IF(DAY(Setup!$B$11)>DAY(H17),1,0)),0)) | K17: =IF($A17="","",VAT_Returns!AT17) | L17: =IF($A17="","",-(SUMPRODUCT(((TB_Monthly!$D$6:$D$505="Output VAT")+(TB_Monthly!$D$6:$D$505="Input VAT")+(TB_Monthly!$D$6:$D$505="VAT Payable / Settlement"))*TB_Monthly!$E$6:$E$505)+SUMPRODUCT(((TB_Monthly!$D$6:$D$505="Output VAT")+(TB_Monthly!$D$6:$D$505="Input VAT")+(TB_Monthly!$D$6:$D$505="VAT Payable / Settlement"))*(TB_Monthly!$F$4:$Q$4<=C17)*TB_Monthly!$F$6:$Q$505))) | M17: =IF($A17="","",$E$3+SUM(D$6:D17)-SUMIFS(ZATCA_Payments!$D$6:$D$505,ZATCA_Payments!$B$6:$B$505,"<="&C17)) | N17: =IF($A17="","",L17-M17) | O17: =IF($A17="","",IF(ABS(N17)<=Setup!$B$10,"✓ Agrees","✗ Investigate"))
B18: TOTAL | D18: =SUM(D6:D17) | E18: =SUM(E6:E17) | F18: =SUM(F6:F17) | G18: =SUM(G6:G17) | I18: =SUM(I6:I17) | J18: =SUM(J6:J17) | O18: =IF(COUNTIF(O6:O17,"✗*")=0,"✓ Agrees","✗ Investigate")
A20: Penalties shown are indicative estimates only (5% of unpaid tax per month or part). ZATCA may also apply late-filing (5%–25%) and incorrect-return (50% of the difference) penalties – see Dashboard and Inspection_Guide.

Sheet Inspection_Guide
A1: ZATCA VAT Inspection – Practical Guide
A2: Rules summarised from the KSA VAT Law & Implementing Regulations. Confirm current rates, penalties and deadlines with ZATCA or your advisor before relying on them.
A4: HOW TO USE THIS WORKBOOK
A5: 1 | B5: Setup: enter company details, the audit year start date and filing frequency. Periods generate automatically.
A6: 2 | B6: TB_Monthly: paste opening balances and monthly net movements (Dr +, Cr −). Map EVERY account in column D – this drives all GL reconciliations.
A7: 3 | B7: VAT_Returns: copy every filed return box-by-box from the ZATCA portal, including filing date. Check columns AS–AU.
A8: 4 | B8: Sales_Register / Purchase_Register: export invoice-level data from the ERP or FATOORA. For very high volumes (POS), use daily summary lines per VAT category.
A9: 5 | B9: ZATCA_Payments: enter each SADAD payment and any refunds (negative).
A10: 6 | B10: Work through every ✗ on Recon_Sales, Recon_OutputVAT, Recon_InputVAT and Recon_VAT_Account. Document each explanation.
A11: 7 | B11: Use the Checklist to collect evidence; the Dashboard shows overall readiness and indicative exposure.
A12: WHAT ZATCA TYPICALLY TESTS
A13: • | B13: Revenue in audited financial statements / Zakat return vs total sales in VAT returns (the #1 test).
A14: • | B14: Bank receipts vs declared sales; customs import data vs Box 8; withholding-tax returns vs Box 9 (reverse charge).
A15: • | B15: Zero-rated and export sales: proof the goods left KSA (customs exit) or the service conditions were met.
A16: • | B16: Input VAT: valid tax invoice in the company's name with a valid supplier VAT number; no blocked items.
A17: • | B17: Credit notes: valid reason, issued correctly, linked to the original invoice.
A18: • | B18: Deemed supplies: gifts, samples, own use, staff benefits, asset write-offs.
A19: • | B19: E-invoicing: invoices generated/cleared/reported through a compliant solution with required fields and QR code.
A20: • | B20: Timeliness of filing and payment; use of Box 14 above the SAR 5,000 limit.
A21: COMMON FINDINGS IN KSA VAT AUDITS
A22: • | B22: Revenue booked in GL but not declared (accruals, other income, recharges, asset sales).
A23: • | B23: Exports zero-rated without exit evidence → reassessed at 15%.
A24: • | B24: Input VAT claimed on invoices without supplier VAT number, in another entity's name, or on simplified invoices above limits.
A25: • | B25: Reverse charge not applied on foreign services (consulting, software, royalties, management fees).
A26: • | B26: Customs VAT claimed where the company is not the importer of record.
A27: • | B27: Blocked input VAT claimed: entertainment, hospitality, private-use vehicles, staff personal benefits.
A28: • | B28: Errors above SAR 5,000 corrected through Box 14 instead of a voluntary disclosure.
A29: KEY RULES & PENALTIES (verify current position)
A30: Filing | B30: Monthly if taxable supplies exceed SAR 40 million a year, otherwise quarterly. Return and payment due by the last day of the following month.
A31: Late filing | B31: 5% to 25% of the tax due (VAT Law Art. 43).
A32: Late payment | B32: 5% of the unpaid tax for each month or part of a month (VAT Law Art. 43).
A33: Incorrect return | B33: 50% of the difference between the tax calculated and the tax due (VAT Law Art. 42).
A34: Tax evasion | B34: Up to three times the value of the goods or services concerned (VAT Law Art. 40).
A35: Corrections | B35: Net errors above SAR 5,000 → voluntary disclosure (within 20 days of discovery). Errors up to SAR 5,000 can be corrected in Box 14 of the next return.
A36: Records | B36: Keep records at least 6 years; capital assets 11 years; real estate 15 years.
A37: Assessment window | B37: ZATCA can generally assess within 5 years from the end of the tax period (10 years where no return was filed or in cases of evasion).
A38: Objection | B38: File an objection against an assessment within the statutory deadline (currently 60 days from notification – verify), then escalate to the GSTC committees if needed.
A39: Relief | B39: Check whether a ZATCA penalty-waiver / amnesty initiative is currently active – these have been extended several times.
A40: RESPONSE TIPS
A41: • | B41: Answer only what is requested, in writing, within the deadline in the ZATCA notice; ask for an extension in writing if needed.
A42: • | B42: Never submit a reconciliation with unexplained differences – fix or explain every ✗ first.
A43: • | B43: Keep one index of everything submitted (Checklist col H) and the date it was sent.
A44: • | B44: If you find an error before ZATCA does, assess whether a voluntary disclosure reduces the penalty.
A45: • | B45: Get your tax advisor to review the pack before submission.

Sheet Lists
A1: Sales VAT Category | B1: Purchase VAT Category | C1: TB VAT Mapping | D1: Document Type | E1: Customer Type | F1: Expense Nature | G1: Yes/No | H1: Checklist Status | I1: FS Class | J1: Filing Frequency
A2: Standard 15% (Box 1) | B2: Standard domestic 15% (Box 7) | C2: Standard 15% (Box 1) | D2: Tax Invoice | E2: B2B - VAT registered | F2: General business expense | G2: Yes | H2: Not started | I2: Asset | J2: Monthly
A3: Citizens - Healthcare/Education (Box 2) | B3: Import - VAT paid at customs (Box 8) | C3: Citizens - Healthcare/Education (Box 2) | D3: Simplified Tax Invoice | E3: B2B - Not registered | F3: Capital asset | G3: No | H3: In progress | I3: Liability | J3: Quarterly
A4: Zero-rated domestic (Box 3) | B4: Import - Reverse charge (Box 9) | C4: Zero-rated domestic (Box 3) | D4: Credit Note | E4: B2C - Individual | F4: Entertainment / hospitality (blocked) | H4: Ready | I4: Equity
A5: Export (Box 4) | B5: Zero-rated purchase (Box 10) | C5: Export (Box 4) | D5: Debit Note | E5: Government | F5: Motor vehicle - private use (blocked) | H5: Submitted | I5: Revenue
A6: Exempt (Box 5) | B6: Exempt purchase (Box 11) | C6: Exempt (Box 5) | F6: Staff personal benefit (blocked) | H6: N/A | I6: Expense
A7: Out of scope | B7: Out of scope / Not reported | C7: Revenue - Out of scope / Other income | F7: Other non-business (blocked)
C8: Output VAT
C9: Input VAT
C10: VAT Payable / Settlement
C11: Not VAT relevant
